Workbook
Name Eno_TM: '[1]1997 Table 1a Modified'!#REF!
Name Eno_TM: '[2]1997 Table 1a Modified'!#REF!
Name Eno_TM: '[1]1997 Table 1a Modified'!#REF!
Name Eno_Tons: '[1]1997 Table 1a Modified'!#REF!
Name Eno_Tons: '[2]1997 Table 1a Modified'!#REF!
Name Eno_Tons: '[1]1997 Table 1a Modified'!#REF!
Name NTS_YR: [3]About!$B$136
Name Sum_T2: '[1]1997 Table 1a Modified'!#REF!
Name Sum_T2: '[2]1997 Table 1a Modified'!#REF!
Name Sum_T2: '[1]1997 Table 1a Modified'!#REF!
Name Sum_TTM: '[1]1997 Table 1a Modified'!#REF!
Name Sum_TTM: '[2]1997 Table 1a Modified'!#REF!
Name Sum_TTM: '[1]1997 Table 1a Modified'!#REF!
Name ti_tbl_50: #REF!
Name ti_tbl_50: #REF!
Name ti_tbl_50: #REF!
Name ti_tbl_69: #REF!
Name ti_tbl_69: #REF!
Name ti_tbl_69: #REF!

Sheet About
A1: BCDTRtSY BAU Cargo Dist Transported Relative to Start Year | B1: Virginia | C1: 46248 | H1: State | I1: Abbr.
B2: =VLOOKUP(B1,H2:I52,2) -> VA | H2: Alabama | I2: AL
A3: Sources: | B3: See Notes section for which vehicle types use which sources | H3: Alaska | I3: AK
B4: EIA | H4: Arizona | I4: AZ
B5: 2025, 2026 | H5: Arkansas | I5: AR
B6: Annual Energy Outlook | H6: California | I6: CA
B7: Alternative Electricity and Transportation | H7: Colorado | I7: CO
B8: https://www.eia.gov/outlooks/aeo/tables_side.php | H8: Connecticut | I8: CT
B9: Tables 7, 36, 46, 47, 49 | H9: Delaware | I9: DE
H10: Florida | I10: FL
B11: Bus adjustment factor, 2020-2025 | H11: Georgia | I11: GA
B12: EPA | H12: Hawaii | I12: HI
B13: 2022 | H13: Idaho | I13: ID
B14: Inventory of U.S. Greenhouse Gas Emissions and Sinks: 1990-2020 | H14: Illinois | I14: IL
B15: https://www.epa.gov/ghgemissions/inventory-us-greenhouse-gas-emissions-and-sinks-1990-2020 | H15: Indiana | I15: IN
B16: Table 3-13 | H16: Iowa | I16: IA
H17: Kansas | I17: KS
A18: Notes | H18: Kentucky | I18: KY
A19: This variable contains ratios of cargo distance transported in each year of the | H19: Louisiana | I19: LA
A20: model run relative to the start year. The start year is the year before the | H20: Maine | I20: ME
A21: first simulated year. So if the first year for which the model outputs data | H21: Maryland | I21: MD
A22: is 2020, the start year is 2019. The start year column does not have to be | H22: Massachusetts | I22: MA
A23: included in the outputs but is retained here for visual clarity. | H23: Michigan | I23: MI
A24: We use AEO 2021 to calculate start year vehicles, as AEO 2021 does not include 2019 data. | H24: Minnesota | I24: MN
H25: Mississippi | I25: MS
A26: We scale by passenger-miles, freight ton-miles, or vehicle-miles where available. | H26: Missouri | I26: MO
A27: (We assume vehicle loading remains constant, so scaling by vehicle-miles is | H27: Montana | I27: MT
A28: identical to scaling by passenger-miles or freight ton-miles.) | H28: Nebraska | I28: NE
H29: Nevada | I29: NV
A30: We classify AEO's light commercial trucks category as well as light-medium and medium duty vehicles | H30: New Hampshire | I30: NH
A31: in "freight LDVs" and heavy duty vehicles in "freight HDVs." | H31: New Jersey | I31: NJ
A32: 2026-08-14: re-anchored to 2025 = 1 on AEO 2026 alone (was mixed AEO2025/AEO2026, which put the editions' level re-benchmark into 2025 as a fake -5.7% LDV travel drop). Population adjustment re-anchored 2024 -> 2025 to match. Approved by Olivia 2026-08-14. | H32: New Mexico | I32: NM
A33: Without any calibration adjustment, the very large dip in passenger air travel in 2020 leads to discrepancies | H33: New York | I33: NY
A34: in energy use between AEO and the EPS outputs given our current methodology. Therefore, we add a calibration | H34: North Carolina | I34: NC
A35: adjustment factor here, which adjusts the BAU aircraft cargo distance so that final aircraft energy use aligns | H35: North Dakota | I35: ND
A36: with the energy use in AEO 2021. | H36: Ohio | I36: OH
H37: Oklahoma | I37: OK
A38: For buses, we choose to use the EPA GHG Inventory to calculate the 2020 value, due to the fact the Inventory | H38: Oregon | I38: OR
A39: reports only a ~20% drop in emissions from buses vs. the AEO which reports a ~50% drop. We then scale back | H39: Pennsylvania | I39: PA
A40: up to AEO values over a period of 5 years. | H40: Rhode Island | I40: RI
H41: South Carolina | I41: SC
H42: South Dakota | I42: SD
H43: template | I43: National data for template (added)
A44: Active state name: | H44: Tennessee | I44: TN
H45: Texas | I45: TX
A46: What the state adjustment does | H46: Utah | I46: UT
A47: BCDTRtSY-psgr / BCDTRtSY-frgt (original IA tabs): one national growth curve, applied to every state. | H47: Vermont | I47: VT
A48: BCDTRtSY-state-adjusted (new tab): same national curve × (state pop growth / national pop growth). | H48: Virginia | I48: VA
H49: Washington | I49: WA
A50: Formula per cell: | H50: West Virginia | I50: WV
A51: state_adjusted[mode, year] = national_BCDTRtSY[mode, year] | H51: Wisconsin | I51: WI
A52: × (state_pop[year] / state_pop[2024]) | H52: Wyoming | I52: WY
A53: / (US_pop[year] / US_pop[2024])
A55: States projected to grow faster than national average (TX, AZ, FL, etc.) → multiplier > 1.
A56: Slower-growth states (WV, IL, CT) → multiplier < 1.
A57: 2024 = 1.000 by definition (start year).
A59: Population sources:
A60: • 2024–2025: Census Bureau NST-EST2025-POP (annual estimates)
A61: • 2026–2029: linear interpolation Census 2025 → Cooper 2030
A62: • 2030, 2040, 2050: UVA Weldon Cooper Center state projections (released July 2024)
A63: • 2031–2039, 2041–2049: linear interpolation between Cooper anchor years
A65: Per organizational guidance: framing as inputs for staff review. Population projections
A66: should be verified against primary sources before external use.

Sheet Sources
A1: Source citations
A2: Compiled from docs/methodology/*.md and builder scripts. Built 2026-06-04. Per organizational guidance: framed as inputs for staff review. Staff should verify every URL and version against the primary source before incorporating these citations in published work.
A4: 1 | B4: Energy Innovation (internal)
B5: IA reference workbook BCDTRtSY — BAU Cargo Distance Transported Relative to Start Year (national growth curves)
B6: internal eps-us repo: InputData/trans/BCDTRtSY/
B7: BAU Cargo Dist Transported Relative to Start Yr.xlsx — EPS US baseline snapshot, TBD: confirm EPS version with staff
A9: 2 | B9: EIA
B10: Annual Energy Outlook 2026 — Transportation Tables 7, 35, 45, 47, 49 (national growth-rate sources)
B11: https://www.eia.gov/outlooks/aeo/
B12: Tables 7 (Travel Indicators), 35 (Energy Use by Mode), 45 (Car Stock), 47 (Air Travel), 49 (Freight Truck) — embedded verbatim in workbook, April 2026
A14: 3 | B14: EIA
B15: Annual Energy Outlook 2025 — Transportation Tables 7, 35, 45–49 (legacy IA references)
B16: https://www.eia.gov/outlooks/aeo/
B17: Tables 7, 35, 45, 46, 47, 49 — embedded verbatim in workbook (from IA reference, December 2025 release)
A19: 4 | B19: EPA
B20: Inventory of U.S. Greenhouse Gas Emissions and Sinks, Table 3-13 — Transportation Fuel Use by Vehicle Type
B21: https://www.epa.gov/ghgemissions/inventory-us-greenhouse-gas-emissions-and-sinks
B22: EPA GHG Inventory (2022 reporting year, embedded verbatim in IA reference)
A24: 5 | B24: Census Bureau
B25: State Population Totals — Vintage 2025 (NST-EST2025-POP)
B26: https://www.census.gov/programs-surveys/popest/data/tables.html
B27: NST-EST2025-POP.xlsx (annual estimates 2020–2025)
A29: 6 | B29: University of Virginia Weldon Cooper Center for Public Service
B30: National Population Projections (state-level, 2020 base)
B31: https://www.coopercenter.org/national-population-projections
B32: NationalProjections_ProjectedTotalPopulation_2030-2050.xlsx (released July 2024)

Sheet source data>

Sheet EPA_Table 3-13
A1: Table 3-13: CO2 Emissions from Fossil Fuel Combustion in Transportation End-Use Sector (MMT CO2 Eq.)
A3: Fuel/Vehicle Type | B3: 2020 | C3: 2021 | G3: 2021 to 2020 growth rate
A4: Gasolinea | B4: 937 | C4: 1029 | F4: Buses | G4: =SUM(C8,C15,C35,C41,C45)/SUM(B45,B41,B35,B15,B8) -> 1.0416667
A5: Passenger Cars | B5: 328 | C5: 361
A6: Light-Duty Trucks | B6: 566 | C6: 620
A7: Medium- and Heavy-Duty Trucksb | B7: 24 | C7: 27
A8: Buses | B8: 3 | C8: 3
A9: Motorcycles | B9: 7 | C9: 7
A10: Recreational Boatsc | B10: 10 | C10: 11
A11: Distillate Fuel Oil (Diesel)a | B11: 455 | C11: 488
A12: Passenger Cars | B12: 3 | C12: 3
A13: Light-Duty Trucks | B13: 30 | C13: 33
A14: Medium- and Heavy-Duty Trucksb | B14: 353 | C14: 380
A15: Buses | B15: 20 | C15: 21
A16: Rail | B16: 31 | C16: 32
... A50: Biofuels-Biodieselh | B50: 17.7 | C50: 16.1
A51: + Does not exceed 0.05 MMT CO2 Eq.
A52: a On-road fuel consumption data from FHWA Table MF-21 and MF-27 were used to determine total on-road use of motor gasoline and diesel fuel (FHWA 1996 through 2023). Ratios developed from MOVES3 output are used to apportion FHWA fuel consumption data to vehicle type and fuel type (see Annex 3.2 for information about the MOVES model).
A53: b Includes medium- and heavy-duty trucks over 8,500 lbs.
A54: c In 2014, EPA incorporated the NONROAD2008 model into the MOVES model framework. The current Inventory uses the Nonroad component of MOVES3 for years 1999 through 2021. See Annex 3.2 for information about the MOVES model.
A55: d Note that large year over year fluctuations in emission estimates partially reflect nature of data collection for these sources.
A56: e Official estimates exclude emissions from the combustion of both aviation and marine international bunker fuels; however, estimates of international bunker fuel-related emissions are presented for informational purposes.
A57: f Commercial aircraft, as modeled in FAA’s Aviation Environmental Design Tool (AEDT), consists of passenger aircraft, cargo, and other chartered flights.
A58: g Pipelines reflect CO2 emissions from natural gas-powered pipelines transporting natural gas.
A59: h Ethanol and biodiesel estimates are presented for informational purposes only. See Section 3.10 of this chapter and the estimates in Land Use, Land-Use Change, and Forestry (see Chapter 6), in line with IPCC methodological guidance and UNFCCC reporting obligations, for more information on ethanol and biodiesel.
A60: i Transportation sector natural gas and LPG consumption are based on data from EIA (2021b). Prior to the 1990 to 2015 Inventory, data from DOE TEDB were used to estimate each vehicle class’s share of the total natural gas and LPG consumption. Since TEDB does not include estimates for natural gas use by medium and heavy-duty trucks or LPG use by passenger cars, EIA Alternative Fuel Vehicle Data (Browning 2017) is now used to determine each vehicle class’s share of the total natural gas and LPG consumption. These changes were first incorporated in the 1990 to 2016 Inventory and apply to the 1990 to 2021 time period.
A61: j Includes emissions from rail electricity.
A62: k Electricity consumption by passenger cars, light-duty trucks (SUVs), and buses is based on plug-in electric vehicle sales and engine efficiency data, as outlined in Browning (2018a). In prior Inventory years, CO2 emissions from electric vehicle charging were allocated to the residential and commercial sectors. They are now allocated to the transportation sector. These changes apply to the 2010 through 2021 time period.
A63: Notes: This table does not include emissions from non-transportation mobile sources, such as agricultural equipment and construction/mining equipment; it also does not include emissions associated with electricity consumption by pipelines or lubricants used in transportation. In addition, this table does not include CO2 emissions from U.S. Territories, since these are covered in a separate chapter of the Inventory. Totals may not sum due to independent rounding.

Sheet AEO 2025 Table 7
A1: Table 7. Transportation Sector Key Indicators and Delivered Energy Consumption
A2: https://www.eia.gov/outlooks/aeo/data/browser/#/?id=7-AEO2025&cases=alttrnp&sourcekey=0
A3: Fri Dec 05 2025 14:42:41 GMT-0800 (Pacific Standard Time)
A4: Source: U.S. Energy Information Administration
B5: full name | C5: api key | D5: units | E5: 2023 | F5: 2024 | G5: 2025 | H5: 2026 | I5: 2027 | J5: 2028 | K5: 2029 | L5: 2030 | M5: 2031 | N5: 2032 | O5: 2033 | P5: 2034 | Q5: 2035 | R5: 2036 | S5: 2037 | T5: 2038 | U5: 2039 | V5: 2040 | W5: 2041 | X5: 2042 | Y5: 2043 | Z5: 2044 | AA5: 2045 | AB5: 2046 | AC5: 2047 | AD5: 2048 | AE5: 2049 | AF5: 2050 | AG5: Growth (2024-2050)
A6: Key Indicators
A7: Travel Indicators
A8: (billion vehicle miles traveled)
A9: Light-Duty Vehicles less than 8 | B9: 501 pounds | C9: Transportation: Travel Indicators: Light-Duty Vehicles <= 8,500 lbs: Alternative Transportation | D9: AEO.2025.ALTTRNP.KEI_TRV_TRN_NA_LDV_NA_NA_BLNVEHMLS.A | E9: billion vehicle miles | F9: 3013.7297 | G9: 3058.3716 | H9: 3083.4512 | I9: 3100.0171 | J9: 3112.2297 | K9: 3125.5762 | L9: 3140.167 | M9: 3154.0073 | N9: 3161.4351 | O9: 3167.1465 | P9: 3171.917 | Q9: 3174.3567 | R9: 3179.4163 | S9: 3189.5078 | T9: 3202.9607 | U9: 3216.1187 | V9: 3230.5129 | W9: 3244.2317 | X9: 3257.2742 | Y9: 3268.8367 | Z9: 3279.3418 | AA9: 3288.4412 | AB9: 3297.5173 | AC9: 3308.5703 | AD9: 3321.3464 | AE9: 3335.0469 | AF9: 3349.864 | AG9: 0.004
A10: Commercial Light Trucks | B10: Transportation: Travel Indicators: Commercial Light Trucks: Alternative Transportation | C10: AEO.2025.ALTTRNP.KEI_TRV_TRN_NA_CML_NA_NA_BLNVEHMLS.A | D10: billion vehicle miles | F10: 90.234665 | G10: 88.746048 | H10: 87.524918 | I10: 86.879402 | J10: 86.146126 | K10: 85.551414 | L10: 85.088478 | M10: 84.55584 | N10: 84.013214 | O10: 83.542664 | P10: 83.043007 | Q10: 82.538109 | R10: 82.013916 | S10: 81.499672 | T10: 80.976738 | U10: 80.459801 | V10: 79.954575 | W10: 79.410118 | X10: 78.884186 | Y10: 78.326515 | Z10: 77.80687 | AA10: 77.239433 | AB10: 76.680191 | AC10: 76.081207 | AD10: 75.451775 | AE10: 74.792137 | AF10: 74.117767 | AG10: -0.008
A11: Freight Trucks greater than 10 | B11: 000 pounds | C11: Transportation: Travel Indicators: Freight Trucks > 10,000 lbs.: Alternative Transportation | D11: AEO.2025.ALTTRNP.KEI_TRV_TRN_NA_FGHT_NA_NA_BLNVEHMLS.A | E11: billion vehicle miles | F11: 340.05481 | G11: 346.20789 | H11: 350.06781 | I11: 353.52682 | J11: 356.01294 | K11: 358.95523 | L11: 362.11615 | M11: 364.84686 | N11: 367.715 | O11: 370.28033 | P11: 373.22687 | Q11: 376.19421 | R11: 379.62561 | S11: 383.28888 | T11: 386.97992 | U11: 390.32495 | V11: 393.89111 | W11: 397.25488 | X11: 400.59506 | Y11: 403.50134 | Z11: 406.14972 | AA11: 409.08057 | AB11: 411.83875 | AC11: 416.01117 | AD11: 420.09766 | AE11: 423.84226 | AF11: 427.05206 | AG11: 0.009
A12: (billion passenger miles traveled)
A13: Bus Transportation | B13: Transportation: Travel Indicators: Bus: Alternative Transportation | C13: AEO.2025.ALTTRNP.KEI_TRV_TRN_NA_BST_NA_NA_BPM.A | D13: billion passenger miles | F13: 190.78021 | G13: 196.63762 | H13: 200.38203 | I13: 202.76497 | J13: 204.50441 | K13: 205.76622 | L13: 206.65466 | M13: 207.15369 | N13: 207.40228 | O13: 207.54491 | P13: 207.69394 | Q13: 207.71609 | R13: 207.67081 | S13: 207.61053 | T13: 207.42905 | U13: 207.19026 | V13: 206.88676 | W13: 206.52594 | X13: 206.10233 | Y13: 205.65778 | Z13: 205.15973 | AA13: 204.65633 | AB13: 204.09099 | AC13: 203.49281 | AD13: 202.89883 | AE13: 202.30595 | AF13: 201.76945 | AG13: 0.002
A14: Passenger Rail | B14: Transportation: Travel Indicators: Passenger Rail: Alternative Transportation | C14: AEO.2025.ALTTRNP.KEI_TRV_TRN_NA_RLP_NA_NA_BPM.A | D14: billion passenger miles | F14: 25.878023 | G14: 28.773293 | H14: 30.990028 | I14: 32.691128 | J14: 34.018692 | K14: 35.161125 | L14: 36.109001 | M14: 36.852859 | N14: 37.463329 | O14: 37.9645 | P14: 38.458427 | Q14: 38.854378 | R14: 39.233795 | S14: 39.64349 | T14: 40.072304 | U14: 40.454437 | V14: 40.811695 | W14: 41.128437 | X14: 41.427906 | Y14: 41.717632 | Z14: 41.951229 | AA14: 42.199917 | AB14: 42.38929 | AC14: 42.61396 | AD14: 42.893345 | AE14: 43.173431 | AF14: 43.548084 | AG14: 0.02
A15: (billion seat miles available)
A16: Air | B16: Transportation: Travel Indicators: Air: Alternative Transportation | C16: AEO.2025.ALTTRNP.KEI_TRV_TRN_NA_AIR_NA_NA_BLNSEATMLS.A | D16: billion seat miles | F16: 1413.1366 | G16: 1426.5015 | H16: 1461.8976 | I16: 1494.7886 | J16: 1522.1002 | K16: 1551.6201 | L16: 1578.683 | M16: 1601.1815 | N16: 1627.1464 | O16: 1654.8922 | P16: 1681.6215 | Q16: 1711.0176 | R16: 1740.9607 | S16: 1772.7719 | T16: 1806.9364 | U16: 1841.1686 | V16: 1875.4396 | W16: 1909.1254 | X16: 1945.6185 | Y16: 1981.347 | Z16: 2014.7141 | AA16: 2047.4543 | AB16: 2079.6472 | AC16: 2117.3379 | AD16: 2157.5337 | AE16: 2196.0696 | AF16: 2234.0925 | AG16: 0.018
A17: (billion ton miles traveled)
A18: Rail | B18: Transportation: Travel Indicators: Rail: Alternative Transportation | C18: AEO.2025.ALTTRNP.KEI_TRV_TRN_NA_RAIL_NA_NA_BLNTNMLS.A | D18: billion ton miles | F18: 1464.8552 | G18: 1498.5776 | H18: 1462.3732 | I18: 1413.7332 | J18: 1414.1151 | K18: 1410.5652 | L18: 1369.7415 | M18: 1370.1805 | N18: 1305.8112 | O18: 1312.2113 | P18: 1299.8524 | Q18: 1300.421 | R18: 1305.7511 | S18: 1312.3923 | T18: 1330.2866 | U18: 1321.975 | V18: 1328.3295 | W18: 1330.2947 | X18: 1337.3475 | Y18: 1345.2047 | Z18: 1349.7686 | AA18: 1354.5587 | AB18: 1355.686 | AC18: 1370.3556 | AD18: 1382.5275 | AE18: 1392.7019 | AF18: 1397.2123 | AG18: -0.002
A19: Domestic Shipping | B19: Transportation: Travel Indicators: Domestic Shipping: Alternative Transportation | C19: AEO.2025.ALTTRNP.KEI_TRV_TRN_NA_DMT_NA_NA_BLNTNMLS.A | D19: billion ton miles | F19: 458.77335 | G19: 464.89285 | H19: 462.96167 | I19: 460.98572 | J19: 459.37042 | K19: 457.35059 | L19: 454.85974 | M19: 451.94983 | N19: 448.2905 | O19: 446.2366 | P19: 444.57028 | Q19: 442.67673 | R19: 440.63129 | S19: 439.09964 | T19: 437.71414 | U19: 435.98474 | V19: 434.76898 | W19: 433.49097 | X19: 432.2272 | Y19: 430.6734 | Z19: 428.80133 | AA19: 427.06717 | AB19: 425.276 | AC19: 424.65442 | AD19: 423.51385 | AE19: 422.14224 | AF19: 420.62109 | AG19: -0.003 | AH19: =AF19/F19 -> 0.91683856
A20: Energy Efficiency Indicators
A21: (miles per gallon)
A22: New Light-Duty Vehicle CAFE Standard | B22: Transportation: Energy Efficiency Indicators: CAFE Standard: New Light-Duty Vehicle: Alternative Transportation | C22: AEO.2025.ALTTRNP.EFI_CAFES_TRN_HWY_LDTY_NEW_NA_MLSPGLN.A | D22: mpg | F22: 39.271114 | G22: 42.959927 | H22: 47.575771 | I22: 47.493256 | J22: 47.449085 | K22: 47.490925 | L22: 47.59132 | M22: 47.604393 | N22: 47.569965 | O22: 47.492599 | P22: 47.679401 | Q22: 47.648468 | R22: 47.59169 | S22: 47.590065 | T22: 47.59457 | U22: 47.597126 | V22: 47.557652 | W22: 47.536556 | X22: 47.522251 | Y22: 47.527641 | Z22: 47.509605 | AA22: 47.515839 | AB22: 47.499699 | AC22: 47.476486 | AD22: 47.471779 | AE22: 47.466419 | AF22: 47.51144 | AG22: 0.007
A23: New Car | B23: Transportation: Energy Efficiency Indicators: CAFE Standard: New Car: Alternative Transportation | C23: AEO.2025.ALTTRNP.EFI_CAFES_TRN_HWY_CAR_NEW_NA_MLSPGLN.A | D23: mpg | F23: 48.175083 | G23: 52.414536 | H23: 58.241451 | I23: 58.255463 | J23: 58.26667 | K23: 58.284412 | L23: 58.290977 | M23: 58.296238 | N23: 58.292618 | O23: 58.297882 | P23: 58.32222 | Q23: 58.317551 | R23: 58.313091 | S23: 58.312267 | T23: 58.318325 | U23: 58.320648 | V23: 58.313702 | W23: 58.314289 | X23: 58.312122 | Y23: 58.322739 | Z23: 58.317924 | AA23: 58.327766 | AB23: 58.321186 | AC23: 58.318832 | AD23: 58.325527 | AE23: 58.327377 | AF23: 58.347694 | AG23: 0.007
A24: New Light Truck | B24: Transportation: Energy Efficiency Indicators: CAFE Standard: New Light Truck: Alternative Transportation | C24: AEO.2025.ALTTRNP.EFI_CAFES_TRN_HWY_LTRT_NEW_NA_MLSPGLN.A | D24: mpg | F24: 35.086903 | G24: 38.087925 | H24: 42.293404 | I24: 42.265976 | J24: 42.251019 | K24: 42.23045 | L24: 42.21875 | M24: 42.207088 | N24: 42.198193 | O24: 42.188656 | P24: 42.178352 | Q24: 42.170338 | R24: 42.163197 | S24: 42.15712 | T24: 42.150414 | U24: 42.144039 | V24: 42.139084 | W24: 42.13335 | X24: 42.127731 | Y24: 42.121071 | Z24: 42.115974 | AA24: 42.109615 | AB24: 42.105438 | AC24: 42.100983 | AD24: 42.095028 | AE24: 42.089645 | AF24: 42.083157 | AG24: 0.007
A25: Compliance New Light-Duty Vehicle | B25: Transportation: Energy Efficiency Indicators: Compliance: New Light-Duty Vehicle: Alternative Transportation | C25: AEO.2025.ALTTRNP.EFI_CAFEC_TRN_HWY_LDTY_NEW_NA_MLSPGLN.A | D25: mpg | F25: 39.942822 | G25: 43.957706 | H25: 47.924385 | I25: 48.168633 | J25: 48.206814 | K25: 47.845936 | L25: 47.905159 | M25: 48.590633 | N25: 49.493092 | O25: 48.658333 | P25: 49.540321 | Q25: 50.266624 | R25: 50.779812 | S25: 51.219345 | T25: 51.674301 | U25: 52.231579 | V25: 52.558426 | W25: 52.808189 | X25: 52.984974 | Y25: 53.223259 | Z25: 53.34993 | AA25: 53.548645 | AB25: 53.65453 | AC25: 53.715496 | AD25: 53.847446 | AE25: 53.972466 | AF25: 54.298809 | AG25: 0.012
A26: New Car | B26: Transportation: Energy Efficiency Indicators: Compliance: New Car: Alternative Transportation | C26: AEO.2025.ALTTRNP.EFI_CAFEC_TRN_HWY_CAR_NEW_NA_MLSPGLN.A | D26: mpg | F26: 53.113453 | G26: 57.640594 | H26: 63.3256 | I26: 68.261688 | J26: 68.800171 | K26: 66.58007 | L26: 66.17157 | M26: 67.334129 | N26: 70.141273 | O26: 69.02169 | P26: 70.175095 | Q26: 72.345963 | R26: 73.417397 | S26: 74.362701 | T26: 75.273003 | U26: 76.767471 | V26: 77.966553 | W26: 78.546875 | X26: 79.005653 | Y26: 79.448586 | Z26: 79.81424 | AA26: 80.153214 | AB26: 80.456696 | AC26: 80.688454 | AD26: 80.951462 | AE26: 81.205383 | AF26: 81.537048 | AG26: 0.017
A27: New Light Truck | B27: Transportation: Energy Efficiency Indicators: Compliance: New Light Truck: Alternative Transportation | C27: AEO.2025.ALTTRNP.EFI_CAFEC_TRN_HWY_LTRT_NEW_NA_MLSPGLN.A | D27: mpg | F27: 34.459515 | G27: 37.642277 | H27: 41.127472 | I27: 40.267258 | J27: 40.25531 | K27: 40.242519 | L27: 40.218754 | M27: 40.700054 | N27: 41.130524 | O27: 40.5546 | P27: 40.930511 | Q27: 41.310795 | R27: 41.765965 | S27: 42.053349 | T27: 42.351562 | U27: 42.643215 | V27: 42.837719 | W27: 43.033184 | X27: 43.158432 | Y27: 43.308086 | Z27: 43.407925 | AA27: 43.533504 | AB27: 43.621685 | AC27: 43.68882 | AD27: 43.782269 | AE27: 43.872547 | AF27: 44.049908 | AG27: 0.009
A28: Tested New Light-Duty Vehicle | B28: Transportation: Energy Efficiency Indicators: Tested: New Light-Duty Vehicle: Alternative Transportation | C28: AEO.2025.ALTTRNP.EFI_CAFET_TRN_HWY_LDTY_NEW_NA_MLSPGLN.A | D28: mpg | F28: 36.992214 | G28: 40.049953 | H28: 42.808971 | I28: 43.230892 | J28: 44.016903 | K28: 44.308899 | L28: 44.989899 | M28: 45.61496 | N28: 46.454155 | O28: 45.667557 | P28: 46.478081 | Q28: 47.149429 | R28: 47.616024 | S28: 48.020485 | T28: 48.435196 | U28: 48.949013 | V28: 49.253231 | W28: 49.479267 | X28: 49.642773 | Y28: 49.856163 | Z28: 49.976059 | AA28: 50.153816 | AB28: 50.256393 | AC28: 50.313774 | AD28: 50.431538 | AE28: 50.545406 | AF28: 50.836014 | AG28: 0.012
A29: New Car | B29: Transportation: Energy Efficiency Indicators: Tested: New Car: Alternative Transportation | C29: AEO.2025.ALTTRNP.EFI_CAFET_TRN_HWY_CAR_NEW_NA_MLSPGLN.A | D29: mpg | F29: 48.381924 | G29: 51.754009 | H29: 55.653797 | I29: 59.137737 | J29: 61.278339 | K29: 61.308632 | L29: 62.88327 | M29: 63.968285 | N29: 66.642883 | O29: 65.576897 | P29: 66.66021 | Q29: 68.722473 | R29: 69.727547 | S29: 70.61306 | T29: 71.466324 | U29: 72.886696 | V29: 74.021286 | W29: 74.5662 | X29: 74.998436 | Y29: 75.41684 | Z29: 75.761993 | AA29: 76.083054 | AB29: 76.370346 | AC29: 76.590515 | AD29: 76.839706 | AE29: 77.080559 | AF29: 77.395805 | AG29: 0.018
A30: New Light Truck | B30: Transportation: Energy Efficiency Indicators: Tested: New Light Truck: Alternative Transportation | C30: AEO.2025.ALTTRNP.EFI_CAFET_TRN_HWY_LTRT_NEW_NA_MLSPGLN.A | D30: mpg | F30: 32.114288 | G30: 34.514839 | H30: 36.986862 | I30: 36.634201 | J30: 37.092926 | K30: 37.343777 | L30: 37.577011 | M30: 38.011017 | N30: 38.403038 | O30: 37.869068 | P30: 38.209908 | Q30: 38.555424 | R30: 38.963661 | S30: 39.224598 | T30: 39.495064 | U30: 39.75996 | V30: 39.93721 | W30: 40.114799 | X30: 40.230305 | Y30: 40.36813 | Z30: 40.460381 | AA30: 40.576187 | AB30: 40.657494 | AC30: 40.719509 | AD30: 40.805653 | AE30: 40.888672 | AF30: 41.051575 | AG30: 0.009
A31: On-Road New Light-Duty Vehicle | B31: Transportation: Energy Efficiency Indicators: On-Road New Light-Duty Vehicle: Alternative Transportation | C31: AEO.2025.ALTTRNP.EFI_CAFEO_TRN_HWY_LDTY_NEW_NA_MLSPGLN.A | D31: mpg | F31: 27.538565 | G31: 29.747971 | H31: 31.720669 | I31: 32.058968 | J31: 32.641983 | K31: 32.859589 | L31: 33.335556 | M31: 33.78616 | N31: 34.398438 | O31: 33.841164 | P31: 34.423504 | Q31: 34.90659 | R31: 35.2328 | S31: 35.521309 | T31: 35.816288 | U31: 36.185467 | V31: 36.402821 | W31: 36.561584 | X31: 36.675686 | Y31: 36.824799 | Z31: 36.907936 | AA31: 37.031731 | AB31: 37.102467 | AC31: 37.140446 | AD31: 37.221237 | AE31: 37.299519 | AF31: 37.503345 | AG31: 0.012
A32: New Car | B32: Transportation: Energy Efficiency Indicators: On-Road New Car: Alternative Transportation | C32: AEO.2025.ALTTRNP.EFI_CAFEO_TRN_HWY_CAR_NEW_NA_MLSPGLN.A | D32: mpg | F32: 35.736515 | G32: 38.187515 | H32: 41.026562 | I32: 43.567795 | J32: 45.12907 | K32: 45.143227 | L32: 46.28548 | M32: 47.069462 | N32: 49.029163 | O32: 48.263416 | P32: 49.0424 | Q32: 50.544037 | R32: 51.270535 | S32: 51.909389 | T32: 52.522804 | U32: 53.556107 | V32: 54.379284 | W32: 54.76899 | X32: 55.077839 | Y32: 55.373089 | Z32: 55.619442 | AA32: 55.844055 | AB32: 56.048706 | AC32: 56.203579 | AD32: 56.377033 | AE32: 56.545631 | AF32: 56.762432 | AG32: 0.018
A33: New Light Truck | B33: Transportation: Energy Efficiency Indicators: On-Road New Light Truck: Alternative Transportation | C33: AEO.2025.ALTTRNP.EFI_CAFEO_TRN_HWY_LTRT_NEW_NA_MLSPGLN.A | D33: mpg | F33: 23.988018 | G33: 25.717506 | H33: 27.470898 | I33: 27.24152 | J33: 27.584202 | K33: 27.775764 | L33: 27.919968 | M33: 28.231255 | N33: 28.51063 | O33: 28.137867 | P33: 28.37771 | Q33: 28.619431 | R33: 28.901937 | S33: 29.085546 | T33: 29.275507 | U33: 29.461161 | V33: 29.584818 | W33: 29.708748 | X33: 29.788166 | Y33: 29.883118 | Z33: 29.9464 | AA33: 30.026072 | AB33: 30.081591 | AC33: 30.123497 | AD33: 30.182156 | AE33: 30.238665 | AF33: 30.351025 | AG33: 0.009
... A37: Freight Truck | B37: Transportation: Energy Efficiency Indicators: Freight Truck: Alternative Transportation | C37: AEO.2025.ALTTRNP.EFI_NA_TRN_HWY_FRTT_STK_NA_MLSPGLN.A | D37: mpg | F37: 7.757023 | G37: 7.826031 | H37: 7.906292 | I37: 7.996029 | J37: 8.094789 | K37: 8.199175 | L37: 8.307471 | M37: 8.417607 | N37: 8.528322 | O37: 8.63801 | P37: 8.745068 | Q37: 8.847067 | R37: 8.942054 | S37: 9.029954 | T37: 9.112733 | U37: 9.191482 | V37: 9.266891 | W37: 9.337207 | X37: 9.402058 | Y37: 9.46137 | Z37: 9.51621 | AA37: 9.569106 | AB37: 9.620891 | AC37: 9.670567 | AD37: 9.716979 | AE37: 9.761371 | AF37: 9.804544 | AG37: 0.009
A38: (seat miles per gallon)
A39: Aircraft | B39: Transportation: Energy Efficiency Indicators: Aircraft: Alternative Transportation | C39: AEO.2025.ALTTRNP.EFI_NA_TRN_NA_AIRC_NA_NA_SEATMPG.A | D39: seat mpg | F39: 85.368492 | G39: 85.782234 | H39: 86.453064 | I39: 87.12735 | J39: 87.815926 | K39: 88.497086 | L39: 89.183655 | M39: 89.886848 | N39: 90.639893 | O39: 91.399002 | P39: 92.155807 | Q39: 92.914574 | R39: 93.675323 | S39: 94.433296 | T39: 95.211731 | U39: 95.983521 | V39: 96.76857 | W39: 97.563377 | X39: 98.389313 | Y39: 99.21096 | Z39: 100.03321 | AA39: 100.86144 | AB39: 101.69376 | AC39: 102.53442 | AD39: 103.37976 | AE39: 104.222 | AF39: 105.06316 | AG39: 0.008
A40: (ton miles/thousand Btu)
A41: Rail | B41: Transportation: Energy Efficiency Indicators: Rail: Alternative Transportation | C41: AEO.2025.ALTTRNP.EFI_NA_TRN_NA_RAIL_NA_NA_TONMLPTHBTU.A | D41: ton miles/thousand Btu | F41: 3.37345 | G41: 3.37701 | H41: 3.380574 | I41: 3.384142 | J41: 3.387713 | K41: 3.391289 | L41: 3.394868 | M41: 3.398451 | N41: 3.402037 | O41: 3.405628 | P41: 3.409222 | Q41: 3.41282 | R41: 3.416422 | S41: 3.420027 | T41: 3.423637 | U41: 3.42725 | V41: 3.430867 | W41: 3.434488 | X41: 3.438113 | Y41: 3.441741 | Z41: 3.445373 | AA41: 3.44901 | AB41: 3.452649 | AC41: 3.456293 | AD41: 3.459941 | AE41: 3.463593 | AF41: 3.467248 | AG41: 0.001
A42: Domestic Shipping | B42: Transportation: Energy Efficiency Indicators: Domestic Shipping: Alternative Transportation | C42: AEO.2025.ALTTRNP.EFI_NA_TRN_NA_DMT_NA_NA_TONMLPTHBTU.A | D42: ton miles/thousand Btu | F42: 4.857779 | G42: 4.876665 | H42: 4.895624 | I42: 4.914657 | J42: 4.933764 | K42: 4.952945 | L42: 4.9722 | M42: 4.991531 | N42: 5.010937 | O42: 5.030418 | P42: 5.049975 | Q42: 5.069608 | R42: 5.089317 | S42: 5.109103 | T42: 5.128966 | U42: 5.148906 | V42: 5.168923 | W42: 5.189019 | X42: 5.209192 | Y42: 5.229445 | Z42: 5.249775 | AA42: 5.270185 | AB42: 5.290674 | AC42: 5.311243 | AD42: 5.331892 | AE42: 5.352621 | AF42: 5.37343 | AG42: 0.004
A43: Energy Use by Mode
A44: (quadrillion Btu)
A45: Light-Duty Vehicles | B45: Transportation: Energy Use by Mode: Light-Duty Vehicles: Alternative Transportation | C45: AEO.2025.ALTTRNP.CNSM_NA_TRN_LDV_USE_NA_NA_QBTU.A | D45: quads | F45: 15.264656 | G45: 15.318794 | H45: 15.263797 | I45: 15.137206 | J45: 14.977221 | K45: 14.792022 | L45: 14.586777 | M45: 14.410761 | N45: 14.212754 | O45: 14.032137 | P45: 13.876548 | Q45: 13.716936 | R45: 13.53182 | S45: 13.355209 | T45: 13.213084 | U45: 13.074738 | V45: 12.960391 | W45: 12.861576 | X45: 12.746393 | Y45: 12.672747 | Z45: 12.58318 | AA45: 12.516975 | AB45: 12.440613 | AC45: 12.393321 | AD45: 12.311717 | AE45: 12.264787 | AF45: 12.255931 | AG45: -0.008
A46: Commercial Light Trucks | B46: Transportation: Energy Use by Mode: Commercial Light Trucks: Alternative Transportation | C46: AEO.2025.ALTTRNP.CNSM_NA_TRN_CML_USE_NA_NA_QBTU.A | D46: quads | F46: 0.874375 | G46: 0.855739 | H46: 0.839741 | I46: 0.829063 | J46: 0.817038 | K46: 0.806523 | L46: 0.797053 | M46: 0.786668 | N46: 0.776019 | O46: 0.765748 | P46: 0.755153 | Q46: 0.744233 | R46: 0.733154 | S46: 0.721991 | T46: 0.710859 | U46: 0.699931 | V46: 0.689723 | W46: 0.678654 | X46: 0.668121 | Y46: 0.657262 | Z46: 0.646873 | AA46: 0.636532 | AB46: 0.626425 | AC46: 0.616496 | AD46: 0.606532 | AE46: 0.596606 | AF46: 0.586683 | AG46: -0.015
A47: Bus Transportation | B47: Transportation: Energy Use by Mode: Bus Transportation: Alternative Transportation | C47: AEO.2025.ALTTRNP.CNSM_NA_TRN_BST_USE_NA_NA_QBTU.A | D47: quads | F47: 0.207859 | G47: 0.213516 | H47: 0.21613 | I47: 0.217126 | J47: 0.217482 | K47: 0.217428 | L47: 0.217244 | M47: 0.216242 | N47: 0.214765 | O47: 0.213186 | P47: 0.211906 | Q47: 0.210372 | R47: 0.208783 | S47: 0.207225 | T47: 0.205645 | U47: 0.20398 | V47: 0.202187 | W47: 0.200301 | X47: 0.198292 | Y47: 0.196337 | Z47: 0.194281 | AA47: 0.19232 | AB47: 0.190195 | AC47: 0.187951 | AD47: 0.185792 | AE47: 0.183691 | AF47: 0.181904 | AG47: -0.005
A48: Freight Trucks | B48: Transportation: Energy Use by Mode: Freight Trucks: Alternative Transportation | C48: AEO.2025.ALTTRNP.CNSM_NA_TRN_FGHT_USE_NA_NA_QBTU.A | D48: quads | F48: 6.005128 | G48: 6.058611 | H48: 6.062553 | I48: 6.052277 | J48: 6.018679 | K48: 5.988855 | L48: 5.960129 | M48: 5.92348 | N48: 5.889193 | O48: 5.851345 | P48: 5.82186 | Q48: 5.796485 | R48: 5.783072 | S48: 5.777648 | T48: 5.775574 | U48: 5.770501 | V48: 5.770604 | W48: 5.771068 | X48: 5.774972 | Y48: 5.776579 | Z48: 5.77775 | AA48: 5.784515 | AB48: 5.789783 | AC48: 5.816376 | AD48: 5.843774 | AE48: 5.867581 | AF48: 5.884564 | AG48: -0.001
A49: Rail | B49: Passenger | C49: Transportation: Energy Use by Mode: Rail, Passenger: Alternative Transportation | D49: AEO.2025.ALTTRNP.CNSM_NA_TRN_RLP_USE_NA_NA_QBTU.A | E49: quads | F49: 0.043892 | G49: 0.046491 | H49: 0.047929 | I49: 0.048711 | J49: 0.049232 | K49: 0.049774 | L49: 0.050394 | M49: 0.050847 | N49: 0.05125 | O49: 0.051578 | P49: 0.051859 | Q49: 0.052284 | R49: 0.052821 | S49: 0.05337 | T49: 0.053936 | U49: 0.054449 | V49: 0.05492 | W49: 0.05534 | X49: 0.055737 | Y49: 0.056129 | Z49: 0.056455 | AA49: 0.056805 | AB49: 0.057083 | AC49: 0.057393 | AD49: 0.057765 | AE49: 0.058137 | AF49: 0.058625 | AG49: 0.011
A50: Rail | B50: Freight | C50: Transportation: Energy Use by Mode: Rail, Freight: Alternative Transportation | D50: AEO.2025.ALTTRNP.CNSM_NA_TRN_RLF_USE_NA_NA_QBTU.A | E50: quads | F50: 0.434231 | G50: 0.443759 | H50: 0.432581 | I50: 0.417752 | J50: 0.417425 | K50: 0.415938 | L50: 0.403474 | M50: 0.403178 | N50: 0.383832 | O50: 0.385307 | P50: 0.381275 | Q50: 0.38104 | R50: 0.382198 | S50: 0.383737 | T50: 0.38856 | U50: 0.385725 | V50: 0.38717 | W50: 0.387334 | X50: 0.388977 | Y50: 0.39085 | Z50: 0.391763 | AA50: 0.392738 | AB50: 0.392651 | AC50: 0.396481 | AD50: 0.399581 | AE50: 0.402098 | AF50: 0.402975 | AG50: -0.003
A51: Shipping | B51: Domestic | C51: Transportation: Energy Use by Mode: Shipping, Domestic: Alternative Transportation | D51: AEO.2025.ALTTRNP.CNSM_NA_TRN_SHDT_USE_NA_NA_QBTU.A | E51: quads | F51: 0.094441 | G51: 0.09533 | H51: 0.094566 | I51: 0.093798 | J51: 0.093108 | K51: 0.092339 | L51: 0.091481 | M51: 0.090543 | N51: 0.089462 | O51: 0.088708 | P51: 0.088034 | Q51: 0.08732 | R51: 0.08658 | S51: 0.085945 | T51: 0.085342 | U51: 0.084675 | V51: 0.084112 | W51: 0.08354 | X51: 0.082974 | Y51: 0.082355 | Z51: 0.08168 | AA51: 0.081035 | AB51: 0.080382 | AC51: 0.079954 | AD51: 0.07943 | AE51: 0.078866 | AF51: 0.078278 | AG51: -0.007 | AH51: =AF51/F51 -> 0.82885611
A52: Shipping | B52: International | C52: Transportation: Energy Use by Mode: Shipping, International: Alternative Transportation | D52: AEO.2025.ALTTRNP.CNSM_NA_TRN_SHINT_USE_NA_NA_QBTU.A | E52: quads | F52: 0.752119 | G52: 0.733382 | H52: 0.741755 | I52: 0.75532 | J52: 0.766295 | K52: 0.778196 | L52: 0.789926 | M52: 0.800556 | N52: 0.812124 | O52: 0.823287 | P52: 0.83493 | Q52: 0.844164 | R52: 0.851842 | S52: 0.859284 | T52: 0.865818 | U52: 0.872407 | V52: 0.878262 | W52: 0.883989 | X52: 0.889835 | Y52: 0.895572 | Z52: 0.901093 | AA52: 0.906316 | AB52: 0.910759 | AC52: 0.916784 | AD52: 0.923919 | AE52: 0.930804 | AF52: 0.937273 | AG52: 0.009 | AH52: =AF52/F52 -> 1.2461765
A53: Recreational Boats | B53: Transportation: Energy Use by Mode: Recreational Boats: Alternative Transportation | C53: AEO.2025.ALTTRNP.CNSM_NA_TRN_RBT_USE_NA_NA_QBTU.A | D53: quads | F53: 0.207605 | G53: 0.206045 | H53: 0.205252 | I53: 0.204434 | J53: 0.203145 | K53: 0.202085 | L53: 0.200753 | M53: 0.199065 | N53: 0.197719 | O53: 0.196503 | P53: 0.195253 | Q53: 0.194235 | R53: 0.193269 | S53: 0.192455 | T53: 0.191702 | U53: 0.190906 | V53: 0.190126 | W53: 0.189319 | X53: 0.188616 | Y53: 0.187856 | Z53: 0.186963 | AA53: 0.186015 | AB53: 0.185016 | AC53: 0.184286 | AD53: 0.183617 | AE53: 0.182851 | AF53: 0.182055 | AG53: -0.005
A54: Air | B54: Transportation: Energy Use by Mode: Air: Alternative Transportation | C54: AEO.2025.ALTTRNP.CNSM_NA_TRN_AIR_USE_NA_NA_QBTU.A | D54: quads | F54: 3.268324 | G54: 3.262033 | H54: 3.288747 | I54: 3.323875 | J54: 3.351261 | K54: 3.383548 | L54: 3.411572 | M54: 3.430951 | N54: 3.454605 | O54: 3.479305 | P54: 3.503246 | Q54: 3.534024 | R54: 3.567556 | S54: 3.607157 | T54: 3.649621 | U54: 3.693142 | V54: 3.735951 | W54: 3.776446 | X54: 3.821688 | Y54: 3.863978 | Z54: 3.901178 | AA54: 3.93691 | AB54: 3.970224 | AC54: 4.011132 | AD54: 4.05513 | AE54: 4.094516 | AF54: 4.133512 | AG54: 0.009
A55: Military Use | B55: Transportation: Energy Use by Mode: Military Use: Alternative Transportation | C55: AEO.2025.ALTTRNP.CNSM_NA_TRN_MILU_USE_NA_NA_QBTU.A | D55: quads | F55: 0.444789 | G55: 0.449845 | H55: 0.452969 | I55: 0.454896 | J55: 0.455762 | K55: 0.455593 | L55: 0.455377 | M55: 0.455842 | N55: 0.456217 | O55: 0.45661 | P55: 0.456933 | Q55: 0.457185 | R55: 0.457633 | S55: 0.458221 | T55: 0.458787 | U55: 0.459339 | V55: 0.459875 | W55: 0.460399 | X55: 0.460914 | Y55: 0.461423 | Z55: 0.461927 | AA55: 0.462425 | AB55: 0.462922 | AC55: 0.463419 | AD55: 0.463913 | AE55: 0.464408 | AF55: 0.464904 | AG55: 0.002
A56: Lubricants | B56: Transportation: Energy Use by Mode: Lubricants: Alternative Transportation | C56: AEO.2025.ALTTRNP.CNSM_NA_TRN_LBC_USE_NA_NA_QBTU.A | D56: quads | F56: 0.134269 | G56: 0.134665 | H56: 0.135305 | I56: 0.135764 | J56: 0.135972 | K56: 0.136085 | L56: 0.136129 | M56: 0.136055 | N56: 0.135958 | O56: 0.13591 | P56: 0.135892 | Q56: 0.135863 | R56: 0.135821 | S56: 0.135776 | T56: 0.135757 | U56: 0.135764 | V56: 0.135768 | W56: 0.135743 | X56: 0.135699 | Y56: 0.135634 | Z56: 0.135567 | AA56: 0.135501 | AB56: 0.135418 | AC56: 0.135323 | AD56: 0.135196 | AE56: 0.135056 | AF56: 0.134919 | AG56: 0
A57: Pipeline Fuel | B57: Transportation: Energy Use by Mode: Pipeline Fuel: Alternative Transportation | C57: AEO.2025.ALTTRNP.CNSM_NA_TRN_PFT_USE_NA_NA_QBTU.A | D57: quads | F57: 0.924158 | G57: 0.87021 | H57: 0.863571 | I57: 0.835609 | J57: 0.791565 | K57: 0.75779 | L57: 0.713011 | M57: 0.703353 | N57: 0.716096 | O57: 0.709196 | P57: 0.701622 | Q57: 0.701985 | R57: 0.70707 | S57: 0.716512 | T57: 0.726482 | U57: 0.73761 | V57: 0.746228 | W57: 0.752332 | X57: 0.756957 | Y57: 0.765151 | Z57: 0.774861 | AA57: 0.781811 | AB57: 0.792943 | AC57: 0.801185 | AD57: 0.810293 | AE57: 0.819837 | AF57: 0.831599 | AG57: -0.004
A58: Natural Gas Liquefaction for Export | B58: Transportation: Energy Use by Mode: Natural Gas for Liquefaction: Alternative Transportation | C58: AEO.2025.ALTTRNP.CNSM_NA_TRN_IDEI_LQFCT_NA_USA_QBTU.A | D58: quads | F58: 0.36799 | G58: 0.420411 | H58: 0.447693 | I58: 0.448493 | J58: 0.534997 | K58: 0.595588 | L58: 0.658577 | M58: 0.700788 | N58: 0.769518 | O58: 0.835053 | P58: 0.877011 | Q58: 0.893794 | R58: 0.912176 | S58: 0.927361 | T58: 0.935752 | U58: 0.935752 | V58: 0.937351 | W58: 0.935752 | X58: 0.935742 | Y58: 0.930754 | Z58: 0.932171 | AA58: 0.929527 | AB58: 0.934687 | AC58: 0.934997 | AD58: 0.936232 | AE58: 0.934129 | AF58: 0.935018 | AG58: 0.037
A59: Total | B59: Transportation: Energy Use by Mode: Total: Alternative Transportation | C59: AEO.2025.ALTTRNP.CNSM_NA_TRN_NA_USE_NA_NA_QBTU.A | D59: quads | F59: 29.023834 | G59: 29.108829 | H59: 29.09259 | I59: 28.954325 | J59: 28.829184 | K59: 28.671766 | L59: 28.471897 | M59: 28.308323 | N59: 28.159512 | O59: 28.02387 | P59: 27.891521 | Q59: 27.749924 | R59: 27.603794 | S59: 27.481892 | T59: 27.396921 | U59: 27.298918 | V59: 27.232672 | W59: 27.171799 | X59: 27.104918 | Y59: 27.072628 | Z59: 27.025742 | AA59: 26.999422 | AB59: 26.969101 | AC59: 26.995098 | AD59: 26.992891 | AE59: 27.013369 | AF59: 27.068243 | AG59: -0.003
A60: (million barrels per day oil equivalent)
A61: Light-Duty Vehicles | B61: Transportation: Energy Use by Mode: Light-Duty Vehicles: Alternative Transportation | C61: AEO.2025.ALTTRNP.CNSM_NA_TRN_LDV_USE_NA_NA_MILLBPDYOEQ.A | D61: MMb/d oil eq | F61: 8.280889 | G61: 8.309361 | H61: 8.277567 | I61: 8.20647 | J61: 8.11729 | K61: 8.014231 | L61: 7.900139 | M61: 7.802271 | N61: 7.692446 | O61: 7.592483 | P61: 7.506065 | Q61: 7.417579 | R61: 7.314888 | S61: 7.216888 | T61: 7.13751 | U61: 7.060346 | V61: 6.996391 | W61: 6.940898 | X61: 6.876627 | Y61: 6.835149 | Z61: 6.785208 | AA61: 6.74804 | AB61: 6.705527 | AC61: 6.679025 | AD61: 6.633841 | AE61: 6.607573 | AF61: 6.602071 | AG61: -0.009
A62: Commercial Light Trucks | B62: Transportation: Energy Use by Mode: Commercial Light Trucks: Alternative Transportation | C62: AEO.2025.ALTTRNP.CNSM_NA_TRN_CML_USE_NA_NA_MILLBPDYOEQ.A | D62: MMb/d oil eq | F62: 0.457016 | G62: 0.447813 | H62: 0.440019 | I62: 0.434969 | J62: 0.429303 | K62: 0.42445 | L62: 0.420061 | M62: 0.415188 | N62: 0.410158 | O62: 0.405297 | P62: 0.400243 | Q62: 0.39499 | R62: 0.389598 | S62: 0.384107 | T62: 0.378557 | U62: 0.373077 | V62: 0.367916 | W62: 0.362277 | X62: 0.35687 | Y62: 0.351243 | Z62: 0.345849 | AA62: 0.340455 | AB62: 0.335169 | AC62: 0.329957 | AD62: 0.324721 | AE62: 0.319494 | AF62: 0.314264 | AG62: -0.014
A63: Bus Transportation | B63: Transportation: Energy Use by Mode: Bus Transportation: Alternative Transportation | C63: AEO.2025.ALTTRNP.CNSM_NA_TRN_BST_USE_NA_NA_MILLBPDYOEQ.A | D63: MMb/d oil eq | F63: 0.103228 | G63: 0.105926 | H63: 0.107151 | I63: 0.107583 | J63: 0.107718 | K63: 0.107648 | L63: 0.107517 | M63: 0.106982 | N63: 0.106228 | O63: 0.105447 | P63: 0.104835 | Q63: 0.104076 | R63: 0.103287 | S63: 0.102533 | T63: 0.101759 | U63: 0.100944 | V63: 0.100055 | W63: 0.099111 | X63: 0.098109 | Y63: 0.097108 | Z63: 0.096052 | AA63: 0.095037 | AB63: 0.093949 | AC63: 0.09284 | AD63: 0.091765 | AE63: 0.090727 | AF63: 0.089832 | AG63: -0.005
A64: Freight Trucks | B64: Transportation: Energy Use by Mode: Freight Trucks: Alternative Transportation | C64: AEO.2025.ALTTRNP.CNSM_NA_TRN_FGHT_USE_NA_NA_MILLBPDYOEQ.A | D64: MMb/d oil eq | F64: 2.893941 | G64: 2.920017 | H64: 2.922178 | I64: 2.91758 | J64: 2.902385 | K64: 2.889214 | L64: 2.876924 | M64: 2.860907 | N64: 2.846161 | O64: 2.829921 | P64: 2.817726 | Q64: 2.807262 | R64: 2.802357 | S64: 2.801118 | T64: 2.801233 | U64: 2.799705 | V64: 2.800392 | W64: 2.800707 | X64: 2.80227 | Y64: 2.802311 | Z64: 2.802036 | AA64: 2.804259 | AB64: 2.805666 | AC64: 2.817162 | AD64: 2.828771 | AE64: 2.838518 | AF64: 2.844889 | AG64: -0.001
A65: Rail | B65: Passenger | C65: Transportation: Energy Use by Mode: Rail, Passenger: Alternative Transportation | D65: AEO.2025.ALTTRNP.CNSM_NA_TRN_RLP_USE_NA_NA_MILLBPDYOEQ.A | E65: MMb/d oil eq | F65: 0.020775 | G65: 0.022004 | H65: 0.022684 | I65: 0.023053 | J65: 0.0233 | K65: 0.023556 | L65: 0.023849 | M65: 0.024064 | N65: 0.024254 | O65: 0.02441 | P65: 0.024543 | Q65: 0.024743 | R65: 0.024998 | S65: 0.025258 | T65: 0.025526 | U65: 0.025769 | V65: 0.025992 | W65: 0.026191 | X65: 0.026378 | Y65: 0.026564 | Z65: 0.026718 | AA65: 0.026884 | AB65: 0.027016 | AC65: 0.027163 | AD65: 0.027339 | AE65: 0.027515 | AF65: 0.027746 | AG65: 0.011
A66: Rail | B66: Freight | C66: Transportation: Energy Use by Mode: Rail, Freight: Alternative Transportation | D66: AEO.2025.ALTTRNP.CNSM_NA_TRN_RLF_USE_NA_NA_MILLBPDYOEQ.A | E66: MMb/d oil eq | F66: 0.205982 | G66: 0.210496 | H66: 0.205175 | I66: 0.198123 | J66: 0.197978 | K66: 0.197273 | L66: 0.191365 | M66: 0.191222 | N66: 0.182045 | O66: 0.182744 | P66: 0.180835 | Q66: 0.180721 | R66: 0.181272 | S66: 0.182005 | T66: 0.184292 | U66: 0.182949 | V66: 0.183637 | W66: 0.183713 | X66: 0.184492 | Y66: 0.18538 | Z66: 0.185815 | AA66: 0.186277 | AB66: 0.186239 | AC66: 0.188059 | AD66: 0.189528 | AE66: 0.19072 | AF66: 0.191137 | AG66: -0.003
A67: Shipping | B67: Domestic | C67: Transportation: Energy Use by Mode: Shipping, Domestic: Alternative Transportation | D67: AEO.2025.ALTTRNP.CNSM_NA_TRN_SHDT_USE_NA_NA_MILLBPDYOEQ.A | E67: MMb/d oil eq | F67: 0.044744 | G67: 0.045169 | H67: 0.044805 | I67: 0.044439 | J67: 0.044117 | K67: 0.043755 | L67: 0.043351 | M67: 0.042908 | N67: 0.042398 | O67: 0.042042 | P67: 0.041725 | Q67: 0.041388 | R67: 0.04104 | S67: 0.040741 | T67: 0.040457 | U67: 0.040144 | V67: 0.039879 | W67: 0.039608 | X67: 0.039339 | Y67: 0.039046 | Z67: 0.038726 | AA67: 0.038419 | AB67: 0.03811 | AC67: 0.037908 | AD67: 0.037659 | AE67: 0.037391 | AF67: 0.037112 | AG67: -0.007
A68: Shipping | B68: International | C68: Transportation: Energy Use by Mode: Shipping, International: Alternative Transportation | D68: AEO.2025.ALTTRNP.CNSM_NA_TRN_SHINT_USE_NA_NA_MILLBPDYOEQ.A | E68: MMb/d oil eq | F68: 0.335526 | G68: 0.328032 | H68: 0.332124 | I68: 0.338171 | J68: 0.34317 | K68: 0.348464 | L68: 0.353706 | M68: 0.358505 | N68: 0.363798 | O68: 0.368916 | P68: 0.374241 | Q68: 0.378378 | R68: 0.381832 | S68: 0.385139 | T68: 0.388078 | U68: 0.391027 | V68: 0.393661 | W68: 0.396252 | X68: 0.398897 | Y68: 0.401481 | Z68: 0.403971 | AA68: 0.40631 | AB68: 0.408261 | AC68: 0.410949 | AD68: 0.414133 | AE68: 0.417221 | AF68: 0.420119 | AG68: 0.009
A69: Recreational Boats | B69: Transportation: Energy Use by Mode: Recreational Boats: Alternative Transportation | C69: AEO.2025.ALTTRNP.CNSM_NA_TRN_RBT_USE_NA_NA_MILLBPDYOEQ.A | D69: MMb/d oil eq | F69: 0.112644 | G69: 0.111823 | H69: 0.111419 | I69: 0.111002 | J69: 0.110329 | K69: 0.109779 | L69: 0.109081 | M69: 0.10819 | N69: 0.107484 | O69: 0.106848 | P69: 0.106194 | Q69: 0.105666 | R69: 0.105161 | S69: 0.104739 | T69: 0.10435 | U69: 0.103936 | V69: 0.103532 | W69: 0.10311 | X69: 0.102745 | Y69: 0.102349 | Z69: 0.10188 | AA69: 0.101381 | AB69: 0.100854 | AC69: 0.100474 | AD69: 0.100127 | AE69: 0.099726 | AF69: 0.099309 | AG69: -0.005
A70: Air | B70: Transportation: Energy Use by Mode: Air: Alternative Transportation | C70: AEO.2025.ALTTRNP.CNSM_NA_TRN_AIR_USE_NA_NA_MILLBPDYOEQ.A | D70: MMb/d oil eq | F70: 1.580574 | G70: 1.577537 | H70: 1.590447 | I70: 1.607424 | J70: 1.620659 | K70: 1.636263 | L70: 1.649807 | M70: 1.659173 | N70: 1.670605 | O70: 1.682543 | P70: 1.694114 | Q70: 1.708989 | R70: 1.725194 | S70: 1.744331 | T70: 1.764852 | U70: 1.785884 | V70: 1.806571 | W70: 1.82614 | X70: 1.848003 | Y70: 1.86844 | Z70: 1.886417 | AA70: 1.903684 | AB70: 1.919784 | AC70: 1.939552 | AD70: 1.960815 | AE70: 1.979848 | AF70: 1.998692 | AG70: 0.009
A71: Military Use | B71: Transportation: Energy Use by Mode: Military Use: Alternative Transportation | C71: AEO.2025.ALTTRNP.CNSM_NA_TRN_MILU_USE_NA_NA_MILLBPDYOEQ.A | D71: MMb/d oil eq | F71: 0.213959 | G71: 0.216389 | H71: 0.217888 | I71: 0.218809 | J71: 0.219229 | K71: 0.219148 | L71: 0.219045 | M71: 0.219267 | N71: 0.219448 | O71: 0.219636 | P71: 0.219792 | Q71: 0.219913 | R71: 0.220129 | S71: 0.220413 | T71: 0.220685 | U71: 0.220951 | V71: 0.22121 | W71: 0.221461 | X71: 0.221709 | Y71: 0.221954 | Z71: 0.222197 | AA71: 0.222436 | AB71: 0.222676 | AC71: 0.222916 | AD71: 0.223153 | AE71: 0.223391 | AF71: 0.22363 | AG71: 0.002
A72: Lubricants | B72: Transportation: Energy Use by Mode: Lubricants: Alternative Transportation | C72: AEO.2025.ALTTRNP.CNSM_NA_TRN_LBC_USE_NA_NA_MILLBPDYOEQ.A | D72: MMb/d oil eq | F72: 0.063424 | G72: 0.063611 | H72: 0.063913 | I72: 0.064131 | J72: 0.064228 | K72: 0.064282 | L72: 0.064303 | M72: 0.064268 | N72: 0.064222 | O72: 0.064199 | P72: 0.064191 | Q72: 0.064177 | R72: 0.064157 | S72: 0.064136 | T72: 0.064127 | U72: 0.06413 | V72: 0.064132 | W72: 0.064121 | X72: 0.0641 | Y72: 0.064069 | Z72: 0.064037 | AA72: 0.064006 | AB72: 0.063967 | AC72: 0.063922 | AD72: 0.063862 | AE72: 0.063796 | AF72: 0.063731 | AG72: 0
A73: Pipeline Fuel | B73: Transportation: Energy Use by Mode: Pipeline Fuel: Alternative Transportation | C73: AEO.2025.ALTTRNP.CNSM_NA_TRN_PFT_USE_NA_NA_MILLBPDYOEQ.A | D73: MMb/d oil eq | F73: 0.436541 | G73: 0.411058 | H73: 0.407922 | I73: 0.394714 | J73: 0.373909 | K73: 0.357955 | L73: 0.336803 | M73: 0.33224 | N73: 0.33826 | O73: 0.335001 | P73: 0.331423 | Q73: 0.331594 | R73: 0.333996 | S73: 0.338456 | T73: 0.343166 | U73: 0.348422 | V73: 0.352493 | W73: 0.355376 | X73: 0.357561 | Y73: 0.361432 | Z73: 0.366018 | AA73: 0.369301 | AB73: 0.37456 | AC73: 0.378453 | AD73: 0.382755 | AE73: 0.387263 | AF73: 0.39282 | AG73: -0.004
A74: Natural Gas Liquefaction for Export | B74: Transportation: Energy Use by Mode: Natural Gas for Liquefaction: Alternative Transportation | C74: AEO.2025.ALTTRNP.CNSM_NA_TRN_NA_LQFCT_NA_USA_MILLBPDYOEQ.A | D74: MMb/d oil eq | F74: 0.173826 | G74: 0.198588 | H74: 0.211475 | I74: 0.211853 | J74: 0.252715 | K74: 0.281336 | L74: 0.31109 | M74: 0.331029 | N74: 0.363495 | O74: 0.394451 | P74: 0.414271 | Q74: 0.422199 | R74: 0.430881 | S74: 0.438054 | T74: 0.442018 | U74: 0.442018 | V74: 0.442773 | W74: 0.442018 | X74: 0.442013 | Y74: 0.439657 | Z74: 0.440326 | AA74: 0.439078 | AB74: 0.441515 | AC74: 0.441661 | AD74: 0.442245 | AE74: 0.441251 | AF74: 0.441671 | AG74: 0.037
A75: Total | B75: Transportation: Energy Use by Mode: Total: Alternative Transportation | C75: AEO.2025.ALTTRNP.CNSM_NA_TRN_NA_USE_NA_NA_MILLBPDYOEQ.A | D75: MMb/d oil eq | F75: 14.923069 | G75: 14.967827 | H75: 14.954769 | I75: 14.878322 | J75: 14.806329 | K75: 14.717354 | L75: 14.60704 | M75: 14.516214 | N75: 14.431001 | O75: 14.353938 | P75: 14.280197 | Q75: 14.201674 | R75: 14.11879 | S75: 14.047919 | T75: 13.996613 | U75: 13.939302 | V75: 13.898635 | W75: 13.860985 | X75: 13.819115 | Y75: 13.79618 | Z75: 13.765251 | AA75: 13.745568 | AB75: 13.723292 | AC75: 13.73004 | AD75: 13.720713 | AE75: 13.724433 | AF75: 13.747025 | AG75: -0.003
A76: Battery Prices (2024 dollars per nominal kWh)
A77: Light-Duty Vehicles
A78: Battery Electric Vehicles | B78: Transportation: Battery Prices: Light-Duty Battery Electric: Alternative Transportation | C78: AEO.2025.ALTTRNP.PRCE_NA_TRN_NA_BAT_LDV_NA_13YDKWH.A | D78: 2024 $/kWh RPE | F78: 196.04523 | G78: 171.4099 | H78: 162.35551 | I78: 154.32104 | J78: 148.64557 | K78: 144.48248 | L78: 141.27228 | M78: 138.77521 | N78: 136.61577 | O78: 134.6274 | P78: 133.02846 | Q78: 131.5237 | R78: 130.10266 | S78: 128.79533 | T78: 127.58627 | U78: 126.45885 | V78: 125.39216 | W78: 124.39598 | X78: 123.47098 | Y78: 122.61042 | Z78: 121.80572 | AA78: 121.05392 | AB78: 120.34687 | AC78: 119.6844 | AD78: 119.06255 | AE78: 118.47816 | AF78: 117.92687 | AG78: -0.019
A79: Plug-In Hybrid Electric Vehicles | B79: Transportation: Battery Prices: Light-Duty Plug-in Hybrid Electric: Alternative Transportation | C79: AEO.2025.ALTTRNP.PRCE_NA_TRN_NA_BAT_LDV_NA_13YDKWH.A | D79: 2024 $/kWh RPE | F79: 570.03552 | G79: 489.47833 | H79: 459.87057 | I79: 433.59802 | J79: 415.03928 | K79: 401.426 | L79: 390.92868 | M79: 382.76331 | N79: 375.70193 | O79: 369.19998 | P79: 363.9715 | Q79: 359.0509 | R79: 354.40418 | S79: 350.12924 | T79: 346.17563 | U79: 342.48895 | V79: 339.00088 | W79: 335.74341 | X79: 332.71866 | Y79: 329.9046 | Z79: 327.27328 | AA79: 324.81485 | AB79: 322.50284 | AC79: 320.33652 | AD79: 318.30307 | AE79: 316.39218 | AF79: 314.58951 | AG79: -0.023
A80: Hybrid Electric Vehicles | B80: Transportation: Battery Prices: Light-Duty Hybrid Electric: Alternative Transportation | C80: AEO.2025.ALTTRNP.PRCE_NA_TRN_NA_BAT_LDV_NA_13YDKWH.A | D80: 2024 $/kWh RPE | F80: 570.03552 | G80: 489.47833 | H80: 459.87057 | I80: 433.59802 | J80: 415.03928 | K80: 401.426 | L80: 390.92868 | M80: 382.76331 | N80: 375.70193 | O80: 369.19998 | P80: 363.9715 | Q80: 359.0509 | R80: 354.40418 | S80: 350.12924 | T80: 346.17563 | U80: 342.48895 | V80: 339.00088 | W80: 335.74341 | X80: 332.71866 | Y80: 329.9046 | Z80: 327.27328 | AA80: 324.81485 | AB80: 322.50284 | AC80: 320.33652 | AD80: 318.30307 | AE80: 316.39218 | AF80: 314.58951 | AG80: -0.023
A81: Freight Trucks
A82: Class 4 & 5 | B82: Transportation: Battery Prices: Freight Truck Class 4-5: Alternative Transportation | C82: AEO.2025.ALTTRNP.PRCE_NA_TRN_NA_BAT_FRTTRK_NA_13YDKWH.A | D82: 2024 $/kWh | F82: 336.87881 | G82: 307.29883 | H82: 288.80246 | I82: 271.077 | J82: 255.56863 | K82: 244.60071 | L82: 236.54897 | M82: 230.33711 | N82: 225.49472 | O82: 221.30664 | P82: 217.4583 | Q82: 214.35638 | R82: 211.43359 | S82: 208.67517 | T82: 206.13972 | U82: 203.79489 | V82: 201.60883 | W82: 199.54256 | X82: 197.6105 | Y82: 195.81801 | Z82: 194.15103 | AA82: 192.59424 | AB82: 191.14033 | AC82: 189.7733 | AD82: 188.49175 | AE82: 187.28937 | AF82: 186.15944 | AG82: -0.023
A83: Class 6-8 Vocational | B83: Transportation: Battery Prices: Freight Truck Class 6-8 Vocational: Alternative Transportation | C83: AEO.2025.ALTTRNP.PRCE_NA_TRN_NA_BAT_FRTTRK_NA_13YDKWH.A | D83: 2024 $/kWh | F83: 483.72339 | G83: 441.24963 | H83: 414.69074 | I83: 389.23874 | J83: 366.97034 | K83: 351.22153 | L83: 339.66006 | M83: 330.74048 | N83: 323.78732 | O83: 317.77362 | P83: 312.24777 | Q83: 307.79376 | R83: 303.59692 | S83: 299.6362 | T83: 295.99548 | U83: 292.62854 | V83: 289.48953 | W83: 286.52267 | X83: 283.74841 | Y83: 281.17456 | Z83: 278.78098 | AA83: 276.54559 | AB83: 274.45789 | AC83: 272.495 | AD83: 270.65482 | AE83: 268.92828 | AF83: 267.30588 | AG83: -0.023
A84: Class 7&8 Tractors | B84: Transportation: Battery Prices: Freight Truck Class 7&8 Tractor: Alternative Transportation | C84: AEO.2025.ALTTRNP.PRCE_NA_TRN_NA_BAT_FRTTRK_NA_13YDKWH.A | D84: 2024 $/kWh | F84: 362.79254 | G84: 330.93723 | H84: 311.01801 | I84: 291.92905 | J84: 275.22778 | K84: 263.41614 | L84: 254.74504 | M84: 248.05534 | N84: 242.84049 | O84: 238.3302 | P84: 234.18585 | Q84: 230.84532 | R84: 227.69771 | S84: 224.72713 | T84: 221.99663 | U84: 219.47142 | V84: 217.1172 | W84: 214.892 | X84: 212.81133 | Y84: 210.88094 | Z84: 209.08574 | AA84: 207.4092 | AB84: 205.84343 | AC84: 204.37125 | AD84: 202.9911 | AE84: 201.69624 | AF84: 200.4794 | AG84: -0.023
A85: Class 2b & 3 | B85: Transportation: Battery Prices: Freight Truck Class 2b&3: Alternative Transportation | C85: AEO.2025.ALTTRNP.PRCE_NA_TRN_NA_BAT_FRTTRK_NA_13YDKWH.A | D85: 2024 $/kWh | F85: 238.97354 | G85: 217.99026 | H85: 204.86937 | I85: 192.29535 | J85: 181.29411 | K85: 173.51375 | L85: 167.80203 | M85: 163.39551 | N85: 159.96042 | O85: 156.98949 | P85: 154.25957 | Q85: 152.05914 | R85: 149.98578 | S85: 148.02907 | T85: 146.23045 | U85: 144.56708 | V85: 143.01633 | W85: 141.5506 | X85: 140.18007 | Y85: 138.90848 | Z85: 137.72598 | AA85: 136.62163 | AB85: 135.59027 | AC85: 134.62053 | AD85: 133.71143 | AE85: 132.85846 | AF85: 132.05695 | AG85: -0.023
A86: Hybrid Electric Vehicles | B86: Transportation: Battery Prices: Freight Truck Gasoline Hybrid Electric: Alternative Transportation | C86: AEO.2025.ALTTRNP.PRCE_NA_TRN_NA_BAT_FRTTRK_NA_13YDKWH.A | D86: 2024 $/kWh | F86: 993.36047 | G86: 906.13757 | H86: 851.59699 | I86: 799.32953 | J86: 753.59985 | K86: 721.25848 | L86: 697.51624 | M86: 679.1991 | N86: 664.92035 | O86: 652.57074 | P86: 641.22315 | Q86: 632.07648 | R86: 623.45795 | S86: 615.32428 | T86: 607.8479 | U86: 600.93366 | V86: 594.48749 | W86: 588.39471 | X86: 582.69769 | Y86: 577.41205 | Z86: 572.49664 | AA86: 567.90607 | AB86: 563.6189 | AC86: 559.58795 | AD86: 555.80896 | AE86: 552.26349 | AF86: 548.93164 | AG86: -0.023
A87: Electricity Prices (2024 cents per kWh)
A88: Light Trains | B88: Transportation: Electricity Prices: Light Trains: Alternative Transportation | C88: AEO.2025.ALTTRNP.PRCE_NA_TRN_NA_ELC_LTRNS_NA_Y13DLRPMMBTU.A | D88: 2024 cents/kWh | F88: 14.660725 | G88: 14.47932 | H88: 13.539622 | I88: 12.501745 | J88: 12.45952 | K88: 12.533541 | L88: 12.655854 | M88: 12.79153 | N88: 12.88917 | O88: 13.116578 | P88: 13.132267 | Q88: 13.026171 | R88: 13.029432 | S88: 13.024822 | T88: 13.013798 | U88: 12.905737 | V88: 12.819233 | W88: 12.860767 | X88: 12.948478 | Y88: 13.121889 | Z88: 13.205758 | AA88: 13.272813 | AB88: 13.279309 | AC88: 13.341878 | AD88: 13.308397 | AE88: 13.32265 | AF88: 13.292919 | AG88: -0.004
A89: Light-Duty Vehicles | B89: Transportation: Electricity Prices: Light-Duty Vehicles: Alternative Transportation | C89: AEO.2025.ALTTRNP.PRCE_NA_TRN_NA_ELC_LDV_NA_Y13DLRPMMBTU.A | D89: 2024 cents/kWh | F89: 21.406419 | G89: 20.894677 | H89: 18.821585 | I89: 17.486322 | J89: 17.284581 | K89: 17.332429 | L89: 17.445575 | M89: 17.659478 | N89: 17.786637 | O89: 18.025981 | P89: 18.087261 | Q89: 18.058178 | R89: 18.077915 | S89: 18.038933 | T89: 18.008388 | U89: 17.904356 | V89: 17.860285 | W89: 17.921337 | X89: 18.047403 | Y89: 18.188304 | Z89: 18.28047 | AA89: 18.398088 | AB89: 18.47851 | AC89: 18.575383 | AD89: 18.601013 | AE89: 18.634261 | AF89: 18.651932 | AG89: -0.005
A90: Home | B90: Transportation: Electricity Prices: Light-Duty Vehicles Home: Alternative Transportation | C90: AEO.2025.ALTTRNP.PRCE_NA_TRN_NA_ELC_LDV_NA_Y13DLRPMMBTU.A | D90: 2024 cents/kWh | F90: 18.915469 | G90: 18.494361 | H90: 16.748058 | I90: 15.598786 | J90: 15.387491 | K90: 15.411831 | L90: 15.48303 | M90: 15.651556 | N90: 15.761011 | O90: 15.963941 | P90: 16.044131 | Q90: 16.044027 | R90: 16.074539 | S90: 16.049256 | T90: 16.027717 | U90: 15.944241 | V90: 15.890953 | W90: 15.949241 | X90: 16.076356 | Y90: 16.220197 | Z90: 16.330137 | AA90: 16.446975 | AB90: 16.533956 | AC90: 16.647703 | AD90: 16.695798 | AE90: 16.747364 | AF90: 16.7914 | AG90: -0.005
A91: Public Level 2 | B91: Transportation: Electricity Prices: Light-Duty Vehicles Public Level 2: Alternative Transportation | C91: AEO.2025.ALTTRNP.PRCE_NA_TRN_NA_ELC_LDV_NA_Y13DLRPMMBTU.A | D91: 2024 cents/kWh | F91: 24.560234 | G91: 23.65334 | H91: 20.961617 | I91: 19.246886 | J91: 18.991436 | K91: 18.994349 | L91: 19.096301 | M91: 19.288596 | N91: 19.346433 | O91: 19.542026 | P91: 19.505563 | Q91: 19.382212 | R91: 19.341442 | S91: 19.236585 | T91: 19.152076 | U91: 18.98241 | V91: 18.923145 | W91: 18.947121 | X91: 19.024059 | Y91: 19.112776 | Z91: 19.133858 | AA91: 19.210448 | AB91: 19.242525 | AC91: 19.275586 | AD91: 19.235342 | AE91: 19.213842 | AF91: 19.162221 | AG91: -0.01
A92: Public DC Fast Charge | B92: Transportation: Electricity Prices: Light-Duty Vehicles Public DCFC: Alternative Transportation | C92: AEO.2025.ALTTRNP.PRCE_NA_TRN_NA_ELC_LDV_NA_Y13DLRPMMBTU.A | D92: 2024 cents/kWh | F92: 32.392368 | G92: 31.175576 | H92: 27.621338 | I92: 25.355183 | J92: 25.018739 | K92: 25.021774 | L92: 25.15715 | M92: 25.409142 | N92: 25.478199 | O92: 25.725658 | P92: 25.6675 | Q92: 25.497035 | R92: 25.434052 | S92: 25.300881 | T92: 25.193921 | U92: 24.978706 | V92: 24.923964 | W92: 24.95951 | X92: 25.053393 | Y92: 25.160581 | Z92: 25.174086 | AA92: 25.273709 | AB92: 25.316188 | AC92: 25.346585 | AD92: 25.289458 | AE92: 25.253148 | AF92: 25.178396 | AG92: -0.01
A93: Bus | B93: Transportation: Electricity Prices: Bus: Alternative Transportation | C93: AEO.2025.ALTTRNP.PRCE_NA_TRN_NA_ELC_BUS_NA_Y13DLRPMMBTU.A | D93: 2024 cents/kWh | F93: 17.499978 | G93: 16.868295 | H93: 14.858658 | I93: 13.690975 | J93: 13.510317 | K93: 13.550777 | L93: 13.650695 | M93: 13.814606 | N93: 13.887226 | O93: 14.057883 | P93: 14.094117 | Q93: 14.088541 | R93: 14.142582 | S93: 14.072425 | T93: 14.010379 | U93: 13.850702 | V93: 13.739597 | W93: 13.741968 | X93: 13.801117 | Y93: 13.910145 | Z93: 13.958562 | AA93: 14.029274 | AB93: 14.033215 | AC93: 14.086241 | AD93: 14.057613 | AE93: 14.07015 | AF93: 14.052716 | AG93: -0.008
A94: School | B94: Transportation: Electricity Prices: School Bus: Alternative Transportation | C94: AEO.2025.ALTTRNP.PRCE_NA_TRN_NA_ELC_BUS_NA_Y13DLRPMMBTU.A | D94: 2024 cents/kWh | F94: 17.109795 | G94: 16.165377 | H94: 14.333702 | I94: 13.116031 | J94: 12.958225 | K94: 12.986747 | L94: 13.08336 | M94: 13.197463 | N94: 13.25392 | O94: 13.438112 | P94: 13.430469 | Q94: 13.314503 | R94: 13.323175 | S94: 13.323256 | T94: 13.299072 | U94: 13.205408 | V94: 13.172117 | W94: 13.215064 | X94: 13.264645 | Y94: 13.397519 | Z94: 13.428667 | AA94: 13.513114 | AB94: 13.536572 | AC94: 13.570066 | AD94: 13.520778 | AE94: 13.50327 | AF94: 13.441691 | AG94: -0.009
A95: Transit | B95: Transportation: Electricity Prices: Transit Bus: Alternative Transportation | C95: AEO.2025.ALTTRNP.PRCE_NA_TRN_NA_ELC_BUS_NA_Y13DLRPMMBTU.A | D95: 2024 cents/kWh | F95: 17.561289 | G95: 17.02472 | H95: 14.998709 | I95: 13.865488 | J95: 13.694797 | K95: 13.753669 | L95: 13.866458 | M95: 14.061038 | N95: 14.151945 | O95: 14.327889 | P95: 14.392894 | Q95: 14.448506 | R95: 14.535325 | S95: 14.441809 | T95: 14.369105 | U95: 14.182898 | V95: 14.037636 | W95: 14.023992 | X95: 14.093598 | Y95: 14.194002 | Z95: 14.256455 | AA95: 14.322983 | AB95: 14.319469 | AC95: 14.387855 | AD95: 14.374875 | AE95: 14.408455 | AF95: 14.418906 | AG95: -0.008
A96: Intercity | B96: Transportation: Electricity Prices: Intercity Bus: Alternative Transportation | C96: AEO.2025.ALTTRNP.PRCE_NA_TRN_NA_ELC_BUS_NA_Y13DLRPMMBTU.A | D96: 2024 cents/kWh | F96: 12.941013 | G96: 12.624144 | H96: 11.719846 | I96: 11.091652 | J96: 11.041523 | K96: 11.135455 | L96: 11.261929 | M96: 11.467452 | N96: 11.591284 | O96: 11.827546 | P96: 11.914558 | Q96: 11.840053 | R96: 11.800545 | S96: 11.73856 | T96: 11.673352 | U96: 11.557298 | V96: 11.491102 | W96: 11.510795 | X96: 11.566348 | Y96: 11.638818 | Z96: 11.67062 | AA96: 11.73199 | AB96: 11.780459 | AC96: 11.801879 | AD96: 11.767419 | AE96: 11.73159 | AF96: 11.686546 | AG96: -0.004
A97: Freight truck | B97: Transportation: Electricity Prices: Freight Truck: Alternative Transportation | C97: AEO.2025.ALTTRNP.PRCE_NA_TRN_NA_ELC_FRTTRK_NA_Y13DLRPMMBTU.A | D97: 2024 cents/kWh | F97: 18.39276 | G97: 17.9644 | H97: 16.773347 | I97: 15.913227 | J97: 15.843658 | K97: 15.975295 | L97: 16.123283 | M97: 16.242621 | N97: 16.119142 | O97: 16.181033 | P97: 15.929745 | Q97: 15.355148 | R97: 14.820856 | S97: 14.332749 | T97: 13.900952 | U97: 13.469419 | V97: 13.144062 | W97: 12.936471 | X97: 12.805147 | Y97: 12.721908 | Z97: 12.632145 | AA97: 12.598369 | AB97: 12.569184 | AC97: 12.521887 | AD97: 12.426758 | AE97: 12.339561 | AF97: 12.250221 | AG97: -0.016
A98: Depot | B98: Transportation: Electricity Prices: Freight Truck Depot: Alternative Transportation | C98: AEO.2025.ALTTRNP.PRCE_NA_TRN_NA_ELC_FRTTRK_NA_Y13DLRPMMBTU.A | D98: 2024 cents/kWh | F98: 12.941013 | G98: 12.624144 | H98: 11.719846 | I98: 11.091652 | J98: 11.041523 | K98: 11.135455 | L98: 11.261929 | M98: 11.467452 | N98: 11.591284 | O98: 11.827546 | P98: 11.914558 | Q98: 11.840053 | R98: 11.800545 | S98: 11.73856 | T98: 11.673352 | U98: 11.557298 | V98: 11.491102 | W98: 11.510795 | X98: 11.566348 | Y98: 11.638818 | Z98: 11.67062 | AA98: 11.73199 | AB98: 11.780459 | AC98: 11.801879 | AD98: 11.767419 | AE98: 11.73159 | AF98: 11.686546 | AG98: -0.004
A99: Public/Retail | B99: Transportation: Electricity Prices: Freight Truck Public/Retail: Alternative Transportation | C99: AEO.2025.ALTTRNP.PRCE_NA_TRN_NA_ELC_FRTTRK_NA_Y13DLRPMMBTU.A | D99: 2024 cents/kWh | F99: 24.149309 | G99: 23.538984 | H99: 22.020655 | I99: 20.899756 | J99: 20.810403 | K99: 21.018689 | L99: 21.265513 | M99: 21.630918 | N99: 21.821585 | O99: 22.191971 | P99: 22.233132 | Q99: 21.968354 | R99: 21.82507 | S99: 21.729992 | T99: 21.668022 | U99: 21.554519 | V99: 21.546307 | W99: 21.653545 | X99: 21.818481 | Y99: 21.973881 | Z99: 22.062764 | AA99: 22.223499 | AB99: 22.378456 | AC99: 22.459212 | AD99: 22.427599 | AE99: 22.37236 | AF99: 22.297429 | AG99: -0.003
A100: Commercial light truck
A101: Depot | B101: Transportation: Electricity Prices: Commercial Light Truck Depot: Alternative Transportation | C101: AEO.2025.ALTTRNP.PRCE_NA_TRN_NA_ELC_CLT_NA_Y13DLRPMMBTU.A | D101: 2024 cents/kWh | F101: 12.941013 | G101: 12.624144 | H101: 11.719846 | I101: 11.091652 | J101: 11.041523 | K101: 11.135455 | L101: 11.261929 | M101: 11.467452 | N101: 11.591284 | O101: 11.827546 | P101: 11.914558 | Q101: 11.840053 | R101: 11.800545 | S101: 11.73856 | T101: 11.673352 | U101: 11.557298 | V101: 11.491102 | W101: 11.510795 | X101: 11.566348 | Y101: 11.638818 | Z101: 11.67062 | AA101: 11.73199 | AB101: 11.780459 | AC101: 11.801879 | AD101: 11.767419 | AE101: 11.73159 | AF101: 11.686546 | AG101: -0.004
A102: Public/Retail | B102: Transportation: Electricity Prices: Commercial Light Truck Public/Retail: Alternative Transportation | C102: AEO.2025.ALTTRNP.PRCE_NA_TRN_NA_ELC_CLT_NA_Y13DLRPMMBTU.A | D102: 2024 cents/kWh | F102: 24.149309 | G102: 23.538984 | H102: 22.020655 | I102: 20.899756 | J102: 20.810403 | K102: 21.018689 | L102: 21.265513 | M102: 21.630918 | N102: 21.821585 | O102: 22.191971 | P102: 22.233132 | Q102: 21.968354 | R102: 21.82507 | S102: 21.729992 | T102: 21.668022 | U102: 21.554519 | V102: 21.546307 | W102: 21.653545 | X102: 21.818481 | Y102: 21.973881 | Z102: 22.062764 | AA102: 22.223499 | AB102: 22.378456 | AC102: 22.459212 | AD102: 22.427599 | AE102: 22.37236 | AF102: 22.297429 | AG102: -0.003
A103: Hydrogen Price (2024 dollars per kg) | B103: Transportation: Hydrogen Price: Delivered: Alternative Transportation | C103: AEO.2025.ALTTRNP.PRCE_NA_TRN_NA_HDG_NA_NA_NA.A | D103: 2024 $/kg | F103: 8.231517 | G103: 8.356859 | H103: 8.318288 | I103: 8.29093 | J103: 8.307778 | K103: 8.337455 | L103: 8.375732 | M103: 8.402835 | N103: 8.464133 | O103: 8.495932 | P103: 8.540318 | Q103: 8.527973 | R103: 8.505517 | S103: 8.488868 | T103: 8.483689 | U103: 8.47639 | V103: 8.484052 | W103: 8.50936 | X103: 8.535672 | Y103: 8.548611 | Z103: 8.557114 | AA103: 8.560738 | AB103: 8.56083 | AC103: 8.554235 | AD103: 8.551289 | AE103: 8.548012 | AF103: 8.546188 | AG103: 0.001
...

Sheet AEO 2025 Table 35
A1: Table 35. Transportation Sector Energy Use by Mode and Type
A2: https://www.eia.gov/outlooks/aeo/data/browser/#/?id=45-AEO2025&cases=alttrnp&sourcekey=0
A3: Fri Dec 05 2025 14:48:52 GMT-0800 (Pacific Standard Time)
A4: Source: U.S. Energy Information Administration
B5: full name | C5: api key | D5: units | E5: 2023 | F5: 2024 | G5: 2025 | H5: 2026 | I5: 2027 | J5: 2028 | K5: 2029 | L5: 2030 | M5: 2031 | N5: 2032 | O5: 2033 | P5: 2034 | Q5: 2035 | R5: 2036 | S5: 2037 | T5: 2038 | U5: 2039 | V5: 2040 | W5: 2041 | X5: 2042 | Y5: 2043 | Z5: 2044 | AA5: 2045 | AB5: 2046 | AC5: 2047 | AD5: 2048 | AE5: 2049 | AF5: 2050 | AG5: Growth (2024-2050)
A6: Energy Use by Mode
A7: Highway
A8: Light-Duty Vehicles | B8: Transportation Energy Use: Highway: Light-Duty Vehicles: Alternative Transportation | C8: AEO.2025.ALTTRNP.CNSM_NA_TRN_HWY_LDV_NA_NA_TRLBTU.A | D8: trillion Btu | F8: 15264.654 | G8: 15318.795 | H8: 15263.797 | I8: 15137.205 | J8: 14977.219 | K8: 14792.022 | L8: 14586.776 | M8: 14410.759 | N8: 14212.753 | O8: 14032.138 | P8: 13876.546 | Q8: 13716.936 | R8: 13531.819 | S8: 13355.209 | T8: 13213.084 | U8: 13074.737 | V8: 12960.392 | W8: 12861.576 | X8: 12746.393 | Y8: 12672.746 | Z8: 12583.18 | AA8: 12516.974 | AB8: 12440.612 | AC8: 12393.32 | AD8: 12311.716 | AE8: 12264.786 | AF8: 12255.932 | AG8: -0.008
A9: Automobiles | B9: Transportation Energy Use: Highway: Light-Duty Vehicles: Automobiles: Alternative Transportation | C9: AEO.2025.ALTTRNP.CNSM_NA_TRN_HWY_LDV_AUTO_NA_TRLBTU.A | D9: trillion Btu | F9: 5666.4248 | G9: 5554.9678 | H9: 5400.2788 | I9: 5213.4336 | J9: 5021.1035 | K9: 4829.0156 | L9: 4647.3159 | M9: 4471.4189 | N9: 4301.4409 | O9: 4137.5469 | P9: 4011.3757 | Q9: 3874.7188 | R9: 3737.3823 | S9: 3626.634 | T9: 3540.1406 | U9: 3457.0771 | V9: 3381.4636 | W9: 3320.8726 | X9: 3263.1855 | Y9: 3214.3291 | Z9: 3165.2424 | AA9: 3127.6562 | AB9: 3090.6357 | AC9: 3066.7412 | AD9: 3033.1829 | AE9: 3002.1785 | AF9: 2982.7175 | AG9: -0.024
A10: Light Trucks | B10: Transportation Energy Use: Highway: Light-Duty Vehicles: Light Trucks: Alternative Transportation | C10: AEO.2025.ALTTRNP.CNSM_NA_TRN_HWY_LDV_LTRT_NA_TRLBTU.A | D10: trillion Btu | F10: 9580.5361 | G10: 9746.5537 | H10: 9846.8047 | I10: 9907.7139 | J10: 9940.7285 | K10: 9948.2871 | L10: 9925.3662 | M10: 9925.8486 | N10: 9898.3975 | O10: 9882.2314 | P10: 9853.2383 | Q10: 9830.7393 | R10: 9783.4082 | S10: 9717.9102 | T10: 9662.5664 | U10: 9607.5527 | V10: 9569.0596 | W10: 9531.0273 | X10: 9473.7139 | Y10: 9449.0752 | Z10: 9408.7441 | AA10: 9380.2471 | AB10: 9341.0205 | AC10: 9317.6934 | AD10: 9269.752 | AE10: 9253.9219 | AF10: 9264.5908 | AG10: -0.001
A11: Motorcycles | B11: Transportation Energy Use: Highway: Light-Duty Vehicles: Motorcycles: Alternative Transportation | C11: AEO.2025.ALTTRNP.CNSM_NA_TRN_HWY_LDV_MCYCL_NA_TRLBTU.A | D11: trillion Btu | F11: 17.693827 | G11: 17.273775 | H11: 16.712742 | I11: 16.057793 | J11: 15.386235 | K11: 14.720136 | L11: 14.094455 | M11: 13.491011 | N11: 12.914552 | O11: 12.358894 | P11: 11.931881 | Q11: 11.47748 | R11: 11.027963 | S11: 10.665314 | T11: 10.377406 | U11: 10.107397 | V11: 9.867947 | W11: 9.675448 | X11: 9.493168 | Y11: 9.342217 | Z11: 9.193549 | AA11: 9.070769 | AB11: 8.956112 | AC11: 8.885429 | AD11: 8.781081 | AE11: 8.685104 | AF11: 8.623068 | AG11: -0.027
A12: Commercial Light Trucks | B12: Transportation Energy Use: Highway: Commercial Light Trucks: Alternative Transportation | C12: AEO.2025.ALTTRNP.CNSM_NA_TRN_HWY_CML_NA_NA_TRLBTU.A | D12: trillion Btu | F12: 874.37512 | G12: 855.73944 | H12: 839.74072 | I12: 829.06293 | J12: 817.03815 | K12: 806.52301 | L12: 797.05286 | M12: 786.66846 | N12: 776.01849 | O12: 765.74768 | P12: 755.15271 | Q12: 744.23328 | R12: 733.15375 | S12: 721.99127 | T12: 710.85889 | U12: 699.93121 | V12: 689.72302 | W12: 678.65424 | X12: 668.12085 | Y12: 657.26196 | Z12: 646.87317 | AA12: 636.53192 | AB12: 626.42468 | AC12: 616.49579 | AD12: 606.53198 | AE12: 596.60645 | AF12: 586.6828 | AG12: -0.015
A13: Buses | B13: Transportation Energy Use: Highway: Buses: Alternative Transportation | C13: AEO.2025.ALTTRNP.CNSM_NA_TRN_HWY_BUS_NA_NA_TRLBTU.A | D13: trillion Btu | F13: 207.85881 | G13: 213.51556 | H13: 216.12988 | I13: 217.12576 | J13: 217.48173 | K13: 217.42764 | L13: 217.24431 | M13: 216.24175 | N13: 214.76508 | O13: 213.18587 | P13: 211.90617 | Q13: 210.37204 | R13: 208.78293 | S13: 207.22485 | T13: 205.64493 | U13: 203.97955 | V13: 202.18666 | W13: 200.30072 | X13: 198.29199 | Y13: 196.33681 | Z13: 194.28084 | AA13: 192.31953 | AB13: 190.19499 | AC13: 187.9511 | AD13: 185.79196 | AE13: 183.69107 | AF13: 181.90389 | AG13: -0.005
A14: Transit | B14: Transportation Energy Use: Highway: Buses: Transit: Alternative Transportation | C14: AEO.2025.ALTTRNP.CNSM_NA_TRN_HWY_BUS_TNST_NA_TRLBTU.A | D14: trillion Btu | F14: 76.710045 | G14: 81.313904 | H14: 83.939346 | I14: 85.569359 | J14: 86.754189 | K14: 87.688942 | L14: 88.627594 | M14: 88.838867 | N14: 88.562233 | O14: 88.112343 | P14: 87.900932 | Q14: 87.407082 | R14: 86.832077 | S14: 86.239662 | T14: 85.77771 | U14: 85.252876 | V14: 84.619087 | W14: 83.913132 | X14: 83.115341 | Y14: 82.391418 | Z14: 81.586922 | AA14: 80.892448 | AB14: 80.055817 | AC14: 79.108192 | AD14: 78.258156 | AE14: 77.463318 | AF14: 76.982124 | AG14: 0
A15: Intercity | B15: Transportation Energy Use: Highway: Buses: Intercity: Alternative Transportation | C15: AEO.2025.ALTTRNP.CNSM_NA_TRN_HWY_BUS_ICYT_NA_TRLBTU.A | D15: trillion Btu | F15: 30.108593 | G15: 31.324183 | H15: 32.204269 | I15: 32.814285 | J15: 33.256687 | K15: 33.580925 | L15: 33.812759 | M15: 33.971855 | N15: 34.074734 | O15: 34.127522 | P15: 34.138332 | Q15: 34.117863 | R15: 34.071152 | S15: 34.002563 | T15: 33.932446 | U15: 33.85054 | V15: 33.759457 | W15: 33.660358 | X15: 33.556801 | Y15: 33.447479 | Z15: 33.332581 | AA15: 33.213673 | AB15: 33.091961 | AC15: 32.971535 | AD15: 32.850975 | AE15: 32.727406 | AF15: 32.602531 | AG15: 0.003
A16: School | B16: Transportation Energy Use: Highway: Buses: School: Alternative Transportation | C16: AEO.2025.ALTTRNP.CNSM_NA_TRN_HWY_BUS_SCBU_NA_TRLBTU.A | D16: trillion Btu | F16: 101.04017 | G16: 100.87748 | H16: 99.986282 | I16: 98.742126 | J16: 97.470871 | K16: 96.157784 | L16: 94.803955 | M16: 93.431023 | N16: 92.128098 | O16: 90.945992 | P16: 89.86692 | Q16: 88.847099 | R16: 87.879684 | S16: 86.982628 | T16: 85.934761 | U16: 84.876144 | V16: 83.808136 | W16: 82.727234 | X16: 81.619865 | Y16: 80.497902 | Z16: 79.361336 | AA16: 78.213409 | AB16: 77.047211 | AC16: 75.871361 | AD16: 74.682838 | AE16: 73.500343 | AF16: 72.319229 | AG16: -0.013
A17: Freight Trucks | B17: Transportation Energy Use: Highway: Freight Trucks: Alternative Transportation | C17: AEO.2025.ALTTRNP.CNSM_NA_TRN_HWY_FGHT_NA_NA_TRLBTU.A | D17: trillion Btu | F17: 6005.127 | G17: 6058.6118 | H17: 6062.5513 | I17: 6052.2773 | J17: 6018.6777 | K17: 5988.854 | L17: 5960.1274 | M17: 5923.48 | N17: 5889.1938 | O17: 5851.3447 | P17: 5821.8594 | Q17: 5796.4863 | R17: 5783.0732 | S17: 5777.6479 | T17: 5775.5737 | U17: 5770.502 | V17: 5770.6045 | W17: 5771.0684 | X17: 5774.9722 | Y17: 5776.5781 | Z17: 5777.749 | AA17: 5784.5146 | AB17: 5789.7837 | AC17: 5816.376 | AD17: 5843.7744 | AE17: 5867.5796 | AF17: 5884.5645 | AG17: -0.001
A18: Light Medium | B18: Transportation Energy Use: Highway: Freight Trucks: Light Medium: Alternative Transportation | C18: AEO.2025.ALTTRNP.CNSM_NA_TRN_HWY_FGHT_LITEMED_NA_TRLBTU.A | D18: trillion Btu | F18: 851.47601 | G18: 863.49976 | H18: 867.48792 | I18: 868.15887 | J18: 866.95129 | K18: 870.92328 | L18: 877.43018 | M18: 883.93866 | N18: 890.85523 | O18: 897.59168 | P18: 905.22339 | Q18: 912.45801 | R18: 919.90442 | S18: 926.81397 | T18: 933.20429 | U18: 938.7359 | V18: 945.26697 | W18: 950.28949 | X18: 954.30872 | Y18: 956.26917 | Z18: 958.11407 | AA18: 961.7926 | AB18: 966.23438 | AC18: 973.57996 | AD18: 979.5119 | AE18: 984.37396 | AF18: 988.6319 | AG18: 0.006
A19: Medium | B19: Transportation Energy Use: Highway: Freight Trucks: Medium: Alternative Transportation | C19: AEO.2025.ALTTRNP.CNSM_NA_TRN_HWY_FGHT_MD10T26KLB_NA_TRLBTU.A | D19: trillion Btu | F19: 945.58374 | G19: 933.90814 | H19: 915.86285 | I19: 898.11731 | J19: 880.15131 | K19: 864.79657 | L19: 851.15039 | M19: 837.89587 | N19: 826.3302 | O19: 814.63721 | P19: 804.64459 | Q19: 795.93488 | R19: 789.71979 | S19: 785.57684 | T19: 782.27106 | U19: 779.23023 | V19: 777.32288 | W19: 775.71301 | X19: 775.07422 | Y19: 774.70258 | Z19: 774.43353 | AA19: 774.8346 | AB19: 774.97778 | AC19: 778.14654 | AD19: 781.60486 | AE19: 784.56281 | AF19: 786.19134 | AG19: -0.007
A20: Heavy | B20: Transportation Energy Use: Highway: Freight Trucks: Large: Alternative Transportation | C20: AEO.2025.ALTTRNP.CNSM_NA_TRN_HWY_FGHT_LRGGT26KLB_NA_TRLBTU.A | D20: trillion Btu | F20: 4208.0674 | G20: 4261.2041 | H20: 4279.2012 | I20: 4286.001 | J20: 4271.5757 | K20: 4253.1348 | L20: 4231.5469 | M20: 4201.645 | N20: 4172.0083 | O20: 4139.1157 | P20: 4111.9912 | Q20: 4088.0933 | R20: 4073.449 | S20: 4065.2573 | T20: 4060.0986 | U20: 4052.5354 | V20: 4048.0146 | W20: 4045.0657 | X20: 4045.5889 | Y20: 4045.6067 | Z20: 4045.2017 | AA20: 4047.8877 | AB20: 4048.5718 | AC20: 4064.6492 | AD20: 4082.6575 | AE20: 4098.6436 | AF20: 4109.7412 | AG20: -0.001
A21: Non-Highway
A22: Air | B22: Transportation Energy Use: Non-Highway: Air: Alternative Transportation | C22: AEO.2025.ALTTRNP.CNSM_NA_TRN_AIR_NA_NA_NA_TRLBTU.A | D22: trillion Btu | F22: 3268.3242 | G22: 3262.0327 | H22: 3288.7466 | I22: 3323.8755 | J22: 3351.2607 | K22: 3383.5483 | L22: 3411.5718 | M22: 3430.9507 | N22: 3454.6042 | O22: 3479.3049 | P22: 3503.2454 | Q22: 3534.0239 | R22: 3567.5562 | S22: 3607.156 | T22: 3649.6206 | U22: 3693.1416 | V22: 3735.9509 | W22: 3776.4458 | X22: 3821.688 | Y22: 3863.9778 | Z22: 3901.178 | AA22: 3936.9099 | AB22: 3970.2231 | AC22: 4011.1311 | AD22: 4055.1304 | AE22: 4094.5156 | AF22: 4133.5112 | AG22: 0.009
A23: General Aviation | B23: Transportation Energy Use: Non-Highway: Air: General Aviation: Alternative Transportation | C23: AEO.2025.ALTTRNP.CNSM_NA_TRN_AIR_GAV_NA_NA_TRLBTU.A | D23: trillion Btu | F23: 176.96918 | G23: 176.66234 | H23: 177.92859 | I23: 179.59653 | J23: 180.89647 | K23: 182.43054 | L23: 183.76234 | M23: 184.68278 | N23: 185.80727 | O23: 186.98187 | P23: 188.12065 | Q23: 189.5851 | R23: 191.18109 | S23: 193.06606 | T23: 195.08763 | U23: 197.15936 | V23: 199.19751 | W23: 201.12561 | X23: 203.2796 | Y23: 205.29327 | Z23: 207.06455 | AA23: 208.76579 | AB23: 210.35208 | AC23: 212.29996 | AD23: 214.39508 | AE23: 216.27049 | AF23: 218.12735 | AG23: 0.008
A24: Domestic Passenger | B24: Transportation Energy Use: Non-Highway: Air: Domestic Passenger: Alternative Transportation | C24: AEO.2025.ALTTRNP.CNSM_NA_TRN_AIR_DAC_NA_NA_TRLBTU.A | D24: trillion Btu | F24: 1627.3729 | G24: 1628.4395 | H24: 1648.2767 | I24: 1668.1155 | J24: 1681.5041 | K24: 1697.8981 | L24: 1711.0428 | M24: 1719.0887 | N24: 1729.4327 | O24: 1740.863 | P24: 1751.28 | Q24: 1764.3302 | R24: 1777.9761 | S24: 1793.6168 | T24: 1811.2522 | U24: 1829.1019 | V24: 1846.6696 | W24: 1863.1866 | X24: 1882.0354 | Y24: 1899.4946 | Z24: 1914.4185 | AA24: 1928.4327 | AB24: 1941.7546 | AC24: 1959.423 | AD24: 1978.9136 | AE24: 1996.4678 | AF24: 2013.1691 | AG24: 0.008
A25: International Passenger | B25: Transportation Energy Use: Non-Highway: Air: International Passenger: Alternative Transportation | C25: AEO.2025.ALTTRNP.CNSM_NA_TRN_AIR_IAC_NA_NA_TRLBTU.A | D25: trillion Btu | F25: 908.70795 | G25: 902.83484 | H25: 908.52081 | I25: 918.44818 | J25: 927.18286 | K25: 936.98395 | L25: 946.00244 | M25: 952.78186 | N25: 960.73151 | O25: 968.70251 | P25: 976.70752 | Q25: 987.04419 | R25: 998.51453 | S25: 1012.2177 | T25: 1026.4883 | U25: 1041.1876 | V25: 1055.6478 | W25: 1069.3749 | X25: 1084.5186 | Y25: 1098.7596 | Z25: 1111.4924 | AA25: 1123.8741 | AB25: 1135.3002 | AC25: 1148.7244 | AD25: 1162.9369 | AE25: 1175.6084 | AF25: 1188.4796 | AG25: 0.01
A26: Dedicated Freight | B26: Transportation Energy Use: Non-Highway: Air: Dedicated Freight: Alternative Transportation | C26: AEO.2025.ALTTRNP.CNSM_NA_TRN_AIR_DFT_NA_NA_TRLBTU.A | D26: trillion Btu | F26: 555.27417 | G26: 554.09625 | H26: 554.02063 | I26: 557.71521 | J26: 561.67737 | K26: 566.23572 | L26: 570.76416 | M26: 574.39746 | N26: 578.63281 | O26: 582.75751 | P26: 587.13721 | Q26: 593.06451 | R26: 599.88422 | S26: 608.25562 | T26: 616.79248 | U26: 625.69299 | V26: 634.4361 | W26: 642.75873 | X26: 651.85437 | Y26: 660.43036 | Z26: 668.20258 | AA26: 675.8371 | AB26: 682.81634 | AC26: 690.68384 | AD26: 698.88489 | AE26: 706.16888 | AF26: 713.73535 | AG26: 0.01
A27: Water | B27: Transportation Energy Use: Non-Highway: Water: Alternative Transportation | C27: AEO.2025.ALTTRNP.CNSM_NA_TRN_WTR_NA_NA_NA_TRLBTU.A | D27: trillion Btu | F27: 1054.1652 | G27: 1034.7566 | H27: 1041.5731 | I27: 1053.5527 | J27: 1062.5481 | K27: 1072.6205 | L27: 1082.1591 | M27: 1090.1638 | N27: 1099.3053 | O27: 1108.4968 | P27: 1118.2167 | Q27: 1125.7186 | R27: 1131.6902 | S27: 1137.6836 | T27: 1142.8618 | U27: 1147.9878 | V27: 1152.5002 | W27: 1156.8479 | X27: 1161.4255 | Y27: 1165.7836 | Z27: 1169.736 | AA27: 1173.3649 | AB27: 1176.1564 | AC27: 1181.0236 | AD27: 1186.9668 | AE27: 1192.5219 | AF27: 1197.6055 | AG27: 0.005
A28: Freight | B28: Transportation Energy Use: Non-Highway: Water: Freight: Alternative Transportation | C28: AEO.2025.ALTTRNP.CNSM_NA_TRN_WTR_FGT_NA_NA_TRLBTU.A | D28: trillion Btu | F28: 846.56012 | G28: 828.71191 | H28: 836.32147 | I28: 849.11847 | J28: 859.40271 | K28: 870.53509 | L28: 881.40619 | M28: 891.09924 | N28: 901.58679 | O28: 911.99438 | P28: 922.96387 | Q28: 931.48334 | R28: 938.4212 | S28: 945.2287 | T28: 951.15991 | U28: 957.08179 | V28: 962.37433 | W28: 967.52905 | X28: 972.80926 | Y28: 977.92731 | Z28: 982.77283 | AA28: 987.35004 | AB28: 991.14075 | AC28: 996.73749 | AD28: 1003.3494 | AE28: 1009.6706 | AF28: 1015.5508 | AG28: 0.007
A29: Domestic Shipping | B29: Transportation Energy Use: Non-Highway: Water: Freight: Domestic Shipping: Alternative Transportation | C29: AEO.2025.ALTTRNP.CNSM_NA_TRN_WTR_DMT_NA_NA_TRLBTU.A | D29: trillion Btu | F29: 94.440971 | G29: 95.330078 | H29: 94.566444 | I29: 93.798164 | J29: 93.107506 | K29: 92.339127 | L29: 91.480576 | M29: 90.543335 | N29: 89.462425 | O29: 88.707657 | P29: 88.034157 | Q29: 87.31971 | R29: 86.579651 | S29: 85.944572 | T29: 85.341614 | U29: 84.675209 | V29: 84.112099 | W29: 83.540062 | X29: 82.97393 | Y29: 82.355484 | Z29: 81.679947 | AA29: 81.034569 | AB29: 80.382202 | AC29: 79.95388 | AD29: 79.430321 | AE29: 78.86647 | AF29: 78.277954 | AG29: -0.007
A30: International Shipping | B30: Transportation Energy Use: Non-Highway: Water: Freight: International Shipping: Alternative Transportation | C30: AEO.2025.ALTTRNP.CNSM_NA_TRN_WTR_INTS_NA_NA_TRLBTU.A | D30: trillion Btu | F30: 752.11914 | G30: 733.38184 | H30: 741.755 | I30: 755.32031 | J30: 766.29523 | K30: 778.19598 | L30: 789.9256 | M30: 800.55591 | N30: 812.12439 | O30: 823.28674 | P30: 834.92969 | Q30: 844.16363 | R30: 851.84155 | S30: 859.28412 | T30: 865.8183 | U30: 872.40656 | V30: 878.26221 | W30: 883.98901 | X30: 889.83533 | Y30: 895.57184 | Z30: 901.0929 | AA30: 906.31549 | AB30: 910.75855 | AC30: 916.78363 | AD30: 923.91907 | AE30: 930.80414 | AF30: 937.27283 | AG30: 0.009
A31: Recreational Boats | B31: Transportation Energy Use: Non-Highway: Water: Recreational Boats: Alternative Transportation | C31: AEO.2025.ALTTRNP.CNSM_NA_TRN_WTR_RBT_NA_NA_TRLBTU.A | D31: trillion Btu | F31: 207.60503 | G31: 206.04472 | H31: 205.25169 | I31: 204.43427 | J31: 203.14537 | K31: 202.08534 | L31: 200.75287 | M31: 199.06451 | N31: 197.71854 | O31: 196.5025 | P31: 195.25281 | Q31: 194.23524 | R31: 193.26904 | S31: 192.45489 | T31: 191.70195 | U31: 190.90596 | V31: 190.12585 | W31: 189.31891 | X31: 188.61624 | Y31: 187.85625 | Z31: 186.96317 | AA31: 186.01485 | AB31: 185.01559 | AC31: 184.28604 | AD31: 183.61746 | AE31: 182.85123 | AF31: 182.0547 | AG31: -0.005
A32: Rail | B32: Transportation Energy Use: Non-Highway: Rail: Alternative Transportation | C32: AEO.2025.ALTTRNP.CNSM_NA_TRN_RAIL_RAIL_NA_NA_TRLBTU.A | D32: trillion Btu | F32: 478.12289 | G32: 490.24942 | H32: 480.51019 | I32: 466.46356 | J32: 466.65649 | K32: 465.71143 | L32: 453.8681 | M32: 454.02496 | N32: 435.08209 | O32: 436.88516 | P32: 433.13406 | Q32: 433.3237 | R32: 435.01944 | S32: 437.10776 | T32: 442.49597 | U32: 440.17383 | V32: 442.09015 | W32: 442.67453 | X32: 444.71454 | Y32: 446.9794 | Z32: 448.21762 | AA32: 449.54321 | AB32: 449.73407 | AC32: 453.87384 | AD32: 457.34601 | AE32: 460.23428 | AF32: 461.59979 | AG32: -0.001
A33: Freight | B33: Transportation Energy Use: Non-Highway: Rail: Freight: Alternative Transportation | C33: AEO.2025.ALTTRNP.CNSM_NA_TRN_RAIL_FGT_NA_NA_TRLBTU.A | D33: trillion Btu | F33: 434.23068 | G33: 443.7587 | H33: 432.5813 | I33: 417.75235 | J33: 417.42465 | K33: 415.93777 | L33: 403.47412 | M33: 403.17804 | N33: 383.83212 | O33: 385.30667 | P33: 381.27539 | Q33: 381.04004 | R33: 382.19842 | S33: 383.7374 | T33: 388.55951 | U33: 385.72473 | V33: 387.1702 | W33: 387.33423 | X33: 388.97726 | Y33: 390.85007 | Z33: 391.76263 | AA33: 392.73843 | AB33: 392.65094 | AC33: 396.48129 | AD33: 399.58118 | AE33: 402.09753 | AF33: 402.97449 | AG33: -0.003
... A42: Jet Fuel and Aviation Gasoline | B42: Transportation Energy Use: Military Use: Aviation: Alternative Transportation | C42: AEO.2025.ALTTRNP.CNSM_NA_TRN_MLU_AVI_NA_NA_TRLBTU.A | D42: trillion Btu | F42: 335.94638 | G42: 339.76504 | H42: 342.12509 | I42: 343.58023 | J42: 344.23431 | K42: 344.10706 | L42: 343.94382 | M42: 344.2944 | N42: 344.57822 | O42: 344.87469 | P42: 345.11853 | Q42: 345.30908 | R42: 345.64752 | S42: 346.09128 | T42: 346.51938 | U42: 346.93585 | V42: 347.34112 | W42: 347.7366 | X42: 348.12558 | Y42: 348.51016 | Z42: 348.89059 | AA42: 349.26682 | AB42: 349.64249 | AC42: 350.01758 | AD42: 350.39069 | AE42: 350.76431 | AF42: 351.13889 | AG42: 0.002
A43: Residual Fuel Oil | B43: Transportation Energy Use: Military Use: Residual Fuel Oil: Alternative Transportation | C43: AEO.2025.ALTTRNP.CNSM_NA_TRN_MLU_RFO_NA_NA_TRLBTU.A | D43: trillion Btu | F43: 0 | G43: 0 | H43: 0 | I43: 0 | J43: 0 | K43: 0 | L43: 0 | M43: 0 | N43: 0 | O43: 0 | P43: 0 | Q43: 0 | R43: 0 | S43: 0 | T43: 0 | U43: 0 | V43: 0 | W43: 0 | X43: 0 | Y43: 0 | Z43: 0 | AA43: 0 | AB43: 0 | AC43: 0 | AD43: 0 | AE43: 0 | AF43: 0 | AG43: - -
A44: Distillates and Diesel | B44: Transportation Energy Use: Military Use: Distillate Fuel Oil: Alternative Transportation | C44: AEO.2025.ALTTRNP.CNSM_NA_TRN_MLU_DFO_NA_NA_TRLBTU.A | D44: trillion Btu | F44: 108.84243 | G44: 110.07963 | H44: 110.84426 | I44: 111.31572 | J44: 111.52762 | K44: 111.4864 | L44: 111.43352 | M44: 111.54709 | N44: 111.63905 | O44: 111.73511 | P44: 111.81412 | Q44: 111.87587 | R44: 111.98552 | S44: 112.1293 | T44: 112.26799 | U44: 112.40292 | V44: 112.53424 | W44: 112.66235 | X44: 112.78838 | Y44: 112.91296 | Z44: 113.03624 | AA44: 113.15813 | AB44: 113.27985 | AC44: 113.40138 | AD44: 113.52225 | AE44: 113.6433 | AF44: 113.76468 | AG44: 0.002
A45: Total | B45: Transportation Energy Use: Total: Alternative Transportation | C45: AEO.2025.ALTTRNP.CNSM_NA_TRN_NA_TOT_NA_NA_TRLBTU.A | D45: trillion Btu | F45: 29023.836 | G45: 29108.83 | H45: 29092.584 | I45: 28954.326 | J45: 28829.18 | K45: 28671.768 | L45: 28471.893 | M45: 28308.326 | N45: 28159.508 | O45: 28023.869 | P45: 27891.523 | Q45: 27749.92 | R45: 27603.795 | S45: 27481.891 | T45: 27396.92 | U45: 27298.916 | V45: 27232.668 | W45: 27171.793 | X45: 27104.918 | Y45: 27072.625 | Z45: 27025.742 | AA45: 26999.422 | AB45: 26969.1 | AC45: 26995.1 | AD45: 26992.889 | AE45: 27013.363 | AF45: 27068.242 | AG45: -0.003
A46: Energy Use by Type
A47: Motor Gasoline excluding E85 | B47: Transportation Energy Use: Petroleum: Motor Gasoline: Alternative Transportation | C47: AEO.2025.ALTTRNP.CNSM_NA_TRN_NA_PET_MGS_NA_TRLBTU.A | D47: trillion Btu | F47: 16560.4 | G47: 16586.141 | H47: 16491.031 | I47: 16322.833 | J47: 16116.017 | K47: 15889.713 | L47: 15646.424 | M47: 15442.433 | N47: 15218.63 | O47: 15020.562 | P47: 14848.118 | Q47: 14673.362 | R47: 14472.294 | S47: 14278.983 | T47: 14119.805 | U47: 13963.114 | V47: 13831.296 | W47: 13713.389 | X47: 13578.589 | Y47: 13483.399 | Z47: 13372.886 | AA47: 13287.871 | AB47: 13192.723 | AC47: 13130.141 | AD47: 13032.898 | AE47: 12968.009 | AF47: 12939.202 | AG47: -0.009
A48: E85 | B48: Transportation Energy Use: E85: Alternative Transportation | C48: AEO.2025.ALTTRNP.CNSM_NA_TRN_NA_E85_NA_NA_TRLBTU.A | D48: trillion Btu | F48: 41.284557 | G48: 40.049072 | H48: 37.582172 | I48: 34.528759 | J48: 33.338047 | K48: 32.040035 | L48: 30.544378 | M48: 28.232197 | N48: 26.313066 | O48: 24.350527 | P48: 22.539648 | Q48: 20.880737 | R48: 19.347086 | S48: 18.291014 | T48: 16.780552 | U48: 16.01264 | V48: 15.460896 | W48: 14.956593 | X48: 14.46664 | Y48: 14.072709 | Z48: 13.952835 | AA48: 13.3923 | AB48: 13.186946 | AC48: 13.295124 | AD48: 13.06893 | AE48: 12.868924 | AF48: 12.591402 | AG48: -0.045
A49: Diesel | B49: Transportation Energy Use: Petroleum: Diesel: Alternative Transportation | C49: AEO.2025.ALTTRNP.CNSM_NA_TRN_NA_PET_DSL_NA_TRLBTU.A | D49: trillion Btu | F49: 6653.7041 | G49: 6716.0161 | H49: 6703.0981 | I49: 6665.5391 | J49: 6617.9302 | K49: 6564.814 | L49: 6497.2319 | M49: 6432.1475 | N49: 6348.9629 | O49: 6281.3921 | P49: 6214.9932 | Q49: 6151.627 | R49: 6101.0117 | S49: 6057.3623 | T49: 6021.4531 | U49: 5974.8901 | V49: 5937.7769 | W49: 5901.2046 | X49: 5872.0068 | Y49: 5843.0327 | Z49: 5813.5542 | AA49: 5788.8496 | AB49: 5761.7148 | AC49: 5758.0215 | AD49: 5755.5552 | AE49: 5751.1221 | AF49: 5739.8042 | AG49: -0.006
A50: Jet Fuel (kerosene & naphtha) | B50: Transportation Energy Use: Petroleum: Jet Fuel: Alternative Transportation | C50: AEO.2025.ALTTRNP.UNC_NA_TRN_NA_PET_JFL_NA_TRLBTU.A | D50: trillion Btu | F50: 3581.8689 | G50: 3579.4041 | H50: 3608.4841 | I50: 3645.0728 | J50: 3673.1167 | K50: 3705.2803 | L50: 3733.1438 | M50: 3752.8755 | N50: 3776.8149 | O50: 3801.8137 | P50: 3825.9995 | Q50: 3856.9697 | R50: 3890.8408 | S50: 3930.8857 | T50: 3973.7788 | U50: 4017.717 | V50: 4060.9319 | W50: 4101.8228 | X50: 4147.4541 | Y50: 4190.1289 | Z50: 4227.7095 | AA50: 4263.8174 | AB50: 4297.5073 | AC50: 4338.79 | AD50: 4383.1626 | AE50: 4422.9214 | AF50: 4462.2915 | AG50: 0.008
A51: Residual Fuel Oil | B51: Transportation Energy Use: Petroleum: Residual Fuel Oil: Alternative Transportation | C51: AEO.2025.ALTTRNP.CNSM_NA_TRN_NA_PET_RFO_NA_TRLBTU.A | D51: trillion Btu | F51: 551.82117 | G51: 515.44672 | H51: 512.00433 | I51: 521.7146 | J51: 527.1499 | K51: 536.16486 | L51: 544.46399 | M51: 550.63928 | N51: 555.56909 | O51: 560.05176 | P51: 565.12555 | Q51: 571.33374 | R51: 576.15924 | S51: 581.9408 | T51: 586.01965 | U51: 590.54822 | V51: 594.24262 | W51: 597.45154 | X51: 600.77637 | Y51: 604.31085 | Z51: 607.6994 | AA51: 611.23755 | AB51: 615.37231 | AC51: 619.82159 | AD51: 624.9801 | AE51: 629.56622 | AF51: 633.98541 | AG51: 0.005
A52: Aviation Gasoline | B52: Transportation Energy Use: Petroleum: Aviation Gasoline: Alternative Transportation | C52: AEO.2025.ALTTRNP.CNSM_NA_TRN_NA_PET_AVGA_NA_TRLBTU.A | D52: trillion Btu | F52: 22.401548 | G52: 22.394032 | H52: 22.387812 | I52: 22.382666 | J52: 22.378407 | K52: 22.374884 | L52: 22.371969 | M52: 22.369558 | N52: 22.367563 | O52: 22.365911 | P52: 22.364546 | Q52: 22.363417 | R52: 22.36248 | S52: 22.361708 | T52: 22.361067 | U52: 22.360538 | V52: 22.3601 | W52: 22.359737 | X52: 22.359438 | Y52: 22.35919 | Z52: 22.358984 | AA52: 22.358814 | AB52: 22.358673 | AC52: 22.358557 | AD52: 22.358461 | AE52: 22.358381 | AF52: 22.358315 | AG52: 0
A53: Propane | B53: Transportation Energy Use: Petroleum: Propane: Alternative Transportation | C53: AEO.2025.ALTTRNP.CNSM_NA_TRN_NA_PET_PROP_NA_TRLBTU.A | D53: trillion Btu | F53: 11.194937 | G53: 11.326602 | H53: 11.367645 | I53: 11.375973 | J53: 11.351239 | K53: 11.289317 | L53: 11.225379 | M53: 11.113161 | N53: 10.983699 | O53: 10.848458 | P53: 10.725233 | Q53: 10.595365 | R53: 10.469961 | S53: 10.348195 | T53: 10.219623 | U53: 10.09042 | V53: 9.96222 | W53: 9.830092 | X53: 9.696779 | Y53: 9.5655 | Z53: 9.433719 | AA53: 9.3098 | AB53: 9.182885 | AC53: 9.065533 | AD53: 8.946511 | AE53: 8.822084 | AF53: 8.705223 | AG53: -0.01
A54: Lubricants | B54: Transportation Energy Use: Petroleum: Lubricants: Alternative Transportation | C54: AEO.2025.ALTTRNP.CNSM_NA_TRN_NA_PET_LBC_NA_TRLBTU.A | D54: trillion Btu | F54: 134.26944 | G54: 134.66496 | H54: 135.30473 | I54: 135.76445 | J54: 135.97156 | K54: 136.08528 | L54: 136.12859 | M54: 136.05534 | N54: 135.95807 | O54: 135.90976 | P54: 135.89247 | Q54: 135.86319 | R54: 135.82115 | S54: 135.77626 | T54: 135.75709 | U54: 135.76404 | V54: 135.76825 | W54: 135.74341 | X54: 135.69879 | Y54: 135.63441 | Z54: 135.56685 | AA54: 135.50081 | AB54: 135.41753 | AC54: 135.32342 | AD54: 135.19623 | AE54: 135.056 | AF54: 134.91943 | AG54: 0
A55: Petroleum and Other Liquids Subtotal | B55: Transportation Energy Use: Petroleum Subtotal: Alternative Transportation | C55: AEO.2025.ALTTRNP.CNSM_NA_TRN_NA_PET_NA_NA_TRLBTU.A | D55: trillion Btu | F55: 27556.947 | G55: 27605.441 | H55: 27521.26 | I55: 27359.209 | J55: 27137.254 | K55: 26897.762 | L55: 26621.535 | M55: 26375.863 | N55: 26095.6 | O55: 25857.293 | P55: 25645.758 | Q55: 25442.994 | R55: 25228.307 | S55: 25035.947 | T55: 24886.176 | U55: 24730.496 | V55: 24607.797 | W55: 24496.758 | X55: 24381.051 | Y55: 24302.504 | Z55: 24203.16 | AA55: 24132.34 | AB55: 24047.467 | AC55: 24026.82 | AD55: 23976.166 | AE55: 23950.725 | AF55: 23953.857 | AG55: -0.005
A56: Electricity | B56: Transportation Energy Use: Electricity: Alternative Transportation | C56: AEO.2025.ALTTRNP.CNSM_NA_TRN_NA_ELC_NA_NA_TRLBTU.A | D56: trillion Btu | F56: 85.34494 | G56: 115.15037 | H56: 155.98854 | I56: 201.9713 | J56: 252.63286 | K56: 304.47864 | L56: 359.64197 | M56: 406.82205 | N56: 454.85483 | O56: 497.35562 | P56: 540.09924 | Q56: 581.99963 | R56: 624.28204 | S56: 666.59503 | T56: 708.72296 | U56: 750.33447 | V56: 790.61645 | W56: 829.09992 | X56: 865.3623 | Y56: 899.78278 | Z56: 932.20587 | AA56: 962.77515 | AB56: 990.92175 | AC56: 1017.3717 | AD56: 1042.7155 | AE56: 1067.5381 | AF56: 1091.9565 | AG56: 0.103
A57: Compressed/Liquefied Natural Gas | B57: Transportation Energy Use: Natural Gas: Alternative Transportation | C57: AEO.2025.ALTTRNP.CNSM_NA_TRN_NA_NG_NA_NA_TRLBTU.A | D57: trillion Btu | F57: 88.136703 | G57: 95.444481 | H57: 101.01884 | I57: 105.18923 | J57: 108.27601 | K57: 111.1958 | L57: 113.73024 | M57: 115.5424 | N57: 116.80028 | O57: 117.76981 | P57: 119.05447 | Q57: 120.03825 | R57: 121.29671 | S57: 122.92555 | T57: 124.97321 | U57: 127.27069 | V57: 130.1364 | W57: 133.57593 | X57: 137.28264 | Y57: 141.25102 | Z57: 145.45998 | AA57: 150.18043 | AB57: 155.23866 | AC57: 161.42148 | AD57: 168.57367 | AE57: 176.61394 | AF57: 185.69241 | AG57: 0.029
A58: Hydrogen | B58: Transportation Energy Use: Hydrogen: Alternative Transportation | C58: AEO.2025.ALTTRNP.CNSM_NA_TRN_NA_HDG_NA_NA_TRLBTU.A | D58: trillion Btu | F58: 0.435674 | G58: 0.463143 | H58: 0.473567 | I58: 0.47776 | J58: 0.476332 | K58: 0.463263 | L58: 0.450768 | M58: 0.435994 | N58: 0.418304 | O58: 0.39632 | P58: 0.374005 | Q58: 0.35125 | R58: 0.327931 | S58: 0.304437 | T58: 0.281066 | U58: 0.25866 | V58: 0.237191 | W58: 0.216257 | X58: 0.199203 | Y58: 0.184053 | Z58: 0.17237 | AA58: 0.159518 | AB58: 0.149824 | AC58: 0.142795 | AD58: 0.138412 | AE58: 0.134445 | AF58: 0.131483 | AG58: -0.045
... A61: Total Consumption | B61: Transportation: Total Energy Use: Alternative Transportation | C61: AEO.2025.ALTTRNP.CNSM_NA_TRN_NA_NA_NA_NA_TRLBTU.A | D61: trillion Btu | F61: 29023.014 | G61: 29107.121 | H61: 29090.004 | I61: 28950.951 | J61: 28825.201 | K61: 28667.277 | L61: 28466.947 | M61: 28302.805 | N61: 28153.287 | O61: 28017.062 | P61: 27883.92 | Q61: 27741.164 | R61: 27593.459 | S61: 27469.646 | T61: 27382.387 | U61: 27281.721 | V61: 27212.365 | W61: 27147.734 | X61: 27076.596 | Y61: 27039.627 | Z61: 26988.031 | AA61: 26956.793 | AB61: 26921.408 | AC61: 26941.939 | AD61: 26934.119 | AE61: 26948.975 | AF61: 26998.256 | AG61: -0.003

Sheet AEO 2025 Table 45
A1: Table 45. Transportation Fleet Car and Truck Stock by Type and Technology
A2: https://www.eia.gov/outlooks/aeo/data/browser/#/?id=55-AEO2025&cases=alttrnp&sourcekey=0
A3: Fri Dec 05 2025 14:50:52 GMT-0800 (Pacific Standard Time)
A4: Source: U.S. Energy Information Administration
B5: full name | C5: api key | D5: units | E5: 2023 | F5: 2024 | G5: 2025 | H5: 2026 | I5: 2027 | J5: 2028 | K5: 2029 | L5: 2030 | M5: 2031 | N5: 2032 | O5: 2033 | P5: 2034 | Q5: 2035 | R5: 2036 | S5: 2037 | T5: 2038 | U5: 2039 | V5: 2040 | W5: 2041 | X5: 2042 | Y5: 2043 | Z5: 2044 | AA5: 2045 | AB5: 2046 | AC5: 2047 | AD5: 2048 | AE5: 2049 | AF5: 2050 | AG5: Growth (2024-2050)
A6: Car Stock
A7: Conventional Cars
A8: Gasoline ICE Vehicles | B8: Fleet Vehicle Stock: Conventional Cars: Gasoline: Alternative Transportation | C8: AEO.2025.ALTTRNP.ECI_STK_CNV_FLC_GSL_NA_NA_TH.A | D8: thousands | F8: 5075.3691 | G8: 4824.9785 | H8: 4539.7256 | I8: 4228.9844 | J8: 3937.7976 | K8: 3710.9226 | L8: 3512.5742 | M8: 3327.2087 | N8: 3127.4695 | O8: 2978.8933 | P8: 2861.5793 | Q8: 2729.3728 | R8: 2603.5134 | S8: 2492.502 | T8: 2396.8831 | U8: 2302.8364 | V8: 2209.5779 | W8: 2126.697 | X8: 2053.364 | Y8: 1987.5833 | Z8: 1926.649 | AA8: 1871.7106 | AB8: 1819.1608 | AC8: 1769.2786 | AD8: 1721.4883 | AE8: 1676.5723 | AF8: 1637.2051 | AG8: -0.043
A9: TDI Diesel ICE | B9: Fleet Vehicle Stock: Conventional Cars: TDI Diesel: Alternative Transportation | C9: AEO.2025.ALTTRNP.ECI_STK_CNV_FLC_TDS_NA_NA_TH.A | D9: thousands | F9: 15.97803 | G9: 13.911413 | H9: 12.051627 | I9: 10.370836 | J9: 8.844614 | K9: 7.479106 | L9: 6.284921 | M9: 5.252181 | N9: 4.372341 | O9: 3.643175 | P9: 3.051164 | Q9: 2.579858 | R9: 2.209668 | S9: 1.920185 | T9: 1.695036 | U9: 1.51745 | V9: 1.368175 | W9: 1.237102 | X9: 1.121457 | Y9: 1.018339 | Z9: 0.925365 | AA9: 0.841181 | AB9: 0.764935 | AC9: 0.69586 | AD9: 0.633263 | AE9: 0.576521 | AF9: 0.52507 | AG9: -0.123
A10: Total Conventional Cars | B10: Fleet Vehicle Stock: Conventional Cars: Total: Alternative Transportation | C10: AEO.2025.ALTTRNP.ECI_STK_CNV_FLC_NA_NA_NA_TH.A | D10: thousands | F10: 5091.3472 | G10: 4838.8901 | H10: 4551.7773 | I10: 4239.355 | J10: 3946.6423 | K10: 3718.4016 | L10: 3518.8591 | M10: 3332.4609 | N10: 3131.8418 | O10: 2982.5364 | P10: 2864.6306 | Q10: 2731.9526 | R10: 2605.7231 | S10: 2494.4221 | T10: 2398.5781 | U10: 2304.3538 | V10: 2210.946 | W10: 2127.9341 | X10: 2054.4854 | Y10: 1988.6016 | Z10: 1927.5745 | AA10: 1872.5518 | AB10: 1819.9257 | AC10: 1769.9744 | AD10: 1722.1216 | AE10: 1677.1488 | AF10: 1637.7301 | AG10: -0.043
A11: Alternative-Fuel Cars
A12: Ethanol-Flex Fuel ICE | B12: Fleet Vehicle Stock: Alternative-Fuel Cars: Ethanol-Flex Fuel ICE: Alternative Transportation | C12: AEO.2025.ALTTRNP.ECI_STK_ALF1_FLC_EFFI_NA_NA_TH.A | D12: thousands | F12: 185.83043 | G12: 158.76605 | H12: 134.82158 | I12: 113.52628 | J12: 94.714485 | K12: 78.336166 | L12: 64.364655 | M12: 52.711391 | N12: 43.209827 | O12: 35.860065 | P12: 30.128227 | Q12: 25.750183 | R12: 22.493084 | S12: 19.972109 | T12: 17.990849 | U12: 16.438389 | V12: 15.174291 | W12: 14.108563 | X12: 13.189731 | Y12: 12.385399 | Z12: 11.676161 | AA12: 11.033206 | AB12: 10.440344 | AC12: 9.893756 | AD12: 9.3883 | AE12: 8.92121 | AF12: 8.487045 | AG12: -0.112
A13: 100-Mile Electric Vehicle | B13: Fleet Vehicle Stock: Alternative-Fuel Cars: 100-Mile Electric Vehicle: Alternative Transportation | C13: AEO.2025.ALTTRNP.ECI_STK_ALF1_FLC_100MIEV_NA_NA_TH.A | D13: thousands | F13: 11.85019 | G13: 12.360404 | H13: 12.04448 | I13: 11.302363 | J13: 10.383241 | K13: 9.624597 | L13: 9.14712 | M13: 8.794331 | N13: 8.563879 | O13: 7.991126 | P13: 7.706276 | Q13: 7.585549 | R13: 7.577725 | S13: 7.639728 | T13: 7.761407 | U13: 7.928746 | V13: 7.974091 | W13: 8.047615 | X13: 8.139864 | Y13: 8.259529 | Z13: 8.361784 | AA13: 8.471305 | AB13: 8.556553 | AC13: 8.620687 | AD13: 8.678905 | AE13: 8.732212 | AF13: 8.828277 | AG13: -0.011
A14: 200-Mile Electric Vehicle | B14: Fleet Vehicle Stock: Alternative-Fuel Cars: 200-Mile Electric Vehicle: Alternative Transportation | C14: AEO.2025.ALTTRNP.ECI_STK_ALF1_FLC_200MIEV_NA_NA_TH.A | D14: thousands | F14: 70.611595 | G14: 89.524704 | H14: 108.11518 | I14: 128.68025 | J14: 142.52853 | K14: 151.67728 | L14: 165.15234 | M14: 179.0822 | N14: 235.65671 | O14: 287.33295 | P14: 334.09531 | Q14: 392.7757 | R14: 437.33997 | S14: 473.97659 | T14: 507.0426 | U14: 555.18976 | V14: 592.68933 | W14: 622.91486 | X14: 647.55518 | Y14: 671.5658 | Z14: 692.02985 | AA14: 712.49701 | AB14: 728.66309 | AC14: 741.73767 | AD14: 753.25073 | AE14: 763.21765 | AF14: 776.83136 | AG14: 0.097
A15: 300-Mile Electric Vehicle | B15: Fleet Vehicle Stock: Alternative-Fuel Cars: 300-Mile Electric Vehicle: Alternative Transportation | C15: AEO.2025.ALTTRNP.ECI_STK_ALF1_FLC_300MIEV_NA_NA_TH.A | D15: thousands | F15: 278.5542 | G15: 365.3042 | H15: 506.17468 | I15: 651.42444 | J15: 761.15637 | K15: 835.7478 | L15: 906.38159 | M15: 966.11365 | N15: 1013.4059 | O15: 1021.9559 | P15: 1053.6199 | Q15: 1086.2643 | R15: 1118.5103 | S15: 1148.3688 | T15: 1176.9158 | U15: 1200.6284 | V15: 1230.4824 | W15: 1251.8945 | X15: 1267.2229 | Y15: 1277.7421 | Z15: 1286.0959 | AA15: 1292.9971 | AB15: 1297.876 | AC15: 1300.225 | AD15: 1299.7361 | AE15: 1298.2346 | AF15: 1298.1738 | AG15: 0.061
A16: Plug-in 20 Gasoline Hybrid | B16: Fleet Vehicle Stock: Alternative-Fuel Cars: Plug-in 20 Gasoline Hybrid: Alternative Transportation | C16: AEO.2025.ALTTRNP.ECI_STK_ALF1_FLC_PI20GH_NA_NA_TH.A | D16: thousands | F16: 24.319166 | G16: 28.024124 | H16: 31.654152 | I16: 35.126587 | J16: 37.782135 | K16: 38.713367 | L16: 39.330399 | M16: 39.821682 | N16: 39.222111 | O16: 37.875874 | P16: 37.592007 | Q16: 37.293442 | R16: 37.181023 | S16: 37.163883 | T16: 37.256145 | U16: 37.154495 | V16: 37.032181 | W16: 36.916473 | X16: 36.799957 | Y16: 36.725025 | Z16: 36.56406 | AA16: 36.438702 | AB16: 36.224213 | AC16: 35.973831 | AD16: 35.735878 | AE16: 35.502071 | AF16: 35.428936 | AG16: 0.015
A17: Plug-in 50 Gasoline Hybrid | B17: Fleet Vehicle Stock: Alternative-Fuel Cars: Plug-in 50 Gasoline Hybrid: Alternative Transportation | C17: AEO.2025.ALTTRNP.ECI_STK_ALF1_FLC_PI50GH_NA_NA_TH.A | D17: thousands | F17: 16.713234 | G17: 19.646 | H17: 27.47275 | I17: 34.305477 | J17: 39.878403 | K17: 43.144493 | L17: 45.670815 | M17: 47.934826 | N17: 47.271561 | O17: 44.810276 | P17: 44.349277 | Q17: 43.442249 | R17: 43.14138 | S17: 43.079933 | T17: 43.204563 | U17: 42.328564 | V17: 41.575184 | W17: 40.920044 | X17: 40.343662 | Y17: 39.810692 | Z17: 39.193901 | AA17: 38.606316 | AB17: 37.957912 | AC17: 37.301849 | AD17: 36.676651 | AE17: 36.085972 | AF17: 35.664669 | AG17: 0.03
A18: Electric-Diesel Hybrid | B18: Fleet Vehicle Stock: Alternative-Fuel Cars: Electric-Diesel Hybrid: Alternative Transportation | C18: AEO.2025.ALTTRNP.ECI_STK_ALF1_FLC_EDH_NA_NA_TH.A | D18: thousands | F18: 0 | G18: 0 | H18: 0 | I18: 0 | J18: 0 | K18: 0 | L18: 0 | M18: 0 | N18: 0 | O18: 0 | P18: 0 | Q18: 0 | R18: 0 | S18: 0 | T18: 0 | U18: 0 | V18: 0 | W18: 0 | X18: 0 | Y18: 0 | Z18: 0 | AA18: 0 | AB18: 0 | AC18: 0 | AD18: 0 | AE18: 0 | AF18: 0 | AG18: - -
A19: Electric-Gasoline Hybrid | B19: Fleet Vehicle Stock: Alternative-Fuel Cars: Electric-Gasoline Hybrid: Alternative Transportation | C19: AEO.2025.ALTTRNP.ECI_STK_ALF1_FLC_EGH_NA_NA_TH.A | D19: thousands | F19: 274.11764 | G19: 308.04507 | H19: 323.01923 | I19: 335.71899 | J19: 337.89535 | K19: 341.75336 | L19: 345.65527 | M19: 349.70908 | N19: 346.89227 | O19: 349.15042 | P19: 355.9191 | Q19: 358.72296 | R19: 360.87073 | S19: 363.92602 | T19: 368.21139 | U19: 371.38156 | V19: 372.19873 | W19: 373.74976 | X19: 376.0116 | Y19: 378.73047 | Z19: 381.48401 | AA19: 384.61078 | AB19: 387.44223 | AC19: 389.94586 | AD19: 392.03339 | AE19: 394.1467 | AF19: 397.24316 | AG19: 0.014
A20: Natural Gas ICE | B20: Fleet Vehicle Stock: Alternative-Fuel Cars: Natural Gas ICE: Alternative Transportation | C20: AEO.2025.ALTTRNP.ECI_STK_ALF1_FLC_NGI_NA_NA_TH.A | D20: thousands | F20: 9.965523 | G20: 9.08284 | H20: 8.202013 | I20: 7.321419 | J20: 6.466685 | K20: 5.655651 | L20: 4.984686 | M20: 4.35171 | N20: 3.793523 | O20: 3.313169 | P20: 2.91656 | Q20: 2.58629 | R20: 2.315182 | S20: 2.136791 | T20: 1.984197 | U20: 1.85726 | V20: 1.744241 | W20: 1.638098 | X20: 1.538415 | Y20: 1.444798 | Z20: 1.356878 | AA20: 1.274307 | AB20: 1.196762 | AC20: 1.123936 | AD20: 1.055541 | AE20: 0.991308 | AF20: 0.930984 | AG20: -0.087
A21: Natural Gas Bi-fuel | B21: Fleet Vehicle Stock: Alternative-Fuel Cars: Natural Gas Bi-fuel: Alternative Transportation | C21: AEO.2025.ALTTRNP.ECI_STK_ALF1_FLC_NBF_NA_NA_TH.A | D21: thousands | F21: 0.236445 | G21: 0.222056 | H21: 0.208544 | I21: 0.195853 | J21: 0.183935 | K21: 0.172742 | L21: 0.16223 | M21: 0.152358 | N21: 0.143086 | O21: 0.134379 | P21: 0.126202 | Q21: 0.118522 | R21: 0.11131 | S21: 0.104536 | T21: 0.098175 | U21: 0.092201 | V21: 0.08659 | W21: 0.081321 | X21: 0.076372 | Y21: 0.071725 | Z21: 0.06736 | AA21: 0.063261 | AB21: 0.059411 | AC21: 0.055796 | AD21: 0.0524 | AE21: 0.049212 | AF21: 0.046217 | AG21: -0.061
A22: Propane ICE | B22: Fleet Vehicle Stock: Alternative-Fuel Cars: Propane ICE: Alternative Transportation | C22: AEO.2025.ALTTRNP.ECI_STK_ALF1_FLC_PROP_NA_NA_TH.A | D22: thousands | F22: 1.530565 | G22: 1.330983 | H22: 1.206502 | I22: 1.130379 | J22: 1.061592 | K22: 0.996991 | L22: 0.936321 | M22: 0.879343 | N22: 0.825832 | O22: 0.775578 | P22: 0.728382 | Q22: 0.684058 | R22: 0.642431 | S22: 0.603337 | T22: 0.566622 | U22: 0.532141 | V22: 0.499759 | W22: 0.469347 | X22: 0.440786 | Y22: 0.413963 | Z22: 0.388772 | AA22: 0.365114 | AB22: 0.342896 | AC22: 0.322029 | AD22: 0.302433 | AE22: 0.284029 | AF22: 0.266745 | AG22: -0.065
A23: Propane Bi-fuel | B23: Fleet Vehicle Stock: Alternative-Fuel Cars: Propane Bi-fuel: Alternative Transportation | C23: AEO.2025.ALTTRNP.ECI_STK_ALF1_FLC_PBF_NA_NA_TH.A | D23: thousands | F23: 2.995354 | G23: 2.585502 | H23: 2.306102 | I23: 2.135293 | J23: 1.990221 | K23: 1.86911 | L23: 1.755369 | M23: 1.64855 | N23: 1.54823 | O23: 1.454016 | P23: 1.365535 | Q23: 1.282438 | R23: 1.204397 | S23: 1.131106 | T23: 1.062275 | U23: 0.997633 | V23: 0.936924 | W23: 0.879909 | X23: 0.826364 | Y23: 0.776077 | Z23: 0.72885 | AA23: 0.684498 | AB23: 0.642844 | AC23: 0.603725 | AD23: 0.566987 | AE23: 0.532484 | AF23: 0.50008 | AG23: -0.067
A24: Fuel Cell Methanol | B24: Fleet Vehicle Stock: Alternative-Fuel Cars: Fuel Cell Methanol: Alternative Transportation | C24: AEO.2025.ALTTRNP.ECI_STK_ALF1_FLC_FCLMTH_NA_NA_TH.A | D24: thousands | F24: 0 | G24: 0 | H24: 0 | I24: 0 | J24: 0 | K24: 0 | L24: 0 | M24: 0 | N24: 0 | O24: 0 | P24: 0 | Q24: 0 | R24: 0 | S24: 0 | T24: 0 | U24: 0 | V24: 0 | W24: 0 | X24: 0 | Y24: 0 | Z24: 0 | AA24: 0 | AB24: 0 | AC24: 0 | AD24: 0 | AE24: 0 | AF24: 0 | AG24: - -
A25: Fuel Cell Hydrogen | B25: Fleet Vehicle Stock: Alternative-Fuel Cars: Fuel Cell Hydrogen: Alternative Transportation | C25: AEO.2025.ALTTRNP.ECI_STK_ALF1_FLC_FCH_NA_NA_TH.A | D25: thousands | F25: 0.924456 | G25: 0.877771 | H25: 0.846009 | I25: 0.829878 | J25: 0.815457 | K25: 0.743297 | L25: 0.689152 | M25: 0.632596 | N25: 0.577522 | O25: 0.51954 | P25: 0.467688 | Q25: 0.424328 | R25: 0.382815 | S25: 0.345425 | T25: 0.312347 | U25: 0.283862 | V25: 0.26025 | W25: 0.241506 | X25: 0.226721 | Y25: 0.215305 | Z25: 0.205932 | AA25: 0.198986 | AB25: 0.193849 | AC25: 0.189628 | AD25: 0.186557 | AE25: 0.184422 | AF25: 0.184733 | AG25: -0.06
A26: Total Alternative Cars | B26: Fleet Vehicle Stock: Alternative-Fuel Cars: Total: Alternative Transportation | C26: AEO.2025.ALTTRNP.ECI_STK_ALF1_FLC_NA_NA_NA_TH.A | D26: thousands | F26: 877.6488 | G26: 995.76965 | H26: 1156.0712 | I26: 1321.6973 | J26: 1434.8564 | K26: 1508.4348 | L26: 1584.23 | M26: 1651.8317 | N26: 1741.1105 | O26: 1791.1733 | P26: 1869.0144 | Q26: 1956.9299 | R26: 2031.7703 | S26: 2098.4482 | T26: 2162.4062 | U26: 2234.8132 | V26: 2300.6538 | W26: 2351.8621 | X26: 2392.3718 | Y26: 2428.1411 | Z26: 2458.1536 | AA26: 2487.2405 | AB26: 2509.5962 | AC26: 2525.9939 | AD26: 2537.6641 | AE26: 2546.8818 | AF26: 2562.5862 | AG26: 0.042
A27: Total Car Stock | B27: Fleet Vehicle Stock: Cars: Total: Alternative Transportation | C27: AEO.2025.ALTTRNP.ECI_STK_NA_FLC_NA_NA_NA_TH.A | D27: thousands | F27: 5968.9961 | G27: 5834.6597 | H27: 5707.8486 | I27: 5561.0522 | J27: 5381.499 | K27: 5226.8364 | L27: 5103.0889 | M27: 4984.2925 | N27: 4872.9521 | O27: 4773.71 | P27: 4733.645 | Q27: 4688.8828 | R27: 4637.4932 | S27: 4592.8701 | T27: 4560.9844 | U27: 4539.167 | V27: 4511.5996 | W27: 4479.7959 | X27: 4446.8574 | Y27: 4416.7427 | Z27: 4385.728 | AA27: 4359.792 | AB27: 4329.522 | AC27: 4295.9683 | AD27: 4259.7856 | AE27: 4224.0308 | AF27: 4200.3164 | AG27: -0.013
A28: Light Truck Stock
A29: Conventional Light Trucks
A30: Gasoline ICE Vehicles | B30: Fleet Vehicle Stock: Conventional Light Trucks: Gasoline: Alternative Transportation | C30: AEO.2025.ALTTRNP.ECI_STK_CNV_FLTR_GSL_NA_NA_TH.A | D30: thousands | F30: 8923.6709 | G30: 8934.9297 | H30: 8996.376 | I30: 9034.2822 | J30: 9016.0234 | K30: 8998.5684 | L30: 8953.4844 | M30: 8875.3604 | N30: 8791.2803 | O30: 8767.2148 | P30: 8699.2334 | Q30: 8619.7168 | R30: 8527.5742 | S30: 8429.8213 | T30: 8330.1592 | U30: 8231.0176 | V30: 8138.2236 | W30: 8043.1138 | X30: 7947.3481 | Y30: 7847.0762 | Z30: 7751.6323 | AA30: 7657.0732 | AB30: 7565.3296 | AC30: 7477.5024 | AD30: 7385.4668 | AE30: 7292.4482 | AF30: 7192.48 | AG30: -0.008
A31: TDI Diesel ICE | B31: Fleet Vehicle Stock: Conventional Light Trucks: TDI Diesel: Alternative Transportation | C31: AEO.2025.ALTTRNP.ECI_STK_CNV_FLTR_TDS_NA_NA_TH.A | D31: thousands | F31: 137.9073 | G31: 169.55872 | H31: 195.61638 | I31: 215.70016 | J31: 232.51668 | K31: 248.90654 | L31: 252.89879 | M31: 256.48462 | N31: 259.75922 | O31: 265.14529 | P31: 269.12326 | Q31: 272.22946 | R31: 274.67004 | S31: 275.89349 | T31: 276.39572 | U31: 276.4032 | V31: 276.02859 | W31: 275.10642 | X31: 273.64255 | Y31: 271.65329 | Z31: 269.47427 | AA31: 267.15741 | AB31: 264.77933 | AC31: 262.4809 | AD31: 260.10846 | AE31: 257.75995 | AF31: 255.43459 | AG31: 0.024
A32: Total Conventional Light Trucks | B32: Fleet Vehicle Stock: Conventional Light Trucks: Total: Alternative Transportation | C32: AEO.2025.ALTTRNP.ECI_STK_CNV_FLTR_NA_NA_NA_TH.A | D32: thousands | F32: 9061.5781 | G32: 9104.4883 | H32: 9191.9922 | I32: 9249.9824 | J32: 9248.54 | K32: 9247.4746 | L32: 9206.3828 | M32: 9131.8447 | N32: 9051.0391 | O32: 9032.3604 | P32: 8968.3564 | Q32: 8891.9463 | R32: 8802.2441 | S32: 8705.7148 | T32: 8606.5547 | U32: 8507.4209 | V32: 8414.252 | W32: 8318.2197 | X32: 8220.9902 | Y32: 8118.7295 | Z32: 8021.1064 | AA32: 7924.2305 | AB32: 7830.1089 | AC32: 7739.9834 | AD32: 7645.5752 | AE32: 7550.208 | AF32: 7447.9146 | AG32: -0.008
A33: Alternative-Fuel Light Trucks
A34: Ethanol-Flex Fuel ICE | B34: Fleet Vehicle Stock: Alternative-Fuel Light Trucks: Ethanol-Flex Fuel ICE: Alternative Transportation | C34: AEO.2025.ALTTRNP.ECI_STK_ALF1_FLTR_EFFI_NA_NA_TH.A | D34: thousands | F34: 1155.0413 | G34: 1046.23 | H34: 969.38226 | I34: 895.04504 | J34: 825.72241 | K34: 761.86456 | L34: 689.28485 | M34: 624.50824 | N34: 567.1474 | O34: 519.63403 | P34: 477.88129 | Q34: 441.70361 | R34: 410.44513 | S34: 383.56693 | T34: 360.60861 | U34: 340.47806 | V34: 322.67722 | W34: 306.82074 | X34: 292.65668 | Y34: 279.93524 | Z34: 268.63596 | AA34: 258.40308 | AB34: 249.2202 | AC34: 241.05431 | AD34: 233.56988 | AE34: 226.6743 | AF34: 220.02393 | AG34: -0.062
A35: 100-Mile Electric Vehicle | B35: Fleet Vehicle Stock: Alternative-Fuel Light Trucks: 100-Mile Electric Vehicle: Alternative Transportation | C35: AEO.2025.ALTTRNP.ECI_STK_ALF1_FLTR_100MIEV_NA_NA_TH.A | D35: thousands | F35: 0.304786 | G35: 0.269521 | H35: 0.24009 | I35: 0.214159 | J35: 0.190647 | K35: 0.169484 | L35: 0.15061 | M35: 0.133951 | N35: 0.119401 | O35: 0.106739 | P35: 0.095672 | Q35: 0.086231 | R35: 0.078275 | S35: 0.071275 | T35: 0.064934 | U35: 0.059187 | V35: 0.053976 | W35: 0.049249 | X35: 0.044958 | Y35: 0.041061 | Z35: 0.037521 | AA35: 0.034303 | AB35: 0.031376 | AC35: 0.028712 | AD35: 0.026287 | AE35: 0.024078 | AF35: 0.022065 | AG35: -0.096
A36: 200-Mile Electric Vehicle | B36: Fleet Vehicle Stock: Alternative-Fuel Light Trucks: 200-Mile Electric Vehicle: Alternative Transportation | C36: AEO.2025.ALTTRNP.ECI_STK_ALF1_FLTR_200MIEV_NA_NA_TH.A | D36: thousands | F36: 29.193623 | G36: 46.883118 | H36: 72.163597 | I36: 105.34956 | J36: 137.55737 | K36: 161.12241 | L36: 164.73718 | M36: 171.40036 | N36: 181.32606 | O36: 183.96524 | P36: 189.5007 | Q36: 197.5717 | R36: 207.47743 | S36: 218.45459 | T36: 230.42563 | U36: 243.47865 | V36: 256.97647 | W36: 270.49216 | X36: 283.81 | Y36: 297.20404 | Z36: 310.42215 | AA36: 323.80087 | AB36: 336.92816 | AC36: 349.70023 | AD36: 362.15393 | AE36: 374.3374 | AF36: 387.13504 | AG36: 0.105
A37: 300-Mile Electric Vehicle | B37: Fleet Vehicle Stock: Alternative-Fuel Light Trucks: 300-Mile Electric Vehicle: Alternative Transportation | C37: AEO.2025.ALTTRNP.ECI_STK_ALF1_FLTR_300MIEV_NA_NA_TH.A | D37: thousands | F37: 55.996479 | G37: 101.541 | H37: 164.25482 | I37: 242.84007 | J37: 323.41138 | K37: 390.88373 | L37: 434.73364 | M37: 480.23126 | N37: 529.79413 | O37: 557.75793 | P37: 590.2373 | Q37: 627.13812 | R37: 666.81012 | S37: 707.13928 | T37: 747.65613 | U37: 788.29498 | V37: 827.68964 | W37: 864.98523 | X37: 899.77924 | Y37: 932.42383 | Z37: 962.8761 | AA37: 991.71551 | AB37: 1018.3168 | AC37: 1042.7837 | AD37: 1065.0063 | AE37: 1085.4464 | AF37: 1105.5759 | AG37: 0.122
A38: Plug-in 20 Gasoline Hybrid | B38: Fleet Vehicle Stock: Alternative-Fuel Light Trucks: Plug-in 20 Gasoline Hybrid: Alternative Transportation | C38: AEO.2025.ALTTRNP.ECI_STK_ALF1_FLTR_PI20GH_NA_NA_TH.A | D38: thousands | F38: 97.912819 | G38: 134.01071 | H38: 177.14943 | I38: 219.80748 | J38: 256.24222 | K38: 276.30212 | L38: 301.77991 | M38: 325.33951 | N38: 348.625 | O38: 359.59055 | P38: 374.19547 | Q38: 392.9212 | R38: 409.41354 | S38: 425.30969 | T38: 440.83249 | U38: 456.33038 | V38: 470.58194 | W38: 483.10614 | X38: 493.9057 | Y38: 503.306 | Z38: 511.40454 | AA38: 518.49438 | AB38: 524.45532 | AC38: 529.55365 | AD38: 533.5072 | AE38: 536.76221 | AF38: 539.71234 | AG38: 0.068
A39: Plug-in 50 Gasoline Hybrid | B39: Fleet Vehicle Stock: Alternative-Fuel Light Trucks: Plug-in 50 Gasoline Hybrid: Alternative Transportation | C39: AEO.2025.ALTTRNP.ECI_STK_ALF1_FLTR_PI50GH_NA_NA_TH.A | D39: thousands | F39: 11.816848 | G39: 50.810219 | H39: 73.271744 | I39: 117.07578 | J39: 153.87335 | K39: 174.81276 | L39: 229.11229 | M39: 276.06067 | N39: 319.51801 | O39: 347.21335 | P39: 376.59454 | Q39: 409.30499 | R39: 453.83206 | S39: 494.26196 | T39: 531.9054 | U39: 567.30884 | V39: 600.24634 | W39: 630.32581 | X39: 657.58557 | Y39: 682.30548 | Z39: 704.52814 | AA39: 724.65411 | AB39: 742.43994 | AC39: 758.19849 | AD39: 771.72662 | AE39: 783.56 | AF39: 794.37732 | AG39: 0.176
A40: Electric-Diesel Hybrid | B40: Fleet Vehicle Stock: Alternative-Fuel Light Trucks: Electric-Diesel Hybrid: Alternative Transportation | C40: AEO.2025.ALTTRNP.ECI_STK_ALF1_FLTR_EDH_NA_NA_TH.A | D40: thousands | F40: 0 | G40: 0 | H40: 0 | I40: 0 | J40: 0 | K40: 0 | L40: 0 | M40: 0 | N40: 0 | O40: 0 | P40: 0 | Q40: 0 | R40: 0 | S40: 0 | T40: 0 | U40: 0 | V40: 0 | W40: 0 | X40: 0 | Y40: 0 | Z40: 0 | AA40: 0 | AB40: 0 | AC40: 0 | AD40: 0 | AE40: 0 | AF40: 0 | AG40: - -
A41: Electric-Gasoline Hybrid | B41: Fleet Vehicle Stock: Alternative-Fuel Light Trucks: Electric-Gasoline Hybrid: Alternative Transportation | C41: AEO.2025.ALTTRNP.ECI_STK_ALF1_FLTR_EGH_NA_NA_TH.A | D41: thousands | F41: 333.52344 | G41: 425.20145 | H41: 504.40875 | I41: 570.01074 | J41: 625.60529 | K41: 677.85968 | L41: 738.84222 | M41: 791.16101 | N41: 838.12988 | O41: 892.63708 | P41: 938.61102 | Q41: 981.43957 | R41: 1021.3232 | S41: 1057.8328 | T41: 1091.7021 | U41: 1123.217 | V41: 1153.5466 | W41: 1181.3539 | X41: 1207.1405 | Y41: 1230.2968 | Z41: 1252.8519 | AA41: 1274.3451 | AB41: 1295.3204 | AC41: 1316.118 | AD41: 1335.12 | AE41: 1353.2185 | AF41: 1369.2073 | AG41: 0.056
A42: Natural Gas ICE | B42: Fleet Vehicle Stock: Alternative-Fuel Light Trucks: Natural Gas ICE: Alternative Transportation | C42: AEO.2025.ALTTRNP.ECI_STK_ALF1_FLTR_NGI_NA_NA_TH.A | D42: thousands | F42: 2.455484 | G42: 2.287175 | H42: 2.125243 | I42: 1.971612 | J42: 1.831831 | K42: 1.71017 | L42: 1.595576 | M42: 1.484851 | N42: 1.378731 | O42: 1.278646 | P42: 1.185225 | Q42: 1.098376 | R42: 1.02034 | S42: 0.954854 | T42: 0.893697 | U42: 0.83906 | V42: 0.787774 | W42: 0.739634 | X42: 0.694447 | Y42: 0.652029 | Z42: 0.612212 | AA42: 0.574834 | AB42: 0.539747 | AC42: 0.506809 | AD42: 0.475888 | AE42: 0.446859 | AF42: 0.419608 | AG42: -0.066
A43: Natural Gas Bi-fuel | B43: Fleet Vehicle Stock: Alternative-Fuel Light Trucks: Natural Gas Bi-fuel: Alternative Transportation | C43: AEO.2025.ALTTRNP.ECI_STK_ALF1_FLTR_NBF_NA_NA_TH.A | D43: thousands | F43: 1.849428 | G43: 1.735882 | H43: 1.629331 | I43: 1.529345 | J43: 1.435516 | K43: 1.347464 | L43: 1.264833 | M43: 1.187287 | N43: 1.114512 | O43: 1.046214 | P43: 0.982116 | Q43: 0.921959 | R43: 0.8655 | S43: 0.812511 | T43: 0.762777 | U43: 0.716098 | V43: 0.672286 | W43: 0.631164 | X43: 0.592566 | Y43: 0.556337 | Z43: 0.522331 | AA43: 0.49041 | AB43: 0.460447 | AC43: 0.432322 | AD43: 0.40592 | AE43: 0.381136 | AF43: 0.357871 | AG43: -0.061
A44: Propane ICE | B44: Fleet Vehicle Stock: Alternative-Fuel Light Trucks: Propane ICE: Alternative Transportation | C44: AEO.2025.ALTTRNP.ECI_STK_ALF1_FLTR_PROP_NA_NA_TH.A | D44: thousands | F44: 4.661479 | G44: 4.248101 | H44: 3.931493 | I44: 3.680259 | J44: 3.454406 | K44: 3.242462 | L44: 3.043569 | M44: 2.85692 | N44: 2.681759 | O44: 2.517375 | P44: 2.363102 | Q44: 2.218318 | R44: 2.082437 | S44: 1.954908 | T44: 1.835217 | U44: 1.72288 | V44: 1.617443 | W44: 1.518482 | X44: 1.425597 | Y44: 1.338414 | Z44: 1.256582 | AA44: 1.17977 | AB44: 1.10767 | AC44: 1.039992 | AD44: 0.976463 | AE44: 0.916829 | AF44: 0.860849 | AG44: -0.063
A45: Propane Bi-fuel | B45: Fleet Vehicle Stock: Alternative-Fuel Light Trucks: Propane Bi-fuel: Alternative Transportation | C45: AEO.2025.ALTTRNP.ECI_STK_ALF1_FLTR_PBF_NA_NA_TH.A | D45: thousands | F45: 4.33791 | G45: 4.071579 | H45: 3.821659 | I45: 3.587134 | J45: 3.367053 | K45: 3.160523 | L45: 2.966707 | M45: 2.784818 | N45: 2.614121 | O45: 2.453924 | P45: 2.303579 | Q45: 2.162478 | R45: 2.030051 | S45: 1.905762 | T45: 1.78911 | U45: 1.679623 | V45: 1.57686 | W45: 1.480407 | X45: 1.389874 | Y45: 1.304897 | Z45: 1.225134 | AA45: 1.150264 | AB45: 1.079985 | AC45: 1.014015 | AD45: 0.952089 | AE45: 0.893957 | AF45: 0.839388 | AG45: -0.061
A46: Fuel Cell Methanol | B46: Fleet Vehicle Stock: Alternative-Fuel Light Trucks: Fuel Cell Methanol: Alternative Transportation | C46: AEO.2025.ALTTRNP.ECI_STK_ALF1_FLTR_FCLMTH_NA_NA_TH.A | D46: thousands | F46: 0 | G46: 0 | H46: 0 | I46: 0 | J46: 0 | K46: 0 | L46: 0 | M46: 0 | N46: 0 | O46: 0 | P46: 0 | Q46: 0 | R46: 0 | S46: 0 | T46: 0 | U46: 0 | V46: 0 | W46: 0 | X46: 0 | Y46: 0 | Z46: 0 | AA46: 0 | AB46: 0 | AC46: 0 | AD46: 0 | AE46: 0 | AF46: 0 | AG46: - -
A47: Fuel Cell Hydrogen | B47: Fleet Vehicle Stock: Alternative-Fuel Light Trucks: Fuel Cell Hydrogen: Alternative Transportation | C47: AEO.2025.ALTTRNP.ECI_STK_ALF1_FLTR_FCH_NA_NA_TH.A | D47: thousands | F47: 0 | G47: 0 | H47: 0 | I47: 0 | J47: 0 | K47: 0 | L47: 0 | M47: 0 | N47: 0 | O47: 0 | P47: 0 | Q47: 0 | R47: 0 | S47: 0 | T47: 0 | U47: 0 | V47: 0 | W47: 0 | X47: 0 | Y47: 0 | Z47: 0 | AA47: 0 | AB47: 0 | AC47: 0 | AD47: 0 | AE47: 0 | AF47: 0 | AG47: - -
A48: Total Alternative Light Trucks | B48: Fleet Vehicle Stock: Alternative-Fuel Light Trucks: Total: Alternative Transportation | C48: AEO.2025.ALTTRNP.ECI_STK_ALF1_FLTR_NA_NA_NA_TH.A | D48: thousands | F48: 1697.0936 | G48: 1817.2887 | H48: 1972.3784 | I48: 2161.1111 | J48: 2332.6914 | K48: 2452.4756 | L48: 2567.5112 | M48: 2677.1489 | N48: 2792.4487 | O48: 2868.2007 | P48: 2953.95 | Q48: 3056.5667 | R48: 3175.3782 | S48: 3292.2642 | T48: 3408.4761 | U48: 3524.1248 | V48: 3636.4268 | W48: 3741.5029 | X48: 3839.0251 | Y48: 3929.3643 | Z48: 4014.3726 | AA48: 4094.8428 | AB48: 4169.9004 | AC48: 4240.4302 | AD48: 4303.9209 | AE48: 4362.6616 | AF48: 4418.5317 | AG48: 0.037
A49: Total Light Truck Stock | B49: Fleet Vehicle Stock: Light Trucks: Total: Alternative Transportation | C49: AEO.2025.ALTTRNP.ECI_STK_NA_FLTR_NA_NA_NA_TH.A | D49: thousands | F49: 10758.672 | G49: 10921.777 | H49: 11164.371 | I49: 11411.094 | J49: 11581.231 | K49: 11699.95 | L49: 11773.895 | M49: 11808.994 | N49: 11843.488 | O49: 11900.561 | P49: 11922.307 | Q49: 11948.513 | R49: 11977.622 | S49: 11997.979 | T49: 12015.031 | U49: 12031.546 | V49: 12050.679 | W49: 12059.723 | X49: 12060.016 | Y49: 12048.094 | Z49: 12035.479 | AA49: 12019.073 | AB49: 12000.01 | AC49: 11980.414 | AD49: 11949.496 | AE49: 11912.869 | AF49: 11866.446 | AG49: 0.004
A50: Total Fleet Vehicles | B50: Fleet Stock: Total Fleet Vehicles: Alternative Transportation | C50: AEO.2025.ALTTRNP.ECI_STK_NA_NA_NA_NA_NA_TH.A | D50: thousands | F50: 16727.668 | G50: 16756.438 | H50: 16872.219 | I50: 16972.146 | J50: 16962.73 | K50: 16926.787 | L50: 16876.984 | M50: 16793.287 | N50: 16716.441 | O50: 16674.27 | P50: 16655.951 | Q50: 16637.395 | R50: 16615.115 | S50: 16590.848 | T50: 16576.016 | U50: 16570.713 | V50: 16562.277 | W50: 16539.52 | X50: 16506.873 | Y50: 16464.836 | Z50: 16421.207 | AA50: 16378.865 | AB50: 16329.531 | AC50: 16276.383 | AD50: 16209.281 | AE50: 16136.9 | AF50: 16066.763 | AG50: -0.002
A51: Motor Gasoline | B51: Fleet Stock: Commercial Light Trucks: Gasoline: Alternative Transportation | C51: AEO.2025.ALTTRNP.ECI_STK_NA_CLTR_GSL_NA_NA_TH.A | D51: thousands | F51: 7855.1133 | G51: 7665.2778 | H51: 7542.0371 | I51: 7458.8955 | J51: 7381.9429 | K51: 7305.0781 | L51: 7231.6528 | M51: 7145.1934 | N51: 7057.2056 | O51: 6962.4839 | P51: 6857.5386 | Q51: 6737.0884 | R51: 6609.5176 | S51: 6471.2866 | T51: 6324.4775 | U51: 6176.3608 | V51: 6024.8154 | W51: 5867.7144 | X51: 5707.9419 | Y51: 5552.0723 | Z51: 5403.2842 | AA51: 5252.543 | AB51: 5096.5879 | AC51: 4938.9458 | AD51: 4781.4507 | AE51: 4618.0205 | AF51: 4445.1221 | AG51: -0.022
A52: Diesel | B52: Fleet Stock: Commercial Light Trucks: TDI Diesel: Alternative Transportation | C52: AEO.2025.ALTTRNP.ECI_STK_NA_CLTR_TDS_NA_NA_TH.A | D52: thousands | F52: 5019.1895 | G52: 4921.7593 | H52: 4824.1694 | I52: 4722.1992 | J52: 4612.9482 | K52: 4494.3481 | L52: 4367.1333 | M52: 4225.6899 | N52: 4089.4565 | O52: 3940.4841 | P52: 3786.7537 | Q52: 3621.6907 | R52: 3452.0083 | S52: 3278.1594 | T52: 3098.855 | U52: 2921.9287 | V52: 2743.2478 | W52: 2576.4331 | X52: 2419.2429 | Y52: 2284.1414 | Z52: 2165.0586 | AA52: 2049.0903 | AB52: 1935.6875 | AC52: 1827.8242 | AD52: 1724.5015 | AE52: 1614.9531 | AF52: 1504.0861 | AG52: -0.045
A53: Propane | B53: Fleet Stock: Commercial Light Trucks: Propane: Alternative Transportation | C53: AEO.2025.ALTTRNP.ECI_STK_NA_CLTR_PROP_NA_NA_TH.A | D53: thousands | F53: 0.029177 | G53: 0.027894 | H53: 0.028336 | I53: 0.030077 | J53: 0.032547 | K53: 0.035537 | L53: 0.038737 | M53: 0.042037 | N53: 0.045574 | O53: 0.049295 | P53: 0.05287 | Q53: 0.056437 | R53: 0.060086 | S53: 0.063736 | T53: 0.067338 | U53: 0.070848 | V53: 0.074158 | W53: 0.077238 | X53: 0.080094 | Y53: 0.082703 | Z53: 0.085088 | AA53: 0.087238 | AB53: 0.08915 | AC53: 0.090864 | AD53: 0.092347 | AE53: 0.093638 | AF53: 0.094776 | AG53: 0.046
A54: Compressed/Liquefied Natural Gas | B54: Fleet Stock: Commercial Light Trucks: CNG/LNG: Alternative Transportation | C54: AEO.2025.ALTTRNP.ECI_STK_NA_CLTR_NG_NA_NA_TH.A | D54: thousands | F54: 14.902306 | G54: 17.576094 | H54: 20.585962 | I54: 23.665554 | J54: 26.919802 | K54: 30.452202 | L54: 34.228214 | M54: 38.143215 | N54: 42.358658 | O54: 46.960567 | P54: 52.145309 | Q54: 57.921513 | R54: 64.438721 | S54: 71.862915 | T54: 80.503357 | U54: 90.4198 | V54: 101.53952 | W54: 113.77395 | X54: 126.75431 | Y54: 140.46791 | Z54: 154.8305 | AA54: 169.55554 | AB54: 184.50777 | AC54: 199.62676 | AD54: 214.75409 | AE54: 229.75168 | AF54: 244.68684 | AG54: 0.114
A55: Ethanol-Flex Fuel | B55: Fleet Stock: Commercial Light Trucks: Ethanol Flex: Alternative Transportation | C55: AEO.2025.ALTTRNP.ECI_STK_NA_CLTR_EFFI_NA_NA_TH.A | D55: thousands | F55: 1675.2316 | G55: 1730.675 | H55: 1783.8242 | I55: 1831.4545 | J55: 1871.3369 | K55: 1903.2607 | L55: 1927.7737 | M55: 1944.6532 | N55: 1955.0586 | O55: 1961.6097 | P55: 1964.129 | Q55: 1963.7119 | R55: 1961.6047 | S55: 1957.9948 | T55: 1953.3574 | U55: 1948.3369 | V55: 1942.3993 | W55: 1935.6243 | X55: 1928.5331 | Y55: 1920.6377 | Z55: 1908.7698 | AA55: 1892.4994 | AB55: 1874.248 | AC55: 1852.1631 | AD55: 1827.4487 | AE55: 1796.4149 | AF55: 1764.8702 | AG55: 0.002
A56: Electric | B56: Fleet Stock: Commercial Light Trucks: Electric: Alternative Transportation | C56: AEO.2025.ALTTRNP.ECI_STK_NA_CLTR_ELE_NA_NA_TH.A | D56: thousands | F56: 39.214867 | G56: 55.817169 | H56: 73.137619 | I56: 90.519867 | J56: 107.33844 | K56: 123.80302 | L56: 139.9456 | M56: 159.49374 | N56: 182.79228 | O56: 208.52501 | P56: 238.42693 | Q56: 274.92523 | R56: 317.51724 | S56: 365.99771 | T56: 419.79144 | U56: 478.25217 | V56: 539.66425 | W56: 605.26666 | X56: 673.98651 | Y56: 745.78528 | Z56: 819.63544 | AA56: 893.70117 | AB56: 967.68976 | AC56: 1040.8363 | AD56: 1111.6139 | AE56: 1180.5132 | AF56: 1248.1436 | AG56: 0.142
A57: Plug-in Gasoline Hybrid | B57: Fleet Stock: Commercial Light Trucks: Plug-in Gas: Alternative Transportation | C57: AEO.2025.ALTTRNP.ECI_STK_NA_CLTR_EGH_NA_NA_TH.A | D57: thousands | F57: 0 | G57: 0 | H57: 0 | I57: 0 | J57: 0 | K57: 0 | L57: 0 | M57: 0 | N57: 0 | O57: 0 | P57: 0 | Q57: 0 | R57: 0 | S57: 0 | T57: 0 | U57: 0 | V57: 0 | W57: 0 | X57: 0 | Y57: 0 | Z57: 0 | AA57: 0 | AB57: 0 | AC57: 0 | AD57: 0 | AE57: 0 | AF57: 0 | AG57: - -
A58: Plug-in Diesel Hybrid | B58: Fleet Stock: Commercial Light Trucks: Plug-in Diesel: Alternative Transportation | C58: AEO.2025.ALTTRNP.ECI_STK_NA_CLTR_EDH_NA_NA_TH.A | D58: thousands | F58: 0 | G58: 0 | H58: 0 | I58: 0 | J58: 0 | K58: 0 | L58: 0 | M58: 0 | N58: 0 | O58: 0 | P58: 0 | Q58: 0 | R58: 0 | S58: 0 | T58: 0 | U58: 0 | V58: 0 | W58: 0 | X58: 0 | Y58: 0 | Z58: 0 | AA58: 0 | AB58: 0 | AC58: 0 | AD58: 0 | AE58: 0 | AF58: 0 | AG58: - -
A59: Fuel Cell | B59: Fleet Stock: Commercial Light Trucks: Fuel Cell: Alternative Transportation | C59: AEO.2025.ALTTRNP.ECI_STK_NA_CLTR_FUC_NA_NA_TH.A | D59: thousands | F59: 0 | G59: 0 | H59: 0 | I59: 0 | J59: 0 | K59: 0 | L59: 0 | M59: 0 | N59: 0 | O59: 0 | P59: 0 | Q59: 0 | R59: 0 | S59: 0 | T59: 0 | U59: 0 | V59: 0 | W59: 0 | X59: 0 | Y59: 0 | Z59: 0 | AA59: 0 | AB59: 0 | AC59: 0 | AD59: 0 | AE59: 0 | AF59: 0 | AG59: - -
A60: Fuel Cell Battery Dominant | B60: Fleet Stock: Commercial Light Trucks: Fuel Cell Battery Dominant: Alternative Transportation | C60: AEO.2025.ALTTRNP.ECI_STK_NA_CLTR_FEUCELBATDOM_NA_NA_TH.A | D60: thousands | F60: 0 | G60: 0 | H60: 0 | I60: 0 | J60: 0 | K60: 0 | L60: 0 | M60: 0 | N60: 0 | O60: 0 | P60: 0 | Q60: 0 | R60: 0 | S60: 0 | T60: 0 | U60: 0 | V60: 0 | W60: 0 | X60: 0 | Y60: 0 | Z60: 0 | AA60: 0 | AB60: 0 | AC60: 0 | AD60: 0 | AE60: 0 | AF60: 0 | AG60: - -
A61: Gasoline Hybrid | B61: Fleet Stock: Commercial Light Trucks: Gasoline Hybrid: Alternative Transportation | C61: AEO.2025.ALTTRNP.ECI_STK_NA_CLTR_GASHEV_NA_NA_TH.A | D61: thousands | F61: 0 | G61: 1.863994 | H61: 4.466304 | I61: 8.08147 | J61: 22.056372 | K61: 48.933228 | L61: 87.077995 | M61: 138.11633 | N61: 199.38873 | O61: 268.62094 | P61: 344.7597 | Q61: 431.41666 | R61: 522.13275 | S61: 615.81592 | T61: 715.17798 | U61: 819.8161 | V61: 929.44488 | W61: 1047.6221 | X61: 1170.4961 | Y61: 1294.7874 | Z61: 1421.6793 | AA61: 1552.3092 | AB61: 1686.1538 | AC61: 1823.4325 | AD61: 1960.1687 | AE61: 2097.6841 | AF61: 2239.4131 | AG61: - -
A62: Hydrogen ICE | B62: Fleet Stock: Commercial Light Trucks: Hydrogen ICE: Alternative Transportation | C62: AEO.2025.ALTTRNP.ECI_STK_NA_CLTR_HYDICE_NA_NA_TH.A | D62: thousands | F62: 0 | G62: 0 | H62: 0 | I62: 0 | J62: 0 | K62: 0 | L62: 0 | M62: 0 | N62: 0 | O62: 0 | P62: 0 | Q62: 0 | R62: 0 | S62: 0 | T62: 0 | U62: 0 | V62: 0 | W62: 0 | X62: 0 | Y62: 0 | Z62: 0 | AA62: 0 | AB62: 0 | AC62: 0 | AD62: 0 | AE62: 0 | AF62: 0 | AG62: - -
A63: Total Commercial Light Truck Stock | B63: Fleet Stock: Commercial Light Trucks: Total: Alternative Transportation | C63: AEO.2025.ALTTRNP.ECI_STK_NA_CLTR_NA_NA_NA_TH.A | D63: thousands | F63: 14603.681 | G63: 14392.998 | H63: 14248.249 | I63: 14134.846 | J63: 14022.575 | K63: 13905.91 | L63: 13787.851 | M63: 13651.332 | N63: 13526.306 | O63: 13388.733 | P63: 13243.806 | Q63: 13086.812 | R63: 12927.279 | S63: 12761.182 | T63: 12592.229 | U63: 12435.186 | V63: 12281.186 | W63: 12146.512 | X63: 12027.034 | Y63: 11937.975 | Z63: 11873.344 | AA63: 11809.786 | AB63: 11744.965 | AC63: 11682.919 | AD63: 11620.03 | AE63: 11537.43 | AF63: 11446.417 | AG63: -0.009

Sheet AEO 2025 Table 46
A1: Table 46. Transportation Fleet Car and Truck Vehicle Miles Traveled by Type and Technology
A2: https://www.eia.gov/outlooks/aeo/data/browser/#/?id=56-AEO2025&cases=alttrnp&sourcekey=0
A3: Fri Dec 05 2025 14:51:05 GMT-0800 (Pacific Standard Time)
A4: Source: U.S. Energy Information Administration
B5: full name | C5: api key | D5: units | E5: 2023 | F5: 2024 | G5: 2025 | H5: 2026 | I5: 2027 | J5: 2028 | K5: 2029 | L5: 2030 | M5: 2031 | N5: 2032 | O5: 2033 | P5: 2034 | Q5: 2035 | R5: 2036 | S5: 2037 | T5: 2038 | U5: 2039 | V5: 2040 | W5: 2041 | X5: 2042 | Y5: 2043 | Z5: 2044 | AA5: 2045 | AB5: 2046 | AC5: 2047 | AD5: 2048 | AE5: 2049 | AF5: 2050 | AG5: Growth (2024-2050)
A6: Cars
A7: Conventional Cars
A8: Gasoline ICE Vehicles | B8: Fleet Vehicle Miles Traveled: Conventional Cars: Gasoline: Alternative Transportation | C8: AEO.2025.ALTTRNP.ECI_VMT_CNV_FLC_GSL_NA_NA_BLNMLS.A | D8: billion miles | F8: 50.638138 | G8: 48.885429 | H8: 46.748302 | I8: 44.010258 | J8: 41.474693 | K8: 39.650063 | L8: 38.069546 | M8: 36.528156 | N8: 34.710064 | O8: 33.442505 | P8: 32.505722 | Q8: 31.332033 | R8: 30.183113 | S8: 29.184698 | T8: 28.347183 | U8: 27.496824 | V8: 26.624619 | W8: 25.859491 | X8: 25.193741 | Y8: 24.602196 | Z8: 24.052532 | AA8: 23.561592 | AB8: 23.087154 | AC8: 22.633207 | AD8: 22.193701 | AE8: 21.778999 | AF8: 21.422251 | AG8: -0.033
A9: TDI Diesel ICE | B9: Fleet Vehicle Miles Traveled: Conventional Cars: TDI Diesel: Alternative Transportation | C9: AEO.2025.ALTTRNP.ECI_VMT_CNV_FLC_TDS_NA_NA_BLNMLS.A | D9: billion miles | F9: 0.105861 | G9: 0.092278 | H9: 0.080052 | I9: 0.069002 | J9: 0.058967 | K9: 0.049986 | L9: 0.042128 | M9: 0.035328 | N9: 0.029528 | O9: 0.024714 | P9: 0.020797 | Q9: 0.01767 | R9: 0.015205 | S9: 0.013269 | T9: 0.011756 | U9: 0.010555 | V9: 0.009542 | W9: 0.00865 | X9: 0.00786 | Y9: 0.007155 | Z9: 0.006518 | AA9: 0.00594 | AB9: 0.005416 | AC9: 0.00494 | AD9: 0.004507 | AE9: 0.004115 | AF9: 0.003758 | AG9: -0.12
A10: Total Conventional Cars | B10: Fleet Vehicle Miles Traveled: Conventional Cars: Total: Alternative Transportation | C10: AEO.2025.ALTTRNP.ECI_VMT_CNV_FLC_NA_NA_NA_BLNMLS.A | D10: billion miles | F10: 50.743999 | G10: 48.977707 | H10: 46.828354 | I10: 44.079262 | J10: 41.533661 | K10: 39.70005 | L10: 38.111675 | M10: 36.563484 | N10: 34.739594 | O10: 33.46722 | P10: 32.52652 | Q10: 31.349703 | R10: 30.198318 | S10: 29.197968 | T10: 28.358938 | U10: 27.50738 | V10: 26.634161 | W10: 25.868141 | X10: 25.201601 | Y10: 24.60935 | Z10: 24.05905 | AA10: 23.567532 | AB10: 23.092569 | AC10: 22.638147 | AD10: 22.198208 | AE10: 21.783113 | AF10: 21.426008 | AG10: -0.033
A11: Alternative-Fuel Cars
A12: Ethanol-Flex Fuel ICE | B12: Fleet Vehicle Miles Traveled: Alternative-Fuel Cars: Ethanol-Flex Fuel ICE: Alternative Transportation | C12: AEO.2025.ALTTRNP.ECI_VMT_ALF1_FLC_EFFI_NA_NA_BLNMLS.A | D12: billion miles | F12: 1.60873 | G12: 1.349367 | H12: 1.148253 | I12: 0.978525 | J12: 0.834908 | K12: 0.713506 | L12: 0.611642 | M12: 0.527315 | N12: 0.458747 | O12: 0.406132 | P12: 0.365157 | Q12: 0.333794 | R12: 0.310393 | S12: 0.292113 | T12: 0.277586 | U12: 0.266064 | V12: 0.256561 | W12: 0.24847 | X12: 0.241441 | Y12: 0.235245 | Z12: 0.229762 | AA12: 0.22478 | AB12: 0.220178 | AC12: 0.215927 | AD12: 0.211984 | AE12: 0.208329 | AF12: 0.204917 | AG12: -0.076
A13: 100-Mile Electric Vehicle | B13: Fleet Vehicle Miles Traveled: Alternative-Fuel Cars: 100-Mile Electric Vehicle: Alternative Transportation | C13: AEO.2025.ALTTRNP.ECI_VMT_ALF1_FLC_100MIEV_NA_NA_BLNMLS.A | D13: billion miles | F13: 0.091476 | G13: 0.103355 | H13: 0.104404 | I13: 0.099453 | J13: 0.092524 | K13: 0.087859 | L13: 0.086117 | M13: 0.085204 | N13: 0.084946 | O13: 0.080046 | P13: 0.077999 | Q13: 0.077561 | R13: 0.07815 | S13: 0.079242 | T13: 0.080855 | U13: 0.082913 | V13: 0.083385 | W13: 0.084219 | X13: 0.085324 | Y13: 0.086755 | Z13: 0.087947 | AA13: 0.089177 | AB13: 0.090092 | AC13: 0.090739 | AD13: 0.091296 | AE13: 0.091797 | AF13: 0.092786 | AG13: 0.001
A14: 200-Mile Electric Vehicle | B14: Fleet Vehicle Miles Traveled: Alternative-Fuel Cars: 200-Mile Electric Vehicle: Alternative Transportation | C14: AEO.2025.ALTTRNP.ECI_VMT_ALF1_FLC_200MIEV_NA_NA_BLNMLS.A | D14: billion miles | F14: 0.69234 | G14: 0.907057 | H14: 1.119554 | I14: 1.357645 | J14: 1.514705 | K14: 1.616379 | L14: 1.770032 | M14: 1.928347 | N14: 2.597622 | O14: 3.198941 | P14: 3.726064 | Q14: 4.39206 | R14: 4.890418 | S14: 5.289093 | T14: 5.643422 | U14: 6.182402 | V14: 6.586019 | W14: 6.892321 | X14: 7.128041 | Y14: 7.358798 | Z14: 7.548114 | AA14: 7.739197 | AB14: 7.880906 | AC14: 7.988685 | AD14: 8.08247 | AE14: 8.163729 | AF14: 8.294823 | AG14: 0.1
A15: 300-Mile Electric Vehicle | B15: Fleet Vehicle Miles Traveled: Alternative-Fuel Cars: 300-Mile Electric Vehicle: Alternative Transportation | C15: AEO.2025.ALTTRNP.ECI_VMT_ALF1_FLC_300MIEV_NA_NA_BLNMLS.A | D15: billion miles | F15: 2.689883 | G15: 3.591625 | H15: 5.192752 | I15: 6.853583 | J15: 8.083714 | K15: 8.878894 | L15: 9.623186 | M15: 10.23752 | N15: 10.690363 | O15: 10.662129 | P15: 10.907314 | Q15: 11.172157 | R15: 11.436102 | S15: 11.673954 | T15: 11.908784 | U15: 12.099163 | V15: 12.386237 | W15: 12.585106 | X15: 12.720762 | Y15: 12.807727 | Z15: 12.878695 | AA15: 12.938056 | AB15: 12.977659 | AC15: 12.990113 | AD15: 12.971123 | AE15: 12.942655 | AF15: 12.932833 | AG15: 0.062
A16: Plug-in 20 Gasoline Hybrid | B16: Fleet Vehicle Miles Traveled: Alternative-Fuel Cars: Plug-in 20 Gasoline Hybrid: Alternative Transportation | C16: AEO.2025.ALTTRNP.ECI_VMT_ALF1_FLC_PI20GH_NA_NA_BLNMLS.A | D16: billion miles | F16: 0.186914 | G16: 0.230358 | H16: 0.274778 | I16: 0.316991 | J16: 0.349907 | K16: 0.36467 | L16: 0.375659 | M16: 0.384637 | N16: 0.379512 | O16: 0.364105 | P16: 0.359845 | Q16: 0.354965 | R16: 0.351965 | S16: 0.350024 | T16: 0.34971 | U16: 0.347409 | V16: 0.345481 | W16: 0.344235 | X16: 0.343386 | Y16: 0.343194 | Z16: 0.342145 | AA16: 0.341495 | AB16: 0.339861 | AC16: 0.337805 | AD16: 0.335861 | AE16: 0.333926 | AF16: 0.33367 | AG16: 0.023
A17: Plug-in 50 Gasoline Hybrid | B17: Fleet Vehicle Miles Traveled: Alternative-Fuel Cars: Plug-in 50 Gasoline Hybrid: Alternative Transportation | C17: AEO.2025.ALTTRNP.ECI_VMT_ALF1_FLC_PI50GH_NA_NA_BLNMLS.A | D17: billion miles | F17: 0.129778 | G17: 0.16594 | H17: 0.260833 | I17: 0.343484 | J17: 0.409303 | K17: 0.447779 | L17: 0.478465 | M17: 0.505843 | N17: 0.497671 | O17: 0.466614 | P17: 0.458251 | Q17: 0.444216 | R17: 0.436475 | S17: 0.431416 | T17: 0.429262 | U17: 0.416043 | V17: 0.405494 | W17: 0.397586 | X17: 0.391592 | Y17: 0.386597 | Z17: 0.380941 | AA17: 0.375824 | AB17: 0.37006 | AC17: 0.3642 | AD17: 0.358657 | AE17: 0.353414 | AF17: 0.349994 | AG17: 0.039
A18: Electric-Diesel Hybrid | B18: Fleet Vehicle Miles Traveled: Alternative-Fuel Cars: Electric-Diesel Hybrid: Alternative Transportation | C18: AEO.2025.ALTTRNP.ECI_VMT_ALF1_FLC_EDH_NA_NA_BLNMLS.A | D18: billion miles | F18: 0 | G18: 0 | H18: 0 | I18: 0 | J18: 0 | K18: 0 | L18: 0 | M18: 0 | N18: 0 | O18: 0 | P18: 0 | Q18: 0 | R18: 0 | S18: 0 | T18: 0 | U18: 0 | V18: 0 | W18: 0 | X18: 0 | Y18: 0 | Z18: 0 | AA18: 0 | AB18: 0 | AC18: 0 | AD18: 0 | AE18: 0 | AF18: 0 | AG18: - -
A19: Electric-Gasoline Hybrid | B19: Fleet Vehicle Miles Traveled: Alternative-Fuel Cars: Electric-Gasoline Hybrid: Alternative Transportation | C19: AEO.2025.ALTTRNP.ECI_VMT_ALF1_FLC_EGH_NA_NA_BLNMLS.A | D19: billion miles | F19: 2.719198 | G19: 3.198261 | H19: 3.440154 | I19: 3.633343 | J19: 3.696556 | K19: 3.777752 | L19: 3.853174 | M19: 3.922512 | N19: 3.899574 | O19: 3.932047 | P19: 4.015585 | Q19: 4.045547 | R19: 4.063389 | S19: 4.092539 | T19: 4.13829 | U19: 4.171525 | V19: 4.175678 | W19: 4.190537 | X19: 4.215788 | Y19: 4.24763 | Z19: 4.280001 | AA19: 4.317441 | AB19: 4.351369 | AC19: 4.381361 | AD19: 4.406455 | AE19: 4.431942 | AF19: 4.469773 | AG19: 0.019
A20: Natural Gas ICE | B20: Fleet Vehicle Miles Traveled: Alternative-Fuel Cars: Natural Gas ICE: Alternative Transportation | C20: AEO.2025.ALTTRNP.ECI_VMT_ALF1_FLC_NGI_NA_NA_BLNMLS.A | D20: billion miles | F20: 0.07035 | G20: 0.064103 | H20: 0.057872 | I20: 0.051645 | J20: 0.045604 | K20: 0.039873 | L20: 0.035135 | M20: 0.030666 | N20: 0.026725 | O20: 0.023336 | P20: 0.020537 | Q20: 0.018208 | R20: 0.016296 | S20: 0.015039 | T20: 0.013965 | U20: 0.013071 | V20: 0.012276 | W20: 0.011529 | X20: 0.010827 | Y20: 0.010169 | Z20: 0.00955 | AA20: 0.008969 | AB20: 0.008423 | AC20: 0.00791 | AD20: 0.007429 | AE20: 0.006977 | AF20: 0.006552 | AG20: -0.087
A21: Natural Gas Bi-fuel | B21: Fleet Vehicle Miles Traveled: Alternative-Fuel Cars: Natural Gas Bi-fuel: Alternative Transportation | C21: AEO.2025.ALTTRNP.ECI_VMT_ALF1_FLC_NBF_NA_NA_BLNMLS.A | D21: billion miles | F21: 0.001672 | G21: 0.00157 | H21: 0.001475 | I21: 0.001385 | J21: 0.001301 | K21: 0.001221 | L21: 0.001147 | M21: 0.001077 | N21: 0.001012 | O21: 0.00095 | P21: 0.000892 | Q21: 0.000838 | R21: 0.000787 | S21: 0.000739 | T21: 0.000694 | U21: 0.000652 | V21: 0.000612 | W21: 0.000575 | X21: 0.00054 | Y21: 0.000507 | Z21: 0.000476 | AA21: 0.000447 | AB21: 0.00042 | AC21: 0.000395 | AD21: 0.000371 | AE21: 0.000348 | AF21: 0.000327 | AG21: -0.061
A22: Propane ICE | B22: Fleet Vehicle Miles Traveled: Alternative-Fuel Cars: Propane ICE: Alternative Transportation | C22: AEO.2025.ALTTRNP.ECI_VMT_ALF1_FLC_PROP_NA_NA_BLNMLS.A | D22: billion miles | F22: 0.010722 | G22: 0.009319 | H22: 0.008443 | I22: 0.00791 | J22: 0.007429 | K22: 0.006977 | L22: 0.006552 | M22: 0.006154 | N22: 0.005779 | O22: 0.005428 | P22: 0.005097 | Q22: 0.004787 | R22: 0.004496 | S22: 0.004222 | T22: 0.003965 | U22: 0.003724 | V22: 0.003497 | W22: 0.003285 | X22: 0.003085 | Y22: 0.002897 | Z22: 0.002721 | AA22: 0.002555 | AB22: 0.0024 | AC22: 0.002254 | AD22: 0.002116 | AE22: 0.001988 | AF22: 0.001867 | AG22: -0.065
A23: Propane Bi-fuel | B23: Fleet Vehicle Miles Traveled: Alternative-Fuel Cars: Propane Bi-fuel: Alternative Transportation | C23: AEO.2025.ALTTRNP.ECI_VMT_ALF1_FLC_PBF_NA_NA_BLNMLS.A | D23: billion miles | F23: 0.021012 | G23: 0.018135 | H23: 0.016174 | I23: 0.014974 | J23: 0.013956 | K23: 0.013107 | L23: 0.012309 | M23: 0.01156 | N23: 0.010857 | O23: 0.010196 | P23: 0.009576 | Q23: 0.008993 | R23: 0.008446 | S23: 0.007932 | T23: 0.007449 | U23: 0.006996 | V23: 0.00657 | W23: 0.00617 | X23: 0.005795 | Y23: 0.005442 | Z23: 0.005111 | AA23: 0.0048 | AB23: 0.004508 | AC23: 0.004234 | AD23: 0.003976 | AE23: 0.003734 | AF23: 0.003507 | AG23: -0.067
A24: Fuel Cell Methanol | B24: Fleet Vehicle Miles Traveled: Alternative-Fuel Cars: Fuel Cell Methanol: Alternative Transportation | C24: AEO.2025.ALTTRNP.ECI_VMT_ALF1_FLC_FCLMTH_NA_NA_BLNMLS.A | D24: billion miles | F24: 0 | G24: 0 | H24: 0 | I24: 0 | J24: 0 | K24: 0 | L24: 0 | M24: 0 | N24: 0 | O24: 0 | P24: 0 | Q24: 0 | R24: 0 | S24: 0 | T24: 0 | U24: 0 | V24: 0 | W24: 0 | X24: 0 | Y24: 0 | Z24: 0 | AA24: 0 | AB24: 0 | AC24: 0 | AD24: 0 | AE24: 0 | AF24: 0 | AG24: - -
A25: Fuel Cell Hydrogen | B25: Fleet Vehicle Miles Traveled: Alternative-Fuel Cars: Fuel Cell Hydrogen: Alternative Transportation | C25: AEO.2025.ALTTRNP.ECI_VMT_ALF1_FLC_FCH_NA_NA_BLNMLS.A | D25: billion miles | F25: 0.006357 | G25: 0.006213 | H25: 0.006171 | I25: 0.006233 | J25: 0.006309 | K25: 0.005841 | L25: 0.005506 | M25: 0.005127 | N25: 0.004726 | O25: 0.004261 | P25: 0.003834 | Q25: 0.003477 | R25: 0.003138 | S25: 0.002839 | T25: 0.002582 | U25: 0.002367 | V25: 0.002194 | W25: 0.002059 | X25: 0.001954 | Y25: 0.001875 | Z25: 0.00181 | AA25: 0.001765 | AB25: 0.001733 | AC25: 0.001707 | AD25: 0.001689 | AE25: 0.001679 | AF25: 0.00169 | AG25: -0.05
A26: Total Alternative Cars | B26: Fleet Vehicle Miles Traveled: Alternative-Fuel Cars: Total: Alternative Transportation | C26: AEO.2025.ALTTRNP.ECI_VMT_ALF1_FLC_NA_NA_NA_BLNMLS.A | D26: billion miles | F26: 8.228432 | G26: 9.645304 | H26: 11.630861 | I26: 13.665171 | J26: 15.056215 | K26: 15.953857 | L26: 16.858925 | M26: 17.645962 | N26: 18.657536 | O26: 19.154182 | P26: 19.950153 | Q26: 20.856604 | R26: 21.600054 | S26: 22.239153 | T26: 22.856567 | U26: 23.592329 | V26: 24.264004 | W26: 24.76609 | X26: 25.148533 | Y26: 25.486834 | Z26: 25.767271 | AA26: 26.044504 | AB26: 26.247608 | AC26: 26.38533 | AD26: 26.473429 | AE26: 26.540516 | AF26: 26.692738 | AG26: 0.046
A27: Total Cars | B27: Fleet Vehicle Miles Traveled: Cars: Total: Alternative Transportation | C27: AEO.2025.ALTTRNP.ECI_VMT_NA_FLC_NA_NA_NA_BLNMLS.A | D27: billion miles | F27: 58.972431 | G27: 58.623009 | H27: 58.459213 | I27: 57.744431 | J27: 56.589874 | K27: 55.653908 | L27: 54.9706 | M27: 54.209446 | N27: 53.397129 | O27: 52.621403 | P27: 52.476673 | Q27: 52.206306 | R27: 51.79837 | S27: 51.437119 | T27: 51.215508 | U27: 51.099709 | V27: 50.898163 | W27: 50.634232 | X27: 50.350136 | Y27: 50.096184 | Z27: 49.826321 | AA27: 49.612038 | AB27: 49.340179 | AC27: 49.023476 | AD27: 48.671638 | AE27: 48.323631 | AF27: 48.118744 | AG27: -0.008
A28: Light Trucks
A29: Conventional Light Trucks
A30: Gasoline ICE Vehicles | B30: Fleet Vehicle Miles Traveled: Conventional Light Trucks: Gasoline: Alternative Transportation | C30: AEO.2025.ALTTRNP.ECI_VMT_CNV_FLTR_GSL_NA_NA_BLNMLS.A | D30: billion miles | F30: 102.30257 | G30: 102.95161 | H30: 104.19441 | I30: 104.78728 | J30: 104.69175 | K30: 104.5032 | L30: 103.91902 | M30: 102.89201 | N30: 101.79629 | O30: 101.47959 | P30: 100.64827 | Q30: 99.700119 | R30: 98.631935 | S30: 97.535667 | T30: 96.443092 | U30: 95.375633 | V30: 94.396255 | W30: 93.389618 | X30: 92.375191 | Y30: 91.304207 | Z30: 90.293655 | AA30: 89.291634 | AB30: 88.319 | AC30: 87.38652 | AD30: 86.393738 | AE30: 85.382881 | AF30: 84.28228 | AG30: -0.007
A31: TDI Diesel ICE | B31: Fleet Vehicle Miles Traveled: Conventional Light Trucks: TDI Diesel: Alternative Transportation | C31: AEO.2025.ALTTRNP.ECI_VMT_CNV_FLTR_TDS_NA_NA_BLNMLS.A | D31: billion miles | F31: 1.359491 | G31: 1.759176 | H31: 2.090298 | I31: 2.344992 | J31: 2.565301 | K31: 2.77746 | L31: 2.836845 | M31: 2.880445 | N31: 2.910164 | O31: 2.956955 | P31: 2.98198 | Q31: 2.996848 | R31: 3.007325 | S31: 3.00855 | T31: 3.006333 | U31: 3.002885 | V31: 2.998047 | W31: 2.988549 | X31: 2.973746 | Y31: 2.953374 | Z31: 2.931142 | AA31: 2.907207 | AB31: 2.882267 | AC31: 2.857962 | AD31: 2.83234 | AE31: 2.806638 | AF31: 2.781035 | AG31: 0.028
A32: Total Conventional Light Trucks | B32: Fleet Vehicle Miles Traveled: Conventional Light Trucks: Total: Alternative Transportation | C32: AEO.2025.ALTTRNP.ECI_VMT_CNV_FLTR_NA_NA_NA_BLNMLS.A | D32: billion miles | F32: 103.66206 | G32: 104.71079 | H32: 106.2847 | I32: 107.13228 | J32: 107.25705 | K32: 107.28065 | L32: 106.75587 | M32: 105.77246 | N32: 104.70645 | O32: 104.43655 | P32: 103.63025 | Q32: 102.69697 | R32: 101.63926 | S32: 100.54422 | T32: 99.449425 | U32: 98.378517 | V32: 97.394302 | W32: 96.378166 | X32: 95.348938 | Y32: 94.257584 | Z32: 93.2248 | AA32: 92.198837 | AB32: 91.201263 | AC32: 90.244484 | AD32: 89.226082 | AE32: 88.189522 | AF32: 87.063316 | AG32: -0.007
A33: Alternative-Fuel Light Trucks
A34: Ethanol-Flex Fuel ICE | B34: Fleet Vehicle Miles Traveled: Alternative-Fuel Light Trucks: Ethanol-Flex Fuel ICE: Alternative Transportation | C34: AEO.2025.ALTTRNP.ECI_VMT_ALF1_FLTR_EFFI_NA_NA_BLNMLS.A | D34: billion miles | F34: 12.549169 | G34: 11.12314 | H34: 10.291789 | I34: 9.515945 | J34: 8.831144 | K34: 8.216796 | L34: 7.491927 | M34: 6.845081 | N34: 6.273898 | O34: 5.806192 | P34: 5.393387 | Q34: 5.035523 | R34: 4.727867 | S34: 4.466155 | T34: 4.245849 | U34: 4.055197 | V34: 3.88816 | W34: 3.7396 | X34: 3.606637 | Y34: 3.486419 | Z34: 3.379338 | AA34: 3.281725 | AB34: 3.193632 | AC34: 3.114879 | AD34: 3.041973 | AE34: 2.974228 | AF34: 2.907924 | AG34: -0.055
A35: 100-Mile Electric Vehicle | B35: Fleet Vehicle Miles Traveled: Alternative-Fuel Light Trucks: 100-Mile Electric Vehicle: Alternative Transportation | C35: AEO.2025.ALTTRNP.ECI_VMT_ALF1_FLTR_100MIEV_NA_NA_BLNMLS.A | D35: billion miles | F35: 0.002864 | G35: 0.00254 | H35: 0.00227 | I35: 0.002033 | J35: 0.001817 | K35: 0.001623 | L35: 0.001449 | M35: 0.001295 | N35: 0.00116 | O35: 0.001042 | P35: 0.000938 | Q35: 0.000849 | R35: 0.000773 | S35: 0.000706 | T35: 0.000645 | U35: 0.00059 | V35: 0.00054 | W35: 0.000494 | X35: 0.000452 | Y35: 0.000414 | Z35: 0.000379 | AA35: 0.000348 | AB35: 0.000319 | AC35: 0.000293 | AD35: 0.000269 | AE35: 0.000247 | AF35: 0.000227 | AG35: -0.093
A36: 200-Mile Electric Vehicle | B36: Fleet Vehicle Miles Traveled: Alternative-Fuel Light Trucks: 200-Mile Electric Vehicle: Alternative Transportation | C36: AEO.2025.ALTTRNP.ECI_VMT_ALF1_FLTR_200MIEV_NA_NA_BLNMLS.A | D36: billion miles | F36: 0.29653 | G36: 0.503099 | H36: 0.801672 | I36: 1.192376 | J36: 1.572093 | K36: 1.852342 | L36: 1.904124 | M36: 1.986903 | N36: 2.10091 | O36: 2.116401 | P36: 2.155784 | Q36: 2.221788 | R36: 2.310524 | S36: 2.415476 | T36: 2.538403 | U36: 2.680203 | V36: 2.831894 | W36: 2.986858 | X36: 3.140987 | Y36: 3.296113 | Z36: 3.448157 | AA36: 3.60026 | AB36: 3.747308 | AC36: 3.888177 | AD36: 4.023553 | AE36: 4.154433 | AF36: 4.291629 | AG36: 0.108
A37: 300-Mile Electric Vehicle | B37: Fleet Vehicle Miles Traveled: Alternative-Fuel Light Trucks: 300-Mile Electric Vehicle: Alternative Transportation | C37: AEO.2025.ALTTRNP.ECI_VMT_ALF1_FLTR_300MIEV_NA_NA_BLNMLS.A | D37: billion miles | F37: 0.562532 | G37: 1.146296 | H37: 1.929759 | I37: 2.875116 | J37: 3.82409 | K37: 4.634307 | L37: 5.14358 | M37: 5.659524 | N37: 6.202487 | O37: 6.466924 | P37: 6.762447 | Q37: 7.101348 | R37: 7.472496 | S37: 7.855645 | T37: 8.252182 | U37: 8.663074 | V37: 9.071511 | W37: 9.465399 | X37: 9.837065 | Y37: 10.187685 | Z37: 10.514441 | AA37: 10.822344 | AB37: 11.10339 | AC37: 11.358796 | AD37: 11.58757 | AE37: 11.795613 | AF37: 12.000555 | AG37: 0.125
A38: Plug-in 20 Gasoline Hybrid | B38: Fleet Vehicle Miles Traveled: Alternative-Fuel Light Trucks: Plug-in 20 Gasoline Hybrid: Alternative Transportation | C38: AEO.2025.ALTTRNP.ECI_VMT_ALF1_FLTR_PI20GH_NA_NA_BLNMLS.A | D38: billion miles | F38: 1.185069 | G38: 1.638773 | H38: 2.173618 | I38: 2.697939 | J38: 3.138126 | K38: 3.370377 | L38: 3.668004 | M38: 3.940813 | N38: 4.205166 | O38: 4.304063 | P38: 4.448557 | Q38: 4.645327 | R38: 4.815012 | S38: 4.97582 | T38: 5.13379 | U38: 5.295006 | V38: 5.444161 | W38: 5.575405 | X38: 5.688892 | Y38: 5.788318 | Z38: 5.874136 | AA38: 5.949247 | AB38: 6.011307 | AC38: 6.063359 | AD38: 6.101553 | AE38: 6.131683 | AF38: 6.159 | AG38: 0.065
A39: Plug-in 50 Gasoline Hybrid | B39: Fleet Vehicle Miles Traveled: Alternative-Fuel Light Trucks: Plug-in 50 Gasoline Hybrid: Alternative Transportation | C39: AEO.2025.ALTTRNP.ECI_VMT_ALF1_FLTR_PI50GH_NA_NA_BLNMLS.A | D39: billion miles | F39: 0.123646 | G39: 0.600588 | H39: 0.872362 | I39: 1.423158 | J39: 1.879161 | K39: 2.13104 | L39: 2.782913 | M39: 3.344786 | N39: 3.85754 | O39: 4.165747 | P39: 4.498634 | Q39: 4.871407 | R39: 5.382845 | S39: 5.834639 | T39: 6.244909 | U39: 6.626042 | V39: 6.979941 | W39: 7.301455 | X39: 7.59064 | Y39: 7.85028 | Z39: 8.08006 | AA39: 8.285561 | AB39: 8.464336 | AC39: 8.620812 | AD39: 8.752918 | AE39: 8.867428 | AF39: 8.97303 | AG39: 0.179
A40: Electric-Diesel Hybrid | B40: Fleet Vehicle Miles Traveled: Alternative-Fuel Light Trucks: Electric-Diesel Hybrid: Alternative Transportation | C40: AEO.2025.ALTTRNP.ECI_VMT_ALF1_FLTR_EDH_NA_NA_BLNMLS.A | D40: billion miles | F40: 0 | G40: 0 | H40: 0 | I40: 0 | J40: 0 | K40: 0 | L40: 0 | M40: 0 | N40: 0 | O40: 0 | P40: 0 | Q40: 0 | R40: 0 | S40: 0 | T40: 0 | U40: 0 | V40: 0 | W40: 0 | X40: 0 | Y40: 0 | Z40: 0 | AA40: 0 | AB40: 0 | AC40: 0 | AD40: 0 | AE40: 0 | AF40: 0 | AG40: - -
A41: Electric-Gasoline Hybrid | B41: Fleet Vehicle Miles Traveled: Alternative-Fuel Light Trucks: Electric-Gasoline Hybrid: Alternative Transportation | C41: AEO.2025.ALTTRNP.ECI_VMT_ALF1_FLTR_EGH_NA_NA_BLNMLS.A | D41: billion miles | F41: 3.90082 | G41: 5.062801 | H41: 6.116351 | I41: 6.91056 | J41: 7.566715 | K41: 8.163843 | L41: 8.83587 | M41: 9.387321 | N41: 9.861605 | O41: 10.421856 | P41: 10.881164 | Q41: 11.30842 | R41: 11.709387 | S41: 12.07926 | T41: 12.424689 | U41: 12.748823 | V41: 13.065034 | W41: 13.356117 | X41: 13.627514 | Y41: 13.871776 | Z41: 14.11332 | AA41: 14.345657 | AB41: 14.574265 | AC41: 14.802521 | AD41: 15.010236 | AE41: 15.208282 | AF41: 15.382316 | AG41: 0.054
A42: Natural Gas ICE | B42: Fleet Vehicle Miles Traveled: Alternative-Fuel Light Trucks: Natural Gas ICE: Alternative Transportation | C42: AEO.2025.ALTTRNP.ECI_VMT_ALF1_FLTR_NGI_NA_NA_BLNMLS.A | D42: billion miles | F42: 0.023479 | G42: 0.021859 | H42: 0.020301 | I42: 0.018825 | J42: 0.017481 | K42: 0.016312 | L42: 0.015211 | M42: 0.014148 | N42: 0.01313 | O42: 0.01217 | P42: 0.011275 | Q42: 0.010444 | R42: 0.009697 | S42: 0.00907 | T42: 0.008484 | U42: 0.007961 | V42: 0.007471 | W42: 0.007011 | X42: 0.006579 | Y42: 0.006174 | Z42: 0.005794 | AA42: 0.005437 | AB42: 0.005103 | AC42: 0.004789 | AD42: 0.004494 | AE42: 0.004218 | AF42: 0.003959 | AG42: -0.066
A43: Natural Gas Bi-fuel | B43: Fleet Vehicle Miles Traveled: Alternative-Fuel Light Trucks: Natural Gas Bi-fuel: Alternative Transportation | C43: AEO.2025.ALTTRNP.ECI_VMT_ALF1_FLTR_NBF_NA_NA_BLNMLS.A | D43: billion miles | F43: 0.017728 | G43: 0.016631 | H43: 0.015601 | I43: 0.014636 | J43: 0.013731 | K43: 0.012882 | L43: 0.012085 | M43: 0.011338 | N43: 0.010638 | O43: 0.009981 | P43: 0.009364 | Q43: 0.008786 | R43: 0.008244 | S43: 0.007735 | T43: 0.007258 | U43: 0.00681 | V43: 0.00639 | W43: 0.005996 | X43: 0.005626 | Y43: 0.005279 | Z43: 0.004954 | AA43: 0.004649 | AB43: 0.004363 | AC43: 0.004094 | AD43: 0.003842 | AE43: 0.003606 | AF43: 0.003384 | AG43: -0.062
A44: Propane ICE | B44: Fleet Vehicle Miles Traveled: Alternative-Fuel Light Trucks: Propane ICE: Alternative Transportation | C44: AEO.2025.ALTTRNP.ECI_VMT_ALF1_FLTR_PROP_NA_NA_BLNMLS.A | D44: billion miles | F44: 0.044715 | G44: 0.040725 | H44: 0.037668 | I44: 0.035243 | J44: 0.033062 | K44: 0.031017 | L44: 0.029099 | M44: 0.0273 | N44: 0.025613 | O44: 0.02403 | P44: 0.022545 | Q44: 0.021153 | R44: 0.019846 | S44: 0.018621 | T44: 0.017472 | U44: 0.016394 | V44: 0.015382 | W44: 0.014434 | X44: 0.013544 | Y44: 0.012709 | Z44: 0.011925 | AA44: 0.011191 | AB44: 0.010501 | AC44: 0.009854 | AD44: 0.009248 | AE44: 0.008678 | AF44: 0.008144 | AG44: -0.063
A45: Propane Bi-fuel | B45: Fleet Vehicle Miles Traveled: Alternative-Fuel Light Trucks: Propane Bi-fuel: Alternative Transportation | C45: AEO.2025.ALTTRNP.ECI_VMT_ALF1_FLTR_PBF_NA_NA_BLNMLS.A | D45: billion miles | F45: 0.041583 | G45: 0.039009 | H45: 0.036595 | I45: 0.034331 | J45: 0.032207 | K45: 0.030215 | L45: 0.028347 | M45: 0.026595 | N45: 0.024952 | O45: 0.02341 | P45: 0.021964 | Q45: 0.020608 | R45: 0.019336 | S45: 0.018142 | T45: 0.017023 | U45: 0.015973 | V45: 0.014988 | W45: 0.014064 | X45: 0.013197 | Y45: 0.012383 | Z45: 0.01162 | AA45: 0.010904 | AB45: 0.010233 | AC45: 0.009603 | AD45: 0.009012 | AE45: 0.008457 | AF45: 0.007937 | AG45: -0.062
A46: Fuel Cell Methanol | B46: Fleet Vehicle Miles Traveled: Alternative-Fuel Light Trucks: Fuel Cell Methanol: Alternative Transportation | C46: AEO.2025.ALTTRNP.ECI_VMT_ALF1_FLTR_FCLMTH_NA_NA_BLNMLS.A | D46: billion miles | F46: 0 | G46: 0 | H46: 0 | I46: 0 | J46: 0 | K46: 0 | L46: 0 | M46: 0 | N46: 0 | O46: 0 | P46: 0 | Q46: 0 | R46: 0 | S46: 0 | T46: 0 | U46: 0 | V46: 0 | W46: 0 | X46: 0 | Y46: 0 | Z46: 0 | AA46: 0 | AB46: 0 | AC46: 0 | AD46: 0 | AE46: 0 | AF46: 0 | AG46: - -
A47: Fuel Cell Hydrogen | B47: Fleet Vehicle Miles Traveled: Alternative-Fuel Light Trucks: Fuel Cell Hydrogen: Alternative Transportation | C47: AEO.2025.ALTTRNP.ECI_VMT_ALF1_FLTR_FCH_NA_NA_BLNMLS.A | D47: billion miles | F47: 0 | G47: 0 | H47: 0 | I47: 0 | J47: 0 | K47: 0 | L47: 0 | M47: 0 | N47: 0 | O47: 0 | P47: 0 | Q47: 0 | R47: 0 | S47: 0 | T47: 0 | U47: 0 | V47: 0 | W47: 0 | X47: 0 | Y47: 0 | Z47: 0 | AA47: 0 | AB47: 0 | AC47: 0 | AD47: 0 | AE47: 0 | AF47: 0 | AG47: - -
A48: Total Alternative Light Trucks | B48: Fleet Vehicle Miles Traveled: Alternative-Fuel Light Trucks: Total: Alternative Transportation | C48: AEO.2025.ALTTRNP.ECI_VMT_ALF1_FLTR_NA_NA_NA_BLNMLS.A | D48: billion miles | F48: 18.748137 | G48: 20.195459 | H48: 22.297987 | I48: 24.720163 | J48: 26.90963 | K48: 28.460754 | L48: 29.912609 | M48: 31.245108 | N48: 32.577095 | O48: 33.351818 | P48: 34.206062 | Q48: 35.245651 | R48: 36.476028 | S48: 37.681267 | T48: 38.890701 | U48: 40.116074 | V48: 41.325466 | W48: 42.466835 | X48: 43.531128 | Y48: 44.517548 | Z48: 45.444122 | AA48: 46.317329 | AB48: 47.124756 | AC48: 47.877171 | AD48: 48.544662 | AE48: 49.156872 | AF48: 49.738106 | AG48: 0.038
A49: Total Light Trucks | B49: Fleet Vehicle Miles Traveled: Light Trucks: Total: Alternative Transportation | C49: AEO.2025.ALTTRNP.ECI_VMT_NA_FLTR_NA_NA_NA_BLNMLS.A | D49: billion miles | F49: 122.41019 | G49: 124.90625 | H49: 128.58269 | I49: 131.85245 | J49: 134.16669 | K49: 135.74141 | L49: 136.66847 | M49: 137.01756 | N49: 137.28354 | O49: 137.78836 | P49: 137.8363 | Q49: 137.94263 | R49: 138.1153 | S49: 138.22549 | T49: 138.34012 | U49: 138.4946 | V49: 138.71977 | W49: 138.845 | X49: 138.88007 | Y49: 138.77513 | Z49: 138.66891 | AA49: 138.51617 | AB49: 138.32602 | AC49: 138.12166 | AD49: 137.77075 | AE49: 137.34639 | AF49: 136.80142 | AG49: 0.004
A50: Total Fleet Vehicles | B50: Fleet Vehicle Miles Traveled: Total Fleet Vehicles: Alternative Transportation | C50: AEO.2025.ALTTRNP.ECI_VMT_NA_NA_NA_NA_NA_BLNMLS.A | D50: billion miles | F50: 181.38263 | G50: 183.52927 | H50: 187.0419 | I50: 189.59688 | J50: 190.75656 | K50: 191.39533 | L50: 191.63907 | M50: 191.227 | N50: 190.68066 | O50: 190.40976 | P50: 190.31297 | Q50: 190.14893 | R50: 189.91367 | S50: 189.66261 | T50: 189.55563 | U50: 189.5943 | V50: 189.61793 | W50: 189.47923 | X50: 189.23019 | Y50: 188.87131 | Z50: 188.49524 | AA50: 188.1282 | AB50: 187.6662 | AC50: 187.14514 | AD50: 186.44238 | AE50: 185.67001 | AF50: 184.92017 | AG50: 0.001
A51: Motor Gasoline | B51: Fleet Vehicle Miles Traveled: Commercial Light Trucks: Gasoline: Alternative Transportation | C51: AEO.2025.ALTTRNP.ECI_VMT_NA_CLTR_GSL_NA_NA_BLNMLS.A | D51: billion miles | F51: 48.625702 | G51: 48.193687 | H51: 48.078758 | I51: 48.138134 | J51: 48.120186 | K51: 48.007374 | L51: 47.782375 | M51: 47.378162 | N51: 46.818668 | O51: 46.128166 | P51: 45.328541 | Q51: 44.387264 | R51: 43.341335 | S51: 42.20546 | T51: 40.974621 | U51: 39.680935 | V51: 38.330078 | W51: 36.894836 | X51: 35.427395 | Y51: 33.948071 | Z51: 32.468719 | AA51: 30.997244 | AB51: 29.535336 | AC51: 28.095951 | AD51: 26.691463 | AE51: 25.318233 | AF51: 23.955311 | AG51: -0.027
A52: Diesel | B52: Fleet Vehicle Miles Traveled: Commercial Light Trucks: TDI Diesel: Alternative Transportation | C52: AEO.2025.ALTTRNP.ECI_VMT_NA_CLTR_TDS_NA_NA_BLNMLS.A | D52: billion miles | F52: 27.953878 | G52: 26.656334 | H52: 25.340389 | I52: 24.262241 | J52: 23.059395 | K52: 21.850712 | L52: 20.794621 | M52: 19.689993 | N52: 18.581825 | O52: 17.529572 | P52: 16.470074 | Q52: 15.438552 | R52: 14.441746 | S52: 13.511394 | T52: 12.624192 | U52: 11.791507 | V52: 11.019337 | W52: 10.284483 | X52: 9.618806 | Y52: 8.988319 | Z52: 8.412736 | AA52: 7.847524 | AB52: 7.324625 | AC52: 6.80603 | AD52: 6.3243 | AE52: 5.863793 | AF52: 5.40586 | AG52: -0.061
A53: Propane | B53: Fleet Vehicle Miles Traveled: Commercial Light Trucks: Propane: Alternative Transportation | C53: AEO.2025.ALTTRNP.ECI_VMT_NA_CLTR_PROP_NA_NA_BLNMLS.A | D53: billion miles | F53: 9.6e-05 | G53: 0.000128 | H53: 0.000164 | I53: 0.000205 | J53: 0.000247 | K53: 0.00029 | L53: 0.000333 | M53: 0.000366 | N53: 0.0004 | O53: 0.000429 | P53: 0.000456 | Q53: 0.000481 | R53: 0.000505 | S53: 0.000527 | T53: 0.000547 | U53: 0.000565 | V53: 0.000581 | W53: 0.000595 | X53: 0.000607 | Y53: 0.000616 | Z53: 0.000624 | AA53: 0.00063 | AB53: 0.000635 | AC53: 0.000639 | AD53: 0.000641 | AE53: 0.000642 | AF53: 0.000643 | AG53: 0.076
A54: Compressed/Liquefied Natural Gas | B54: Fleet Vehicle Miles Traveled: Commercial Light Trucks: CNG/LNG: Alternative Transportation | C54: AEO.2025.ALTTRNP.ECI_VMT_NA_CLTR_NG_NA_NA_BLNMLS.A | D54: billion miles | F54: 0.114205 | G54: 0.148856 | H54: 0.190802 | I54: 0.235172 | J54: 0.284449 | K54: 0.341472 | L54: 0.402231 | M54: 0.456584 | N54: 0.514632 | O54: 0.572505 | P54: 0.632377 | Q54: 0.690636 | R54: 0.74982 | S54: 0.812388 | T54: 0.884263 | U54: 0.966022 | V54: 1.057511 | W54: 1.157474 | X54: 1.260321 | Y54: 1.365352 | Z54: 1.474288 | AA54: 1.582663 | AB54: 1.690095 | AC54: 1.798157 | AD54: 1.903461 | AE54: 2.00663 | AF54: 2.104888 | AG54: 0.119
A55: Ethanol-Flex Fuel | B55: Fleet Vehicle Miles Traveled: Commercial Light Trucks: Ethanol Flex: Alternative Transportation | C55: AEO.2025.ALTTRNP.ECI_VMT_NA_CLTR_EFFI_NA_NA_BLNMLS.A | D55: billion miles | F55: 13.189996 | G55: 13.193671 | H55: 13.121983 | I55: 13.17378 | J55: 13.154181 | K55: 13.184876 | L55: 13.128769 | M55: 13.043101 | N55: 12.913555 | O55: 12.779474 | P55: 12.625202 | Q55: 12.48172 | R55: 12.34839 | S55: 12.232133 | T55: 12.129589 | U55: 12.031537 | V55: 11.944037 | W55: 11.839661 | X55: 11.745772 | Y55: 11.627108 | Z55: 11.513198 | AA55: 11.378852 | AB55: 11.251727 | AC55: 11.10753 | AD55: 10.963563 | AE55: 10.807909 | AF55: 10.659618 | AG55: -0.008
A56: Electric | B56: Fleet Vehicle Miles Traveled: Commercial Light Trucks: Electric: Alternative Transportation | C56: AEO.2025.ALTTRNP.ECI_VMT_NA_CLTR_ELE_NA_NA_BLNMLS.A | D56: billion miles | F56: 0.350782 | G56: 0.506953 | H56: 0.673135 | I56: 0.845497 | J56: 1.012219 | K56: 1.159367 | L56: 1.29729 | M56: 1.441472 | N56: 1.601266 | O56: 1.766811 | P56: 1.954924 | Q56: 2.181898 | R56: 2.446064 | S56: 2.746255 | T56: 3.077681 | U56: 3.436196 | V56: 3.81223 | W56: 4.211496 | X56: 4.624531 | Y56: 5.05248 | Z56: 5.4872 | AA56: 5.915392 | AB56: 6.335355 | AC56: 6.744765 | AD56: 7.130292 | AE56: 7.496801 | AF56: 7.844782 | AG56: 0.127
A57: Plug-in Gasoline Hybrid | B57: Fleet Vehicle Miles Traveled: Commercial Light Trucks: Plug-in Gas: Alternative Transportation | C57: AEO.2025.ALTTRNP.ECI_VMT_NA_CLTR_EGH_NA_NA_BLNMLS.A | D57: billion miles | F57: 0 | G57: 0 | H57: 0 | I57: 0 | J57: 0 | K57: 0 | L57: 0 | M57: 0 | N57: 0 | O57: 0 | P57: 0 | Q57: 0 | R57: 0 | S57: 0 | T57: 0 | U57: 0 | V57: 0 | W57: 0 | X57: 0 | Y57: 0 | Z57: 0 | AA57: 0 | AB57: 0 | AC57: 0 | AD57: 0 | AE57: 0 | AF57: 0 | AG57: - -
A58: Plug-in Diesel Hybrid | B58: Fleet Vehicle Miles Traveled: Commercial Light Trucks: Plug-in Diesel: Alternative Transportation | C58: AEO.2025.ALTTRNP.ECI_VMT_NA_CLTR_EDH_NA_NA_BLNMLS.A | D58: billion miles | F58: 0 | G58: 0 | H58: 0 | I58: 0 | J58: 0 | K58: 0 | L58: 0 | M58: 0 | N58: 0 | O58: 0 | P58: 0 | Q58: 0 | R58: 0 | S58: 0 | T58: 0 | U58: 0 | V58: 0 | W58: 0 | X58: 0 | Y58: 0 | Z58: 0 | AA58: 0 | AB58: 0 | AC58: 0 | AD58: 0 | AE58: 0 | AF58: 0 | AG58: - -
A59: Fuel Cell | B59: Fleet Vehicle Miles Traveled: Commercial Light Trucks: Fuel Cell: Alternative Transportation | C59: AEO.2025.ALTTRNP.ECI_VMT_NA_CLTR_FUC_NA_NA_BLNMLS.A | D59: billion miles | F59: 0 | G59: 0 | H59: 0 | I59: 0 | J59: 0 | K59: 0 | L59: 0 | M59: 0 | N59: 0 | O59: 0 | P59: 0 | Q59: 0 | R59: 0 | S59: 0 | T59: 0 | U59: 0 | V59: 0 | W59: 0 | X59: 0 | Y59: 0 | Z59: 0 | AA59: 0 | AB59: 0 | AC59: 0 | AD59: 0 | AE59: 0 | AF59: 0 | AG59: - -
A60: Fuel Cell Battery Dominant | B60: Fleet Vehicle Miles Traveled: Commercial Light Trucks: Fuel Cell Battery Dominant: Alternative Transportation | C60: AEO.2025.ALTTRNP.ECI_VMT_NA_CLTR_FEUCELBATDOM_NA_NA_BLNMLS.A | D60: billion miles | F60: 0 | G60: 0 | H60: 0 | I60: 0 | J60: 0 | K60: 0 | L60: 0 | M60: 0 | N60: 0 | O60: 0 | P60: 0 | Q60: 0 | R60: 0 | S60: 0 | T60: 0 | U60: 0 | V60: 0 | W60: 0 | X60: 0 | Y60: 0 | Z60: 0 | AA60: 0 | AB60: 0 | AC60: 0 | AD60: 0 | AE60: 0 | AF60: 0 | AG60: - -
A61: Gasoline Hybrid | B61: Fleet Vehicle Miles Traveled: Commercial Light Trucks: Gasoline Hybrid: Alternative Transportation | C61: AEO.2025.ALTTRNP.ECI_VMT_NA_CLTR_GASHEV_NA_NA_BLNMLS.A | D61: billion miles | F61: 0 | G61: 0.04642 | H61: 0.119693 | I61: 0.22437 | J61: 0.515448 | K61: 1.007321 | L61: 1.682852 | M61: 2.546169 | N61: 3.582861 | O61: 4.765699 | P61: 6.031436 | Q61: 7.357562 | R61: 8.686054 | S61: 9.991514 | T61: 11.285845 | U61: 12.55304 | V61: 13.790806 | W61: 15.02157 | X61: 16.206757 | Y61: 17.344572 | Z61: 18.450102 | AA61: 19.51713 | AB61: 20.542418 | AC61: 21.528131 | AD61: 22.438059 | AE61: 23.298126 | AF61: 24.146671 | AG61: - -
A62: Hydrogen ICE | B62: Fleet Vehicle Miles Traveled: Commercial Light Trucks: Hydrogen ICE: Alternative Transportation | C62: AEO.2025.ALTTRNP.ECI_VMT_NA_CLTR_HYDICE_NA_NA_BLNMLS.A | D62: billion miles | F62: 0 | G62: 0 | H62: 0 | I62: 0 | J62: 0 | K62: 0 | L62: 0 | M62: 0 | N62: 0 | O62: 0 | P62: 0 | Q62: 0 | R62: 0 | S62: 0 | T62: 0 | U62: 0 | V62: 0 | W62: 0 | X62: 0 | Y62: 0 | Z62: 0 | AA62: 0 | AB62: 0 | AC62: 0 | AD62: 0 | AE62: 0 | AF62: 0 | AG62: - -
A63: Total Commercial Light Trucks | B63: Fleet Vehicle Miles Traveled: Commercial Light Trucks: Total: Alternative Transportation | C63: AEO.2025.ALTTRNP.ECI_VMT_NA_CLTR_NA_NA_NA_BLNMLS.A | D63: billion miles | F63: 90.234665 | G63: 88.746048 | H63: 87.52491 | I63: 86.879402 | J63: 86.146126 | K63: 85.551414 | L63: 85.08847 | M63: 84.55584 | N63: 84.013214 | O63: 83.542648 | P63: 83.043015 | Q63: 82.538116 | R63: 82.013916 | S63: 81.499672 | T63: 80.97673 | U63: 80.459801 | V63: 79.954575 | W63: 79.410118 | X63: 78.884186 | Y63: 78.326515 | Z63: 77.80687 | AA63: 77.239441 | AB63: 76.680183 | AC63: 76.0812 | AD63: 75.451775 | AE63: 74.79213 | AF63: 74.117767 | AG63: -0.008

Sheet AEO 2025 Table 47
A1: Table 47. Air Travel Energy Use
A2: https://www.eia.gov/outlooks/aeo/data/browser/#/?id=57-AEO2025&cases=alttrnp&sourcekey=0
A3: Fri Dec 05 2025 14:51:22 GMT-0800 (Pacific Standard Time)
A4: Source: U.S. Energy Information Administration
B5: full name | C5: api key | D5: units | E5: 2023 | F5: 2024 | G5: 2025 | H5: 2026 | I5: 2027 | J5: 2028 | K5: 2029 | L5: 2030 | M5: 2031 | N5: 2032 | O5: 2033 | P5: 2034 | Q5: 2035 | R5: 2036 | S5: 2037 | T5: 2038 | U5: 2039 | V5: 2040 | W5: 2041 | X5: 2042 | Y5: 2043 | Z5: 2044 | AA5: 2045 | AB5: 2046 | AC5: 2047 | AD5: 2048 | AE5: 2049 | AF5: 2050 | AG5: Growth (2024-2050)
A6: Fuel Cost (1987 dollars per MMBtu) | B6: Air Travel: Fuel Cost: Alternative Transportation | C6: AEO.2025.ALTTRNP.PRCE_FUL_AIRT_NA_NA_NA_NA_87DLRPMBTU.A | D6: 1987 $/MMBtu | F6: 7.491065 | G6: 6.962784 | H6: 6.897642 | I6: 7.05128 | J6: 7.298514 | K6: 7.594258 | L6: 7.893686 | M6: 8.04295 | N6: 7.993549 | O6: 8.049672 | P6: 8.217111 | Q6: 8.285393 | R6: 8.268172 | S6: 8.371435 | T6: 8.447915 | U6: 8.533866 | V6: 8.599489 | W6: 8.639607 | X6: 8.654531 | Y6: 8.748531 | Z6: 8.813139 | AA6: 8.959833 | AB6: 9.050186 | AC6: 9.053982 | AD6: 9.101374 | AE6: 9.185375 | AF6: 9.302144 | AG6: 0.008
A7: Load Factor (fraction of seats filled)
A8: U.S. Domestic | B8: Air Travel: Load Factor: U.S. Domestic: Alternative Transportation | C8: AEO.2025.ALTTRNP.CAP_LDFAC_AIRT_DMS_NA_NA_NA_FRAC.A | D8: fraction | F8: 0.85 | G8: 0.85898 | H8: 0.859933 | I8: 0.860784 | J8: 0.861546 | K8: 0.862228 | L8: 0.862842 | M8: 0.863394 | N8: 0.863894 | O8: 0.864348 | P8: 0.864762 | Q8: 0.86514 | R8: 0.865488 | S8: 0.865808 | T8: 0.866103 | U8: 0.866376 | V8: 0.866672 | W8: 0.866967 | X8: 0.867263 | Y8: 0.867559 | Z8: 0.867855 | AA8: 0.868151 | AB8: 0.868447 | AC8: 0.868743 | AD8: 0.869039 | AE8: 0.869336 | AF8: 0.869632 | AG8: 0.001
A9: U.S. International | B9: Air Travel: Load Factor: U.S. International: Alternative Transportation | C9: AEO.2025.ALTTRNP.CAP_LDFAC_AIRT_INTA_NA_NA_NA_FRAC.A | D9: fraction | F9: 0.846 | G9: 0.85932 | H9: 0.860179 | I9: 0.86104 | J9: 0.861901 | K9: 0.862762 | L9: 0.863625 | M9: 0.864489 | N9: 0.865353 | O9: 0.866219 | P9: 0.867085 | Q9: 0.867952 | R9: 0.86882 | S9: 0.869689 | T9: 0.870558 | U9: 0.871429 | V9: 0.8723 | W9: 0.873173 | X9: 0.874046 | Y9: 0.87492 | Z9: 0.875795 | AA9: 0.876671 | AB9: 0.877547 | AC9: 0.878425 | AD9: 0.879303 | AE9: 0.880183 | AF9: 0.881063 | AG9: 0.002
A10: Driver Variables
A11: Population (millions)
A12: United States | B12: Air Travel: Drivers: Population: U.S.: Alternative Transportation | C12: AEO.2025.ALTTRNP.ECI_POP_NA_NA_NA_NA_USA_MILL.A | D12: millions | F12: 342.00198 | G12: 344.85077 | H12: 346.96423 | I12: 348.43741 | J12: 349.87805 | K12: 351.28119 | L12: 352.64179 | M12: 353.9574 | N12: 355.23047 | O12: 356.45853 | P12: 357.63406 | Q12: 358.73593 | R12: 359.77283 | S12: 360.75125 | T12: 361.67264 | U12: 362.53564 | V12: 363.34354 | W12: 364.09573 | X12: 364.79132 | Y12: 365.43613 | Z12: 366.03445 | AA12: 366.59067 | AB12: 367.10648 | AC12: 367.58792 | AD12: 368.03946 | AE12: 368.46582 | AF12: 368.87057 | AG12: 0.003
A13: Canada | B13: Air Travel: Drivers: Population: Canada: Alternative Transportation | C13: AEO.2025.ALTTRNP.ECI_POP_NA_NA_NA_NA_CAN_MILL.A | D13: millions | F13: 41.11554 | G13: 41.536888 | H13: 41.87455 | I13: 42.188862 | J13: 42.649399 | K13: 43.106659 | L13: 43.563068 | M13: 44.018311 | N13: 44.470509 | O13: 44.918892 | P13: 45.363789 | Q13: 45.805729 | R13: 46.244751 | S13: 46.679371 | T13: 47.1096 | U13: 47.535721 | V13: 47.958038 | W13: 48.377232 | X13: 48.793659 | Y13: 49.207779 | Z13: 49.619549 | AA13: 50.028412 | AB13: 50.434639 | AC13: 50.839611 | AD13: 51.243679 | AE13: 51.646778 | AF13: 52.048401 | AG13: 0.009
A14: Mexico | B14: Air Travel: Drivers: Population: Mexico: Alternative Transportation | C14: AEO.2025.ALTTRNP.ECI_POP_NA_NA_NA_NA_MAOOAS_MILL.A | D14: millions | F14: 130.86099 | G14: 131.9469 | H14: 132.9977 | I14: 134.0177 | J14: 135.0087 | K14: 135.9709 | L14: 136.9048 | M14: 137.8111 | N14: 138.6902 | O14: 139.5421 | P14: 140.362 | Q14: 141.1508 | R14: 141.9092 | S14: 142.6375 | T14: 143.3363 | U14: 143.99831 | V14: 144.6243 | W14: 145.2178 | X14: 145.7775 | Y14: 146.3 | Z14: 146.7877 | AA14: 147.2401 | AB14: 147.6542 | AC14: 148.0302 | AD14: 148.37219 | AE14: 148.6779 | AF14: 148.9463 | AG14: 0.005
A15: Western Europe | B15: Air Travel: Drivers: Population: Western Europe: Alternative Transportation | C15: AEO.2025.ALTTRNP.ECI_POP_NA_NA_NA_NA_OCDEU_MILL.A | D15: millions | F15: 638.29211 | G15: 638.9436 | H15: 639.36072 | I15: 639.66699 | J15: 639.91583 | K15: 640.17175 | L15: 640.43732 | M15: 640.70172 | N15: 640.95203 | O15: 641.18213 | P15: 641.40845 | Q15: 641.61481 | R15: 641.79181 | S15: 641.93884 | T15: 642.04028 | U15: 642.09296 | V15: 642.09369 | W15: 642.03827 | X15: 641.92572 | Y15: 641.74835 | Z15: 641.50354 | AA15: 641.18671 | AB15: 640.79913 | AC15: 640.33795 | AD15: 639.78851 | AE15: 639.146 | AF15: 638.40759 | AG15: 0
A16: Japan | B16: Air Travel: Drivers: Population: Japan: Alternative Transportation | C16: AEO.2025.ALTTRNP.ECI_POP_NA_NA_NA_NA_JPN_MILL.A | D16: millions | F16: 123.753 | G16: 123.1035 | H16: 122.4278 | I16: 121.7324 | J16: 121.0243 | K16: 120.3081 | L16: 119.5842 | M16: 118.8521 | N16: 118.1141 | O16: 117.3725 | P16: 116.6268 | Q16: 115.8761 | R16: 115.1255 | S16: 114.3774 | T16: 113.6336 | U16: 112.8945 | V16: 112.1583 | W16: 111.4225 | X16: 110.6923 | Y16: 109.9724 | Z16: 109.2595 | AA16: 108.552 | AB16: 107.8506 | AC16: 107.158 | AD16: 106.4743 | AE16: 105.7969 | AF16: 105.1231 | AG16: -0.006
A17: Australia and New Zealand | B17: Air Travel: Drivers: Population: Australia and New Zealand: Alternative Transportation | C17: AEO.2025.ALTTRNP.ECI_POP_NA_NA_NA_NA_AUNZ_MILL.A | D17: millions | F17: 32.57275 | G17: 32.958988 | H17: 33.324001 | I17: 33.701229 | J17: 34.10144 | K17: 34.498112 | L17: 34.888981 | M17: 35.273869 | N17: 35.652161 | O17: 36.023972 | P17: 36.38942 | Q17: 36.748821 | R17: 37.102631 | S17: 37.450699 | T17: 37.79353 | U17: 38.131569 | V17: 38.464809 | W17: 38.793442 | X17: 39.117519 | Y17: 39.437038 | Z17: 39.751869 | AA17: 40.061821 | AB17: 40.366779 | AC17: 40.666439 | AD17: 40.9608 | AE17: 41.249821 | AF17: 41.533428 | AG17: 0.009
A18: South Korea | B18: Air Travel: Drivers: Population: South Korea: Alternative Transportation | C18: AEO.2025.ALTTRNP.ECI_POP_NA_NA_NA_NA_SOK_MILL.A | D18: millions | F18: 51.71759 | G18: 51.66703 | H18: 51.600391 | I18: 51.518848 | J18: 51.423431 | K18: 51.314018 | L18: 51.18858 | M18: 51.04818 | N18: 50.891289 | O18: 50.714298 | P18: 50.516811 | Q18: 50.300732 | R18: 50.06654 | S18: 49.813431 | T18: 49.541161 | U18: 49.251888 | V18: 48.948681 | W18: 48.630428 | X18: 48.29974 | Y18: 47.959042 | Z18: 47.603371 | AA18: 47.232948 | AB18: 46.850899 | AC18: 46.452061 | AD18: 46.033798 | AE18: 45.597301 | AF18: 45.143131 | AG18: -0.005
A19: Russia | B19: Air Travel: Drivers: Population: Russia: Alternative Transportation | C19: AEO.2025.ALTTRNP.ECI_POP_NA_NA_NA_NA_RUS_MILL.A | D19: millions | F19: 144.8204 | G19: 143.99741 | H19: 143.39439 | I19: 143.0441 | J19: 142.6698 | K19: 142.2851 | L19: 141.8894 | M19: 141.47549 | N19: 141.06039 | O19: 140.6646 | P19: 140.28081 | Q19: 139.9097 | R19: 139.5515 | S19: 139.20489 | T19: 138.8768 | U19: 138.5674 | V19: 138.2818 | W19: 138.02181 | X19: 137.78281 | Y19: 137.55791 | Z19: 137.345 | AA19: 137.15221 | AB19: 136.97369 | AC19: 136.7894 | AD19: 136.586 | AE19: 136.36839 | AF19: 136.1328 | AG19: -0.002
A20: Eastern Europe and Eurasia | B20: Air Travel: Drivers: Population: Eastern Europe and Eurasia: Alternative Transportation | C20: AEO.2025.ALTTRNP.ECI_POP_NA_NA_NA_NA_OEUAS_MILL.A | D20: millions | F20: 149.55203 | G20: 151.9012 | H20: 153.64238 | I20: 154.55901 | J20: 155.43941 | K20: 156.31045 | L20: 157.19643 | M20: 158.05125 | N20: 158.90607 | O20: 159.74928 | P20: 160.57231 | Q20: 161.38737 | R20: 162.21719 | S20: 163.06296 | T20: 163.90462 | U20: 164.75026 | V20: 165.59624 | W20: 166.43773 | X20: 167.2859 | Y20: 168.13182 | Z20: 168.96674 | AA20: 169.78477 | AB20: 170.56317 | AC20: 171.30804 | AD20: 172.02151 | AE20: 172.71736 | AF20: 173.40846 | AG20: 0.006
A21: China | B21: Air Travel: Drivers: Population: China: Alternative Transportation | C21: AEO.2025.ALTTRNP.ECI_POP_NA_NA_NA_NA_CHN_MILL.A | D21: millions | F21: 1419.321 | G21: 1416.0959 | H21: 1412.9139 | I21: 1409.679 | J21: 1406.137 | K21: 1402.283 | L21: 1398.1541 | M21: 1393.749 | N21: 1389.0601 | O21: 1384.097 | P21: 1378.877 | Q21: 1373.428 | R21: 1367.743 | S21: 1361.83 | T21: 1355.723 | U21: 1349.395 | V21: 1342.817 | W21: 1335.99 | X21: 1328.9091 | Y21: 1321.5909 | Z21: 1314.016 | AA21: 1306.114 | AB21: 1297.818 | AC21: 1289.12 | AD21: 1279.993 | AE21: 1270.381 | AF21: 1260.2889 | AG21: -0.005
A22: India | B22: Air Travel: Drivers: Population: India: Alternative Transportation | C22: AEO.2025.ALTTRNP.ECI_POP_NA_NA_NA_NA_IND_MILL.A | D22: millions | F22: 1450.936 | G22: 1463.866 | H22: 1476.626 | I22: 1489.165 | J22: 1501.433 | K22: 1513.424 | L22: 1525.139 | M22: 1536.541 | N22: 1547.6071 | O22: 1558.324 | P22: 1568.688 | Q22: 1578.6949 | R22: 1588.325 | S22: 1597.537 | T22: 1606.301 | U22: 1614.639 | V22: 1622.58 | W22: 1630.119 | X22: 1637.235 | Y22: 1643.915 | Z22: 1650.187 | AA22: 1656.068 | AB22: 1661.548 | AC22: 1666.6281 | AD22: 1671.3101 | AE22: 1675.62 | AF22: 1679.589 | AG22: 0.006
A23: Other Asia Pacific | B23: Air Travel: Drivers: Population: Other Asia Pacific: Alternative Transportation | C23: AEO.2025.ALTTRNP.ECI_POP_NA_NA_NA_NA_ONCDAS_MILL.A | D23: millions | F23: 1291.4583 | G23: 1304.0575 | H23: 1316.5952 | I23: 1329.1713 | J23: 1341.8307 | K23: 1354.4788 | L23: 1367.0858 | M23: 1379.6105 | N23: 1391.9745 | O23: 1404.1891 | P23: 1416.1998 | Q23: 1427.9586 | R23: 1439.533 | S23: 1450.932 | T23: 1462.1069 | U23: 1473.066 | V23: 1483.7819 | W23: 1494.2134 | X23: 1504.3381 | Y23: 1514.1906 | Z23: 1523.7782 | AA23: 1533.0756 | AB23: 1542.127 | AC23: 1550.8334 | AD23: 1559.179 | AE23: 1567.2681 | AF23: 1575.0332 | AG23: 0.008
... A27: Other Americas | B27: Air Travel: Drivers: Population: Other Americas: Alternative Transportation | C27: AEO.2025.ALTTRNP.ECI_POP_NA_NA_NA_NA_ONOAS_MILL.A | D27: millions | F27: 320.53473 | G27: 323.0799 | H27: 325.5528 | I27: 327.96841 | J27: 330.324 | K27: 332.61664 | L27: 334.85278 | M27: 337.03165 | N27: 339.14975 | O27: 341.20331 | P27: 343.19653 | Q27: 345.12198 | R27: 346.96936 | S27: 348.73593 | T27: 350.42746 | U27: 352.04385 | V27: 353.57599 | W27: 355.02155 | X27: 356.38486 | Y27: 357.66562 | Z27: 358.8631 | AA27: 359.98111 | AB27: 361.01959 | AC27: 361.98383 | AD27: 362.87286 | AE27: 363.68106 | AF27: 364.41592 | AG27: 0.005
A28: Travel Demand
A29: Revenue Passenger Miles (billion miles)
A30: Domestic
A31: United States | B31: Air Travel: Travel Demand: Revenue Passenger Miles: Domestic: U.S.: Alternative Transportation | C31: AEO.2025.ALTTRNP.ECI_RPM_AIRT_DMS_NA_NA_USA_BLNMLS.A | D31: billion miles | F31: 769.0744 | G31: 784.82141 | H31: 804.30225 | I31: 822.31329 | J31: 836.94464 | K31: 852.79474 | L31: 867.11853 | M31: 878.67957 | N31: 892.21368 | O31: 906.729 | P31: 920.58386 | Q31: 935.94891 | R31: 951.57721 | S31: 968.24323 | T31: 986.23108 | U31: 1004.2006 | V31: 1022.1676 | W31: 1039.7505 | X31: 1058.9343 | Y31: 1077.6267 | Z31: 1094.8949 | AA31: 1111.7531 | AB31: 1128.2476 | AC31: 1147.9022 | AD31: 1168.9659 | AE31: 1189.0094 | AF31: 1208.7004 | AG31: 0.018
A32: Canada | B32: Air Travel: Travel Demand: Revenue Passenger Miles: Domestic: Canada: Alternative Transportation | C32: AEO.2025.ALTTRNP.ECI_RPM_AIRT_DMS_NA_NA_CAN_BLNMLS.A | D32: billion miles | F32: 37.600502 | G32: 38.178329 | H32: 38.814651 | I32: 39.45327 | J32: 40.180599 | K32: 40.9147 | L32: 41.655926 | M32: 42.395454 | N32: 43.133369 | O32: 43.88018 | P32: 44.634605 | Q32: 45.395569 | R32: 46.160698 | S32: 46.930233 | T32: 47.703876 | U32: 48.486118 | V32: 49.276463 | W32: 50.077091 | X32: 50.886642 | Y32: 51.703285 | Z32: 52.524178 | AA32: 53.346607 | AB32: 54.175564 | AC32: 55.012207 | AD32: 55.854134 | AE32: 56.703068 | AF32: 57.554737 | AG32: 0.017
A33: Mexico | B33: Air Travel: Travel Demand: Revenue Passenger Miles: Domestic: Mexico: Alternative Transportation | C33: AEO.2025.ALTTRNP.ECI_RPM_AIRT_DMS_NA_NA_MAOOAS_BLNMLS.A | D33: billion miles | F33: 44.937325 | G33: 46.664017 | H33: 48.52676 | I33: 50.424767 | J33: 52.343803 | K33: 54.30658 | L33: 56.32291 | M33: 58.395287 | N33: 60.529984 | O33: 62.730732 | P33: 64.997902 | Q33: 67.333366 | R33: 69.738976 | S33: 72.216545 | T33: 74.767998 | U33: 77.392761 | V33: 80.092697 | W33: 82.870613 | X33: 85.727814 | Y33: 88.664772 | Z33: 91.684021 | AA33: 94.787086 | AB33: 97.974487 | AC33: 101.24791 | AD33: 104.61065 | AE33: 108.06347 | AF33: 111.60763 | AG33: 0.036
A34: Western Europe | B34: Air Travel: Travel Demand: Revenue Passenger Miles: Domestic: Western Europe: Alternative Transportation | C34: AEO.2025.ALTTRNP.ECI_RPM_AIRT_DMS_NA_NA_OCDEU_BLNMLS.A | D34: billion miles | F34: 695.7085 | G34: 711.492 | H34: 727.84601 | I34: 744.4021 | J34: 761.14691 | K34: 778.06952 | L34: 795.17676 | M34: 812.43671 | N34: 829.91644 | O34: 847.72449 | P34: 865.89209 | Q34: 884.39624 | R34: 903.27612 | S34: 922.48926 | T34: 942.00446 | U34: 961.84662 | V34: 982.01569 | W34: 1002.5041 | X34: 1023.3381 | Y34: 1044.5065 | Z34: 1065.9882 | AA34: 1087.7701 | AB34: 1109.8762 | AC34: 1132.3049 | AD34: 1155.0436 | AE34: 1178.1086 | AF34: 1201.5139 | AG34: 0.021
A35: Japan | B35: Air Travel: Travel Demand: Revenue Passenger Miles: Domestic: Japan: Alternative Transportation | C35: AEO.2025.ALTTRNP.ECI_RPM_AIRT_DMS_NA_NA_JPN_BLNMLS.A | D35: billion miles | F35: 61.775593 | G35: 62.381695 | H35: 62.855656 | I35: 63.321266 | J35: 63.739643 | K35: 64.132576 | L35: 64.504501 | M35: 64.848396 | N35: 65.182808 | O35: 65.504845 | P35: 65.807434 | Q35: 66.092278 | R35: 66.364037 | S35: 66.631622 | T35: 66.89563 | U35: 67.155266 | V35: 67.418846 | W35: 67.688339 | X35: 67.966217 | Y35: 68.255569 | Z35: 68.556664 | AA35: 68.875145 | AB35: 69.210426 | AC35: 69.559624 | AD35: 69.9188 | AE35: 70.284042 | AF35: 70.661758 | AG35: 0.005
A36: Australia and New Zealand | B36: Air Travel: Travel Demand: Revenue Passenger Miles: Domestic: Australia and New Zealand: Alternative Transportation | C36: AEO.2025.ALTTRNP.ECI_RPM_AIRT_DMS_NA_NA_AUNZ_BLNMLS.A | D36: billion miles | F36: 59.104053 | G36: 60.491245 | H36: 62.26804 | I36: 64.084373 | J36: 65.934128 | K36: 67.765549 | L36: 69.591827 | M36: 71.438934 | N36: 73.293076 | O36: 75.14917 | P36: 77.013268 | Q36: 78.860535 | R36: 80.713531 | S36: 82.578789 | T36: 84.400665 | U36: 86.218666 | V36: 88.039467 | W36: 89.874641 | X36: 91.723427 | Y36: 93.586189 | Z36: 95.459198 | AA36: 97.339409 | AB36: 99.226044 | AC36: 101.11935 | AD36: 103.02018 | AE36: 104.92896 | AF36: 106.8463 | AG36: 0.023
A37: South Korea | B37: Air Travel: Travel Demand: Revenue Passenger Miles: Domestic: South Korea: Alternative Transportation | C37: AEO.2025.ALTTRNP.ECI_RPM_AIRT_DMS_NA_NA_SOK_BLNMLS.A | D37: billion miles | F37: 8.896751 | G37: 9.059666 | H37: 9.254403 | I37: 9.439147 | J37: 9.616467 | K37: 9.78886 | L37: 9.958011 | M37: 10.118227 | N37: 10.269077 | O37: 10.411737 | P37: 10.545367 | Q37: 10.670194 | R37: 10.79082 | S37: 10.900813 | T37: 11.004025 | U37: 11.099137 | V37: 11.190952 | W37: 11.280606 | X37: 11.364059 | Y37: 11.438848 | Z37: 11.500485 | AA37: 11.546016 | AB37: 11.579747 | AC37: 11.604859 | AD37: 11.625552 | AE37: 11.645999 | AF37: 11.664306 | AG37: 0.01
A38: Russia | B38: Air Travel: Travel Demand: Revenue Passenger Miles: Domestic: Russia: Alternative Transportation | C38: AEO.2025.ALTTRNP.ECI_RPM_AIRT_DMS_NA_NA_RUS_BLNMLS.A | D38: billion miles | F38: 79.585274 | G38: 80.866997 | H38: 81.715607 | I38: 82.199478 | J38: 83.152344 | K38: 84.156509 | L38: 85.16629 | M38: 86.18206 | N38: 87.230774 | O38: 88.321007 | P38: 89.456703 | Q38: 90.623169 | R38: 91.766724 | S38: 92.878967 | T38: 93.975449 | U38: 95.062119 | V38: 96.155243 | W38: 97.370361 | X38: 98.666924 | Y38: 99.982994 | Z38: 101.3106 | AA38: 102.64252 | AB38: 104.00653 | AC38: 105.41545 | AD38: 106.80108 | AE38: 108.16437 | AF38: 109.53309 | AG38: 0.012
A39: Eastern Europe and Eurasia | B39: Air Travel: Travel Demand: Revenue Passenger Miles: Domestic: Eastern Europe and Eurasia: Alternative Transportation | C39: AEO.2025.ALTTRNP.ECI_RPM_AIRT_DMS_NA_NA_OEUAS_BLNMLS.A | D39: billion miles | F39: 10.941443 | G39: 11.379101 | H39: 11.839906 | I39: 12.262307 | J39: 12.709543 | K39: 13.170254 | L39: 13.621606 | M39: 14.066698 | N39: 14.516427 | O39: 14.975104 | P39: 15.443627 | Q39: 15.927789 | R39: 16.429544 | S39: 16.944839 | T39: 17.472025 | U39: 18.011406 | V39: 18.559582 | W39: 19.116617 | X39: 19.688261 | Y39: 20.275387 | Z39: 20.877848 | AA39: 21.49608 | AB39: 22.1259 | AC39: 22.769482 | AD39: 23.426699 | AE39: 24.098751 | AF39: 24.786325 | AG39: 0.032
A40: China | B40: Air Travel: Travel Demand: Revenue Passenger Miles: Domestic: China: Alternative Transportation | C40: AEO.2025.ALTTRNP.ECI_RPM_AIRT_DMS_NA_NA_CHN_BLNMLS.A | D40: billion miles | F40: 559.27313 | G40: 594.13141 | H40: 627.76331 | I40: 661.1781 | J40: 695.78857 | K40: 731.95825 | L40: 769.54248 | M40: 808.29694 | N40: 848.34277 | O40: 889.39392 | P40: 931.4057 | Q40: 974.31799 | R40: 1017.7333 | S40: 1061.8749 | T40: 1106.921 | U40: 1152.8358 | V40: 1199.5791 | W40: 1247.1012 | X40: 1295.3479 | Y40: 1344.2566 | Z40: 1393.769 | AA40: 1443.848 | AB40: 1494.4528 | AC40: 1545.5237 | AD40: 1596.9993 | AE40: 1648.838 | AF40: 1700.9683 | AG40: 0.044
A41: India | B41: Air Travel: Travel Demand: Revenue Passenger Miles: Domestic: India: Alternative Transportation | C41: AEO.2025.ALTTRNP.ECI_RPM_AIRT_DMS_NA_NA_IND_BLNMLS.A | D41: billion miles | F41: 92.931549 | G41: 101.3761 | H41: 110.33313 | I41: 120.11643 | J41: 130.41547 | K41: 141.29529 | L41: 152.72458 | M41: 164.62189 | N41: 176.90376 | O41: 189.48221 | P41: 202.3152 | Q41: 215.34853 | R41: 228.49815 | S41: 241.86232 | T41: 255.35088 | U41: 269.00149 | V41: 282.92517 | W41: 297.09122 | X41: 311.47659 | Y41: 326.04114 | Z41: 340.75421 | AA41: 355.61545 | AB41: 370.64233 | AC41: 385.80408 | AD41: 401.07306 | AE41: 416.42178 | AF41: 431.8197 | AG41: 0.061
A42: Other Asia Pacific | B42: Air Travel: Travel Demand: Revenue Passenger Miles: Domestic: Other Asia Pacific: Alternative Transportation | C42: AEO.2025.ALTTRNP.ECI_RPM_AIRT_DMS_NA_NA_ONCDAS_BLNMLS.A | D42: billion miles | F42: 207.68857 | G42: 218.51015 | H42: 230.73056 | I42: 243.18684 | J42: 255.80749 | K42: 268.62222 | L42: 281.77997 | M42: 295.35715 | N42: 309.3494 | O42: 323.70145 | P42: 338.353 | Q42: 353.25491 | R42: 368.41959 | S42: 383.78339 | T42: 399.58884 | U42: 415.85287 | V42: 432.55576 | W42: 449.64737 | X42: 467.16397 | Y42: 485.0939 | Z42: 503.41666 | AA42: 522.11938 | AB42: 541.1651 | AC42: 560.50476 | AD42: 580.16614 | AE42: 600.20392 | AF42: 620.71033 | AG42: 0.043
... A47: Total World Domestic | B47: Air Travel: Travel Demand: Revenue Passenger Miles: Domestic: World: Alternative Transportation | C47: AEO.2025.ALTTRNP.ECI_RPM_AIRT_DMS_NA_NA_WRLD_BLNMLS.A | D47: billion miles | F47: 2861.9478 | G47: 2963.04 | H47: 3070.0647 | I47: 3175.623 | J47: 3280.3511 | K47: 3388.8789 | L47: 3498.4436 | M47: 3607.6426 | N47: 3721.2859 | O47: 3838.1045 | P47: 3956.3628 | Q47: 4078.0508 | R47: 4201.4858 | S47: 4327.668 | T47: 4457.1421 | U47: 4588.6489 | V47: 4722.3101 | W47: 4857.7559 | X47: 4996.9341 | Y47: 5137.5679 | Z47: 5278.5747 | AA47: 5420.8921 | AB47: 5564.561 | AC47: 5713.002 | AD47: 5864.3223 | AE47: 6016.1069 | AF47: 6169.0723 | AG47: 0.03
A48: International
A49: United States | B49: Air Travel: Travel Demand: Revenue Passenger Miles: International U.S.: Alternative Transportation | C49: AEO.2025.ALTTRNP.ECI_RPM_AIRT_INTA_NA_NA_USA_BLNMLS.A | D49: billion miles | F49: 430.05841 | G49: 440.68881 | H49: 452.96109 | I49: 464.51517 | J49: 474.60986 | K49: 485.35654 | L49: 495.48511 | M49: 504.40973 | N49: 514.33551 | O49: 524.80676 | P49: 535.05151 | Q49: 546.09051 | R49: 557.3407 | S49: 569.17609 | T49: 581.73895 | U49: 594.39087 | V49: 607.14081 | W49: 619.80383 | X49: 633.34387 | Y49: 646.74988 | Z49: 659.56421 | AA49: 672.27985 | AB49: 684.91858 | AC49: 699.22736 | AD49: 714.35425 | AE49: 729.09729 | AF49: 743.78802 | AG49: 0.021
A50: Canada | B50: Air Travel: Travel Demand: Revenue Passenger Miles: International Canada: Alternative Transportation | C50: AEO.2025.ALTTRNP.ECI_RPM_AIRT_INTA_NA_NA_CAN_BLNMLS.A | D50: billion miles | F50: 91.476265 | G50: 93.832832 | H50: 96.111671 | I50: 98.392845 | J50: 101.04082 | K50: 103.74071 | L50: 106.49829 | M50: 109.30956 | N50: 112.17171 | O50: 115.08934 | P50: 118.06334 | Q50: 121.09518 | R50: 124.18465 | S50: 127.32953 | T50: 130.53049 | U50: 133.79141 | V50: 137.11359 | W50: 140.50078 | X50: 143.95413 | Y50: 147.47479 | Z50: 151.06226 | AA50: 154.71464 | AB50: 158.43651 | AC50: 162.23325 | AD50: 166.1057 | AE50: 170.05606 | AF50: 174.08186 | AG50: 0.025
A51: Mexico | B51: Air Travel: Travel Demand: Revenue Passenger Miles: International Mexico: Alternative Transportation | C51: AEO.2025.ALTTRNP.ECI_RPM_AIRT_INTA_NA_NA_MAOOAS_BLNMLS.A | D51: billion miles | F51: 53.703476 | G51: 55.506596 | H51: 57.39735 | I51: 59.322151 | J51: 61.27409 | K51: 63.265579 | L51: 65.302078 | M51: 67.385193 | N51: 69.518417 | O51: 71.703735 | P51: 73.940025 | Q51: 76.22847 | R51: 78.57016 | S51: 80.96608 | T51: 83.417336 | U51: 85.921219 | V51: 88.478691 | W51: 91.092148 | X51: 93.761597 | Y51: 96.485855 | Z51: 99.266708 | AA51: 102.10444 | AB51: 104.99782 | AC51: 107.94732 | AD51: 110.95574 | AE51: 114.02214 | AF51: 117.1462 | AG51: 0.03
A52: Western Europe | B52: Air Travel: Travel Demand: Revenue Passenger Miles: International Western Europe: Alternative Transportation | C52: AEO.2025.ALTTRNP.ECI_RPM_AIRT_INTA_NA_NA_OCDEU_BLNMLS.A | D52: billion miles | F52: 654.94727 | G52: 668.00812 | H52: 681.23877 | I52: 694.59607 | J52: 708.112 | K52: 721.83044 | L52: 735.75873 | M52: 749.88165 | N52: 764.21393 | O52: 778.78876 | P52: 793.63092 | Q52: 808.72253 | R52: 824.0705 | S52: 839.6618 | T52: 855.47449 | U52: 871.51465 | V52: 887.77991 | W52: 904.26477 | X52: 920.97662 | Y52: 937.9046 | Z52: 955.03943 | AA52: 972.37189 | AB52: 989.90979 | AC52: 1007.6491 | AD52: 1025.5697 | AE52: 1043.6696 | AF52: 1061.9474 | AG52: 0.019
A53: Japan | B53: Air Travel: Travel Demand: Revenue Passenger Miles: International Japan: Alternative Transportation | C53: AEO.2025.ALTTRNP.ECI_RPM_AIRT_INTA_NA_NA_JPN_BLNMLS.A | D53: billion miles | F53: 111.2005 | G53: 113.24779 | H53: 114.31217 | I53: 115.36617 | J53: 116.07556 | K53: 116.60272 | L53: 116.98399 | M53: 117.16745 | N53: 117.29625 | O53: 117.34146 | P53: 117.25084 | Q53: 117.04381 | R53: 116.74201 | S53: 116.4083 | T53: 116.04179 | U53: 115.63554 | V53: 115.25964 | W53: 114.93729 | X53: 114.66768 | Y53: 114.4557 | Z53: 114.31337 | AA53: 114.28636 | AB53: 114.36597 | AC53: 114.51946 | AD53: 114.71648 | AE53: 114.93708 | AF53: 115.23711 | AG53: 0.001
A54: Australia and New Zealand | B54: Air Travel: Travel Demand: Revenue Passenger Miles: International Australia and New Zealand: Alternative Transportation | C54: AEO.2025.ALTTRNP.ECI_RPM_AIRT_INTA_NA_NA_AUNZ_BLNMLS.A | D54: billion miles | F54: 93.077072 | G54: 97.347054 | H54: 100.34696 | I54: 103.45451 | J54: 106.6972 | K54: 109.99551 | L54: 113.34946 | M54: 116.76859 | N54: 120.24725 | O54: 123.78468 | P54: 127.38407 | Q54: 131.0381 | R54: 134.75696 | S54: 138.54346 | T54: 142.37952 | U54: 146.28174 | V54: 150.25348 | W54: 154.30066 | X54: 158.42427 | Y54: 162.62552 | Z54: 166.90373 | AA54: 171.25819 | AB54: 175.68918 | AC54: 180.19679 | AD54: 184.78239 | AE54: 189.44687 | AF54: 194.19125 | AG54: 0.029
A55: South Korea | B55: Air Travel: Travel Demand: Revenue Passenger Miles: International South Korea: Alternative Transportation | C55: AEO.2025.ALTTRNP.ECI_RPM_AIRT_INTA_NA_NA_SOK_BLNMLS.A | D55: billion miles | F55: 84.734619 | G55: 87.851677 | H55: 93.000404 | I55: 98.037666 | J55: 103.02498 | K55: 108.03778 | L55: 113.14192 | M55: 118.11796 | N55: 122.94112 | O55: 127.6627 | P55: 132.24222 | Q55: 136.66746 | R55: 141.12051 | S55: 145.33145 | T55: 149.45853 | U55: 153.42554 | V55: 157.42264 | W55: 161.51424 | X55: 165.49713 | Y55: 169.23051 | Z55: 172.52617 | AA55: 175.22241 | AB55: 177.48927 | AC55: 179.52078 | AD55: 181.55063 | AE55: 183.78714 | AF55: 186.13983 | AG55: 0.031
A56: Russia | B56: Air Travel: Travel Demand: Revenue Passenger Miles: International Russia: Alternative Transportation | C56: AEO.2025.ALTTRNP.ECI_RPM_AIRT_INTA_NA_NA_RUS_BLNMLS.A | D56: billion miles | F56: 34.823204 | G56: 53.19915 | H56: 68.602608 | I56: 77.888138 | J56: 83.27375 | K56: 84.848167 | L56: 86.445427 | M56: 88.064011 | N56: 89.724434 | O56: 91.438202 | P56: 93.206688 | Q56: 95.022446 | R56: 96.854218 | S56: 98.696892 | T56: 100.56232 | U56: 102.45474 | V56: 104.3865 | W56: 106.43113 | X56: 108.56416 | Y56: 110.7461 | Z56: 112.9722 | AA56: 115.24168 | AB56: 117.57133 | AC56: 119.96314 | AD56: 122.36852 | AE56: 124.78976 | AF56: 127.24361 | AG56: 0.051
A57: Eastern Europe and Eurasia | B57: Air Travel: Travel Demand: Revenue Passenger Miles: International Eastern Europe and Eurasia: Alternative Transportation | C57: AEO.2025.ALTTRNP.ECI_RPM_AIRT_INTA_NA_NA_OEUAS_BLNMLS.A | D57: billion miles | F57: 38.294426 | G57: 40.916958 | H57: 43.039192 | I57: 44.641739 | J57: 47.114616 | K57: 48.803108 | L57: 50.489059 | M57: 52.175716 | N57: 53.893761 | O57: 55.653084 | P57: 57.455379 | Q57: 59.316959 | R57: 61.246197 | S57: 63.23407 | T57: 65.274734 | U57: 67.37075 | V57: 69.513954 | W57: 71.704567 | X57: 73.959312 | Y57: 76.279922 | Z57: 78.665512 | AA57: 81.116997 | AB57: 83.620842 | AC57: 86.183914 | AD57: 88.806725 | AE57: 91.49527 | AF57: 94.254333 | AG57: 0.035
A58: China | B58: Air Travel: Travel Demand: Revenue Passenger Miles: International China: Alternative Transportation | C58: AEO.2025.ALTTRNP.ECI_RPM_AIRT_INTA_NA_NA_CHN_BLNMLS.A | D58: billion miles | F58: 172.03894 | G58: 181.23952 | H58: 190.71088 | I58: 200.33186 | J58: 210.32256 | K58: 220.74736 | L58: 231.59222 | M58: 242.82507 | N58: 254.47191 | O58: 266.49536 | P58: 278.8977 | Q58: 291.68002 | R58: 304.78671 | S58: 318.26239 | T58: 332.14761 | U58: 346.44232 | V58: 361.14477 | W58: 376.25516 | X58: 391.77179 | Y58: 407.69443 | Z58: 424.01837 | AA58: 440.7334 | AB58: 457.827 | AC58: 475.29129 | AD58: 493.11383 | AE58: 511.27841 | AF58: 529.77307 | AG58: 0.044
A59: India | B59: Air Travel: Travel Demand: Revenue Passenger Miles: International India: Alternative Transportation | C59: AEO.2025.ALTTRNP.ECI_RPM_AIRT_INTA_NA_NA_IND_BLNMLS.A | D59: billion miles | F59: 86.520073 | G59: 93.157524 | H59: 100.1253 | I59: 107.63185 | J59: 115.4596 | K59: 123.64992 | L59: 132.17995 | M59: 140.99498 | N59: 150.04169 | O59: 159.26601 | P59: 168.64465 | Q59: 178.14731 | R59: 187.72533 | S59: 197.44218 | T59: 207.24455 | U59: 217.15916 | V59: 227.25673 | W59: 237.5201 | X59: 247.93622 | Y59: 258.48224 | Z59: 269.14267 | AA59: 279.9198 | AB59: 290.82529 | AC59: 301.84232 | AD59: 312.9563 | AE59: 324.15369 | AF59: 335.41962 | AG59: 0.053
A60: Other Asia Pacific | B60: Air Travel: Travel Demand: Revenue Passenger Miles: International Other Asia Pacific: Alternative Transportation | C60: AEO.2025.ALTTRNP.ECI_RPM_AIRT_INTA_NA_NA_ONCDAS_BLNMLS.A | D60: billion miles | F60: 325.84808 | G60: 361.85306 | H60: 377.53589 | I60: 393.58838 | J60: 409.98453 | K60: 426.74027 | L60: 443.95779 | M60: 461.6868 | N60: 479.91617 | O60: 498.62009 | P60: 517.75684 | Q60: 537.29279 | R60: 557.2583 | S60: 577.62469 | T60: 598.53754 | U60: 620.01532 | V60: 642.04523 | W60: 664.59235 | X60: 687.67798 | Y60: 711.30975 | Z60: 735.48334 | AA60: 760.19 | AB60: 785.42694 | AC60: 811.14148 | AD60: 837.35016 | AE60: 864.12317 | AF60: 891.49847 | AG60: 0.039
... A66: Total World | B66: Air Travel: Travel Demand: Revenue Passenger Miles: World: Alternative Transportation | C66: AEO.2025.ALTTRNP.ECI_RPM_AIRT_INTA_NA_NA_WRLD_BLNMLS.A | D66: billion miles | F66: 5598.9658 | G66: 5833.98 | H66: 6054.2861 | I66: 6267.4424 | J66: 6477.1572 | K66: 6688.6172 | L66: 6902.6953 | M66: 7117.1782 | N66: 7339.248 | O66: 7567.166 | P66: 7798.3501 | Q66: 8035.7632 | R66: 8277.3096 | S66: 8524.2354 | T66: 8777.4873 | U66: 9035.2051 | V66: 9297.8711 | W66: 9565.0234 | X66: 9839.3789 | Y66: 10117.48 | Z66: 10397.605 | AA66: 10681.095 | AB66: 10968.157 | AC66: 11264.076 | AD66: 11566.308 | AE66: 11871.498 | AF66: 12180.68 | AG66: 0.03
A67: Freight Revenue Ton Miles (billion miles)
A68: United States | B68: Air Travel: Travel Demand: Revenue Ton Miles: Freight: U.S.: Alternative Transportation | C68: AEO.2025.ALTTRNP.ECI_RTM_AIRT_NA_NA_NA_USA_BLNMLS.A | D68: billion miles | F68: 51.452095 | G68: 52.59079 | H68: 53.859558 | I68: 55.048134 | J68: 56.123325 | K68: 57.271408 | L68: 58.376846 | M68: 59.385468 | N68: 60.493416 | O68: 61.658783 | P68: 62.810963 | Q68: 64.039215 | R68: 65.291115 | S68: 66.600006 | T68: 67.978249 | U68: 69.36792 | V68: 70.769646 | W68: 72.166389 | X68: 73.644211 | Y68: 75.112541 | Z68: 76.530411 | AA68: 77.9422 | AB68: 79.349777 | AC68: 80.910233 | AD68: 82.547386 | AE68: 84.153702 | AF68: 85.759247 | AG68: 0.02
A69: Canada | B69: Air Travel: Travel Demand: Revenue Ton Miles: Freight: Canada: Alternative Transportation | C69: AEO.2025.ALTTRNP.ECI_RTM_AIRT_NA_NA_NA_CAN_BLNMLS.A | D69: billion miles | F69: 1.682606 | G69: 1.693385 | H69: 1.70486 | I69: 1.715508 | J69: 1.725099 | K69: 1.73397 | L69: 1.742209 | M69: 1.749763 | N69: 1.756739 | O69: 1.763382 | P69: 1.769722 | Q69: 1.775785 | R69: 1.781572 | S69: 1.787139 | T69: 1.79251 | U69: 1.797775 | V69: 1.802943 | W69: 1.808054 | X69: 1.813099 | Y69: 1.818059 | Z69: 1.822906 | AA69: 1.827619 | AB69: 1.832273 | AC69: 1.836877 | AD69: 1.841401 | AE69: 1.845873 | AF69: 1.850249 | AG69: 0.004
A70: Mexico | B70: Air Travel: Travel Demand: Revenue Ton Miles: Freight: Mexico: Alternative Transportation | C70: AEO.2025.ALTTRNP.ECI_RTM_AIRT_NA_NA_NA_MAOOAS_BLNMLS.A | D70: billion miles | F70: 1.40537 | G70: 1.474938 | H70: 1.548783 | I70: 1.616765 | J70: 1.677943 | K70: 1.735108 | L70: 1.789583 | M70: 1.841855 | N70: 1.892718 | O70: 1.942656 | P70: 1.991909 | Q70: 2.04068 | R70: 2.089143 | S70: 2.137446 | T70: 2.185717 | U70: 2.234061 | V70: 2.282571 | W70: 2.331327 | X70: 2.380395 | Y70: 2.429831 | Z70: 2.479686 | AA70: 2.530001 | AB70: 2.58081 | AC70: 2.632145 | AD70: 2.684031 | AE70: 2.736489 | AF70: 2.789537 | AG70: 0.027
A71: Western Europe | B71: Air Travel: Travel Demand: Revenue Ton Miles: Freight: Western Europe: Alternative Transportation | C71: AEO.2025.ALTTRNP.ECI_RTM_AIRT_NA_NA_NA_OCDEU_BLNMLS.A | D71: billion miles | F71: 37.819382 | G71: 39.829979 | H71: 41.962402 | I71: 44.017982 | J71: 45.98103 | K71: 47.827194 | L71: 49.563663 | M71: 51.183769 | N71: 52.729202 | O71: 54.258862 | P71: 55.78249 | Q71: 57.298401 | R71: 58.831844 | S71: 60.363056 | T71: 61.885326 | U71: 63.413067 | V71: 64.948074 | W71: 66.489029 | X71: 68.049408 | Y71: 69.627876 | Z71: 71.215385 | AA71: 72.808067 | AB71: 74.416756 | AC71: 76.042305 | AD71: 77.688286 | AE71: 79.366531 | AF71: 81.086922 | AG71: 0.03
A72: Japan | B72: Air Travel: Travel Demand: Revenue Ton Miles: Freight: Japan: Alternative Transportation | C72: AEO.2025.ALTTRNP.ECI_RTM_AIRT_NA_NA_NA_JPN_BLNMLS.A | D72: billion miles | F72: 7.05316 | G72: 7.132802 | H72: 7.193611 | I72: 7.246642 | J72: 7.28966 | K72: 7.325282 | L72: 7.354692 | M72: 7.378053 | N72: 7.397429 | O72: 7.413045 | P72: 7.424799 | Q72: 7.433255 | R72: 7.438978 | S72: 7.442889 | T72: 7.445215 | U72: 7.446084 | V72: 7.44635 | W72: 7.446361 | X72: 7.446255 | Y72: 7.446201 | Z72: 7.44638 | AA72: 7.447296 | AB72: 7.448925 | AC72: 7.451009 | AD72: 7.453295 | AE72: 7.45561 | AF72: 7.458516 | AG72: 0.002
A73: Australia and New Zealand | B73: Air Travel: Travel Demand: Revenue Ton Miles: Freight: Australia and New Zealand: Alternative Transportation | C73: AEO.2025.ALTTRNP.ECI_RTM_AIRT_NA_NA_NA_AUNZ_BLNMLS.A | D73: billion miles | F73: 2.191592 | G73: 2.27911 | H73: 2.367953 | I73: 2.449523 | J73: 2.524696 | K73: 2.593263 | L73: 2.656439 | M73: 2.715615 | N73: 2.771036 | O73: 2.823086 | P73: 2.872358 | Q73: 2.918601 | R73: 2.962705 | S73: 3.005102 | T73: 3.044662 | U73: 3.082563 | V73: 3.119141 | W73: 3.154812 | X73: 3.189677 | Y73: 3.223845 | Z73: 3.257315 | AA73: 3.290095 | AB73: 3.322233 | AC73: 3.353795 | AD73: 3.384848 | AE73: 3.415444 | AF73: 3.445634 | AG73: 0.018
A74: South Korea | B74: Air Travel: Travel Demand: Revenue Ton Miles: Freight: South Korea: Alternative Transportation | C74: AEO.2025.ALTTRNP.ECI_RTM_AIRT_NA_NA_NA_SOK_BLNMLS.A | D74: billion miles | F74: 8.409956 | G74: 8.627151 | H74: 8.873912 | I74: 9.108818 | J74: 9.334806 | K74: 9.554699 | L74: 9.770411 | M74: 9.976318 | N74: 10.172042 | O74: 10.358764 | P74: 10.535639 | Q74: 10.702967 | R74: 10.86559 | S74: 11.016742 | T74: 11.160425 | U74: 11.295287 | V74: 11.42648 | W74: 11.555186 | X74: 11.677162 | Y74: 11.789803 | Z74: 11.888045 | AA74: 11.968592 | AB74: 12.036063 | AC74: 12.093634 | AD74: 12.145685 | AE74: 12.19677 | AF74: 12.244811 | AG74: 0.015
A75: Russia | B75: Air Travel: Travel Demand: Revenue Ton Miles: Freight: Russia: Alternative Transportation | C75: AEO.2025.ALTTRNP.ECI_RTM_AIRT_NA_NA_NA_RUS_BLNMLS.A | D75: billion miles | F75: 0.603527 | G75: 0.647508 | H75: 0.675076 | I75: 0.688334 | J75: 0.709933 | K75: 0.730076 | L75: 0.748053 | M75: 0.764251 | N75: 0.779454 | O75: 0.793934 | P75: 0.808026 | Q75: 0.821536 | R75: 0.83334 | S75: 0.843374 | T75: 0.85205 | U75: 0.859593 | V75: 0.866411 | W75: 0.87519 | X75: 0.885061 | Y75: 0.894695 | Z75: 0.903959 | AA75: 0.912644 | AB75: 0.921451 | AC75: 0.930862 | AD75: 0.939478 | AE75: 0.947303 | AF75: 0.955016 | AG75: 0.018
A76: Eastern Europe and Eurasia | B76: Air Travel: Travel Demand: Revenue Ton Miles: Freight: Eastern Europe and Eurasia: Alternative Transportation | C76: AEO.2025.ALTTRNP.ECI_RTM_AIRT_NA_NA_NA_OEUAS_BLNMLS.A | D76: billion miles | F76: 0.539953 | G76: 0.475857 | H76: 0.422057 | I76: 0.376594 | J76: 0.338501 | K76: 0.306585 | L76: 0.279709 | M76: 0.257139 | N76: 0.238302 | O76: 0.222678 | P76: 0.209799 | Q76: 0.199307 | R76: 0.190861 | S76: 0.184126 | T76: 0.178847 | U76: 0.174807 | V76: 0.171795 | W76: 0.16966 | X76: 0.168315 | Y76: 0.167659 | Z76: 0.1676 | AA76: 0.168062 | AB76: 0.168954 | AC76: 0.17023 | AD76: 0.17184 | AE76: 0.173741 | AF76: 0.175895 | AG76: -0.042
A77: China | B77: Air Travel: Travel Demand: Revenue Ton Miles: Freight: China: Alternative Transportation | C77: AEO.2025.ALTTRNP.ECI_RTM_AIRT_NA_NA_NA_CHN_BLNMLS.A | D77: billion miles | F77: 16.529194 | G77: 17.362122 | H77: 18.12052 | I77: 18.829102 | J77: 19.515839 | K77: 20.189909 | L77: 20.851711 | M77: 21.499815 | N77: 22.138054 | O77: 22.764 | P77: 23.378685 | Q77: 23.982784 | R77: 24.57217 | S77: 25.151173 | T77: 25.7232 | U77: 26.288422 | V77: 26.846848 | W77: 27.398415 | X77: 27.942936 | Y77: 28.480183 | Z77: 29.009817 | AA77: 29.531483 | AB77: 30.044754 | AC77: 30.549208 | AD77: 31.044313 | AE77: 31.529594 | AF77: 32.004528 | AG77: 0.026
A78: India | B78: Air Travel: Travel Demand: Revenue Ton Miles: Freight: India: Alternative Transportation | C78: AEO.2025.ALTTRNP.ECI_RTM_AIRT_NA_NA_NA_IND_BLNMLS.A | D78: billion miles | F78: 3.233301 | G78: 3.423184 | H78: 3.610759 | I78: 3.800875 | J78: 3.989515 | K78: 4.177978 | L78: 4.366218 | M78: 4.553584 | N78: 4.739486 | O78: 4.92336 | P78: 5.105185 | Q78: 5.284803 | R78: 5.461746 | S78: 5.63733 | T78: 5.810939 | U78: 5.983228 | V78: 6.155459 | W78: 6.327491 | X78: 6.499231 | Y78: 6.670447 | Z78: 6.841033 | AA78: 7.011127 | AB78: 7.180972 | AC78: 7.350407 | AD78: 7.519308 | AE78: 7.687574 | AF78: 7.855094 | AG78: 0.035
A79: Other Asia Pacific | B79: Air Travel: Travel Demand: Revenue Ton Miles: Freight: Other Asia Pacific: Alternative Transportation | C79: AEO.2025.ALTTRNP.ECI_RTM_AIRT_NA_NA_NA_ONCDAS_BLNMLS.A | D79: billion miles | F79: 18.962055 | G79: 19.803461 | H79: 20.548679 | I79: 21.198917 | J79: 21.767309 | K79: 22.266064 | L79: 22.706779 | M79: 23.09861 | N79: 23.448578 | O79: 23.762236 | P79: 24.044249 | Q79: 24.298674 | R79: 24.529486 | S79: 24.739485 | T79: 24.933277 | U79: 25.113234 | V79: 25.281115 | W79: 25.438202 | X79: 25.586138 | Y79: 25.726053 | Z79: 25.858837 | AA79: 25.985292 | AB79: 26.105982 | AC79: 26.221277 | AD79: 26.331917 | AE79: 26.438707 | AF79: 26.542498 | AG79: 0.013
... A86: Total World | B86: Air Travel: Travel Demand: Revenue Ton Miles: Freight: World: Alternative Transportation | C86: AEO.2025.ALTTRNP.ECI_RTM_AIRT_NA_NA_NA_WRLD_BLNMLS.A | D86: billion miles | F86: 170.815 | G86: 176.13683 | H86: 181.71564 | I86: 186.99374 | J86: 191.99782 | K86: 196.91232 | L86: 201.6432 | M86: 206.12904 | N86: 210.61032 | O86: 215.10397 | P86: 219.55054 | Q86: 224.03871 | R86: 228.54315 | S86: 233.07843 | T86: 237.65826 | U86: 242.24065 | V86: 246.83581 | W86: 251.42955 | X86: 256.11627 | Y86: 260.80026 | Z86: 265.42575 | AA86: 270.02954 | AB86: 274.62906 | AC86: 279.38412 | AD86: 284.22397 | AE86: 289.0574 | AF86: 293.92371 | AG86: 0.021
A87: Seat Miles Demanded (billion miles)
A88: United States | B88: Air Travel: Seat Miles Demanded: U.S.: Alternative Transportation | C88: AEO.2025.ALTTRNP.ECI_SMD_AIRT_NA_NA_NA_USA_BLNMLS.A | D88: billion miles | F88: 1413.1366 | G88: 1426.5015 | H88: 1461.8976 | I88: 1494.7886 | J88: 1522.1002 | K88: 1551.6201 | L88: 1578.683 | M88: 1601.1815 | N88: 1627.1464 | O88: 1654.8922 | P88: 1681.6215 | Q88: 1711.0176 | R88: 1740.9607 | S88: 1772.7719 | T88: 1806.9364 | U88: 1841.1686 | V88: 1875.4396 | W88: 1909.1254 | X88: 1945.6185 | Y88: 1981.347 | Z88: 2014.7141 | AA88: 2047.4543 | AB88: 2079.6472 | AC88: 2117.3379 | AD88: 2157.5337 | AE88: 2196.0696 | AF88: 2234.0925 | AG88: 0.018
A89: Narrow Body Aircraft | B89: Air Travel: Seat Miles Demanded: U.S.: Narrow Body Aircraft: Alternative Transportation | C89: AEO.2025.ALTTRNP.ECI_SMD_AIRT_NBTR_NA_NA_USA_BLNMLS.A | D89: billion miles | F89: 891.30133 | G89: 899.92389 | H89: 921.62634 | I89: 941.72473 | J89: 958.12878 | K89: 975.96338 | L89: 992.16058 | M89: 1005.3408 | N89: 1020.7743 | O89: 1037.3517 | P89: 1053.2385 | Q89: 1070.8484 | R89: 1088.7902 | S89: 1107.9249 | T89: 1128.5666 | U89: 1149.2212 | V89: 1169.8574 | W89: 1190.074 | X89: 1212.0828 | Y89: 1233.5531 | Z89: 1253.4465 | AA89: 1272.8931 | AB89: 1291.9447 | AC89: 1314.5281 | AD89: 1338.6927 | AE89: 1361.7328 | AF89: 1384.3929 | AG89: 0.017
A90: Wide Body Aircraft | B90: Air Travel: Seat Miles Demanded: U.S.: Wide Body Aircraft: Alternative Transportation | C90: AEO.2025.ALTTRNP.ECI_SMD_AIRT_WBE_NA_NA_USA_BLNMLS.A | D90: billion miles | F90: 436.67462 | G90: 440.58539 | H90: 452.2305 | I90: 463.12854 | J90: 472.50159 | K90: 482.51437 | L90: 491.86749 | M90: 499.96689 | N90: 509.06122 | O90: 518.68286 | P90: 528.04633 | Q90: 538.18732 | R90: 548.51233 | S90: 559.39764 | T90: 570.98431 | U90: 582.62622 | V90: 594.32861 | W90: 605.90723 | X90: 618.32935 | Y90: 630.57855 | Z90: 642.19775 | AA90: 653.68176 | AB90: 665.05255 | AC90: 678.04999 | AD90: 691.81976 | AE90: 705.1648 | AF90: 718.4154 | AG90: 0.019
A91: Regional Jets | B91: Air Travel: Seat Miles Demanded: U.S.: Regional Jets: Alternative Transportation | C91: AEO.2025.ALTTRNP.ECI_SMD_AIRT_REGJ_NA_NA_USA_BLNMLS.A | D91: billion miles | F91: 85.160713 | G91: 85.992302 | H91: 88.040932 | I91: 89.935371 | J91: 91.46978 | K91: 93.14238 | L91: 94.655029 | M91: 95.873886 | N91: 97.310722 | O91: 98.857651 | P91: 100.33663 | Q91: 101.98189 | R91: 103.65834 | S91: 105.44935 | T91: 107.38528 | U91: 109.32124 | V91: 111.2537 | W91: 113.14408 | X91: 115.20652 | Y91: 117.21529 | Z91: 119.06986 | AA91: 120.8797 | AB91: 122.64983 | AC91: 124.75993 | AD91: 127.02118 | AE91: 129.17188 | AF91: 131.28401 | AG91: 0.017
